Workbook
Name TAB_AFP: TASAS!$B$5:$I$13
Name TAB_AFP: #REF!

Sheet TASAS
E1: https://www.sbs.gob.pe/app/spp/empleadores/comisiones_spp/Paginas/comision_prima.aspx
A2: Al mes de devengue 2020/06
A3: ITEM | B3: AFP | C3: ONP | D3: COMISION MIXTA | F3: PRIMA SEGURO | G3: APORTE OBLIGATORIO | H3: Remuneración Máxima Asegurable | I3: TOTAL
D4: COMISION SOBRE LA REMUNERACION (FLUJO ) | E4: COMISION ANUAL SOBRE SALDO
A5: 1 | B5: HABITAT MIXTA | D5: 0.0038 | E5: 0.0125 | F5: 0.0174 | G5: 0.1 | H5: 9665.33 | I5: =SUM(D5,F5,G5) -> 0.1212
A6: =A5+1 -> 2 | B6: HABITAT SUELDO | D6: 0.0147 | E6: 0.0023 | F6: 0.0174 | G6: 0.1 | I6: =SUM(D6,F6,G6) -> 0.1321
A7: =A6+1 -> 3 | B7: INTEGRA MIXTA | D7: 0.0056 | E7: 0.012 | F7: 0.0174 | G7: 0.1 | H7: 9665.33 | I7: =SUM(D7,F7,G7) -> 0.123
A8: =A7+1 -> 4 | B8: INTEGRA SUELDO | D8: 0.0155 | F8: 0.0174 | G8: 0.1 | I8: =SUM(D8,F8,G8) -> 0.1329
A9: =A8+1 -> 5 | B9: PRIMA MIXTA | D9: 0.0018 | E9: 0.0125 | F9: 0.0174 | G9: 0.1 | H9: 9665.33 | I9: =SUM(D9,F9,G9) -> 0.1192
A10: =A9+1 -> 6 | B10: PRIMA SUELDO | D10: 0.016 | F10: 0.0174 | G10: 0.1 | I10: =SUM(D10,F10,G10) -> 0.1334
A11: =A10+1 -> 7 | B11: PROFUTURO MIXTA | D11: 0.0067 | E11: 0.012 | F11: 0.0174 | G11: 0.1 | H11: 9665.33 | I11: =SUM(D11,F11,G11) -> 0.1241
A12: =A11+1 -> 8 | B12: PROFUTURO SUELDO | D12: 0.0169 | F12: 0.0174 | G12: 0.1 | I12: =SUM(D12,F12,G12) -> 0.1343
A13: =A12+1 -> 9 | B13: ONP | C13: 0.13 | G13: 0.13 | H13: 0 | I13: =SUM(D13,F13,G13) -> 0.13
B16: Al mes de devengue 2020-05 1/
B17: AFP | C17: COMISIÓN FIJA 2/ | D17: COMISIÓN SOBRE FLUJO | E17: COMISIÓN MIXTA5/ | G17: PRIMA DE SEGUROS (%) 4/ | H17: APORTE OBLIGATORIO AL FONDO DE PENSIONES | I17: REMUNERACIÓN MÁXIMA ASEGURABLE | K17: PRIMA SUELDO
K18: PROFUTURO MIXTA
E19: COMISIÓN | F19: COMISIÓN | K19: PROFUTURO MIXTA
D20: (% Remuneración Bruta Mensual) | E20: SOBRE FLUJO | F20: ANUAL SOBRE | G20: (% Remuneración Bruta Mensual) | H20: (% Remuneración Bruta Mensual) | K20: PROFUTURO SUELDO
E21: (% Remuneración Bruta Mensual) | F21: SALDO 3/ | K21: INTEGRA SUELDO
B22: HABITAT | D22: 0.0147 | E22: 0.0038 | F22: 0.0125 | G22: 0.0135 | H22: 0.1 | I22: 9788.95 | K22: PROFUTURO SUELDO
B23: INTEGRA | D23: 0.0155 | E23: 0 | F23: 0.0082 | G23: 0.0135 | H23: 0.1 | I23: 9788.95
B24: PRIMA | D24: 0.016 | E24: 0.0018 | F24: 0.0125 | G24: 0.0135 | H24: 0.1 | I24: 9788.95
B25: PROFUTURO | D25: 0.0169 | E25: 0.0067 | F25: 0.012 | G25: 0.0135 | H25: 0.1 | I25: 9788.95

Sheet quinta categoria
C3: Excel para calcular el descuento por el impuesto a la Renta de quinta categoría
C5: Proyección de ingresos brutos anuales | F5: S/. | G5: 71238.46
C6: Monto de 7 UIT descontable | F6: S/. | G6: =+G18*7 -> 38500
C7: Renta neta gravable de impuesto de quinta | F7: S/. | G7: =+IF((G5-G6)<0,0,(G5-G6)) -> 32738.46
C9: Escala UIT | D9: Tasas | E9: Máximos en S/. | F9: Monto afecto en S/. | G9: Impuesto en S/.
C10: Hasta 5 UIT | D10: 0.08 | E10: =5*G18 -> 27500 | F10: =+IF(G5<=(G6),0,(IF(G7<=E10,G7,E10))) -> 27500 | G10: =+F10*D10 -> 2200
C11: Mas de 5 UIT hasta 20 UIT | D11: 0.14 | E11: =20*G18 -> 110000 | F11: =+IF((G7-F10)<=0,0,(IF(G7<=E11,G7-F10,E11-F10))) -> 5238.46 | G11: =+F11*D11 -> 733.3844
C12: Mas de 20 UIT hasta 35 UIT | D12: 0.17 | E12: =35*G18 -> 192500 | F12: =+IF((G7-(F10+F11))<=0,0,(IF(G7<=E12,G7-(F10+F11),E12-F11-F10))) -> 0 | G12: =+F12*D12 -> 0
C13: Mas de 35 UIT hasta 45 UIT | D13: 0.2 | E13: =45*G18 -> 247500 | F13: =+IF((G7-(F10+F11+F12))<=0,0,(IF(G7<=E13,G7-(F10+F11+F12),E13-F12-F11-F10))) -> 0 | G13: =+F13*D13 -> 0
C14: Mas de 45 UIT | D14: 0.3 | E14: =+CONCATENATE("> ",E13) -> > 247500 | F14: =+IF(G7>E13,G7-E13,0) -> 0 | G14: =+F14*D14 -> 0
C15: Impuesto a la Renta a pagar por el año en curso | F15: =+F14+F13+F10 -> 27500 | G15: =+SUM(G10:G14) -> 2933.3844
C17: Retención Mensual aproximada que se realiza al trabajador | G17: =+G15/12 -> 244.4487
C18: Unidad Impositiva Tributaria (UIT) del año en curso | G18: 5500

Sheet Tabla
J2: COMISIÓN MIXTA (5)
F3: % DCTO POR REMUNER | G3: APORTE FONDO DE PENSIONES | H3: PRIMA DE SEGURO (4) | I3: COMISION SOBRE REMUNERACIÓN MENSUAL | J3: COMISION SOBRE REMUNERACIÓN FLUJO(% remuneración bruta mensual) | K3: COMISION ANUAL SOBRE SALDO (3) | L3: % DCTO POR COMISIÓN MIXTA | M3: % DCTO POR SALDO
C4: REG NORMAL | D4: =+B6 -> 11238.83 | E4: INT | F4: =+G4+H4+I4 -> 0.1329 | G4: 0.1 | H4: 0.0174 | I4: 0.0155 | J4: 0 | K4: 0.0079 | L4: =+G4+H4+J4 -> 0.1174 | M4: =+G4+H4+K4 -> 0.1253
C5: REG NORMAL | E5: PRI | F5: =+G5+H5+I5 -> 0.1334 | G5: 0.1 | H5: 0.0174 | I5: 0.016 | J5: 0.0018 | K5: 0.0125 | L5: =+G5+H5+J5 -> 0.1192 | M5: =+G5+H5+K5 -> 0.1299
B6: 11238.83 | C6: REG NORMAL | E6: PRO | F6: =+G6+H6+I6 -> 0.1343 | G6: 0.1 | H6: 0.0174 | I6: 0.0169 | J6: 0.0028 | K6: 0.012 | L6: =+G6+H6+J6 -> 0.1202 | M6: =+G6+H6+K6 -> 0.1294
B7: oct - dic 2022} | C7: REG NORMAL | E7: HAB | F7: =+G7+H7+I7 -> 0.1321 | G7: 0.1 | H7: 0.0174 | I7: 0.0147 | J7: 0.0023 | K7: 0.0125 | L7: =+G7+H7+J7 -> 0.1197 | M7: =+G7+H7+K7 -> 0.1299
B8: Monto limite gtos. Sepelio
B9: 4554.41
B10: ASIGNACIÓN FAMILIAR | D10: RMV | E10: % | F10: TOTAL
D11: =930+95 -> 1025 | E11: 0.1 | F11: =+D11*E11 -> 102.5

Sheet 1RA QUINCENA JUNIO 26
B1: LEYENDA | AJ1: 1RA QUINCENA JUNIO 2026
B2: CESADOS | AY2: HASTA 5 UIT | AZ2: 0.08
B3: VACACIONES | C3: 30 | AY3: DE 5 A 20 UIT | AZ3: 0.14
B4: COLECTORA | C4: 46174 | Q4: DIAS LABORADOS | AY4: DE 20 A 35 UIT | AZ4: 0.17
B5: LICENCIA | AY5: DE 35 A 45 UIT | AZ5: 0.2
A6: 1 | B6: =+A6+1 -> 2 | C6: =+B6+1 -> 3 | D6: =+C6+1 -> 4 | E6: =+D6+1 -> 5 | F6: =+E6+1 -> 6 | G6: =+F6+1 -> 7 | H6: =+G6+1 -> 8 | I6: =+H6+1 -> 9 | ... BJ6: =+BI6+1 -> 62
A7: N° | B7: APELLIDO Y NOMBRES | C7: FECHA DE NACIM. | D7: DNI | E7: FECHA INGRESO | F7: FECHA DE CESE | G7: GENERO | H7: TIPO DE CONTRATO | I7: CATEGORIA OCUPACIONAL | J7: ONP | K7: SCTR | L7: SENATI | M7: COD AFP | N7: AREA | O7: CARGO | P7: SUELDO BASICO | Q7: ASIG FAM | R7: MOVILIDAD | S7: POR FUERA | T7: TOTAL MENSUAL | U7: DIAS TRABAJADOS | V7: DM | W7: DIAS FALTO | Y7: TARDANZAS | AA7: PAGO | AB7: LICENCIA | AC7: SUBSIDIO | AD7: LIQ VACACIONES | AG7: INCENTIVOS | AH7: LICENCIA HIJO ENFERMO | AJ7: REMUNERACIÓN QUINCENAL | AK7: SABADOS | AM7: HORAS EXTRAS | AO7: DOMINGOS Y FERIADOS | AQ7: INCENTIVO POR PRODUCION | AR7: TOTAL MOVIL QUINCENAL | AS7: SISTEMA DE PENSIONES | AV7: ONP | AW7: AFP PRIMA | AZ7: DSCTO AFP | BA7: RETENCION AFP/ONP | BB7: RTA. 5TA CATEG | BC7: NETO A PAGAR | BD7: ESSALUD | BE7: SCTR PENSIÓN | BF7: SCTR SALUD | BG7: SVL | BH7: ADELANTOS/PRESTA | BI7: REINTEGRO | BJ7: A PAGAR 15/06/26
W8: CANT | X8: DESCUENTO | Y8: CANT | Z8: DESCUENTO | AA8: GRAT | AD8: DIAS | AE8: MONTO | AF8: FINAL | AH8: CANT | AI8: DESCUENTO | AK8: CANTIDA | AL8: MONTO | AM8: CANT. | AN8: MONTO | AO8: CANTIDA | AP8: MONTO | AT8: COM | AV8: 0.13 | AW8: 0.1 | AX8: COMISION | AY8: PRIMA | BD8: 0.09 | BE8: 0.0214 | BG8: DL 688
A10: 1 | B10: CISNEROS PACOTAYPE KEVIN | D10: 71246290 | E10: 46143 | G10: MASCULINO | H10: A PLAZO FIJO | I10: EMPLEADO | J10: NO | K10: SI | L10: NO | N10: PRODUCCION | O10: INGENIERO | P10: 4500 | T10: =P10+Q10+R10+S10 -> 4500 | U10: ='HOJA RXH'!AH6 -> 8 | W10: ='HOJA RXH'!Z6 -> 7 | X10: =((P10+Q10)/$C$3)*W10 -> 1050 | Y10: ='HOJA RXH'!AD6 -> 0 | Z10: =(T10/30/8/60*Y10) -> 0 | AC10: =(P10/30)*V10 -> 0 | AH10: ='HOJA RXH'!V6 -> 0 | AJ10: =(((P10+Q10)/30)*U10)-Z10+AA10+AB10+AC10+AF10+AG10+AI10 -> 1200 | AK10: ='HOJA RXH'!J6 -> 0 | AL10: =T10/30*AK10 -> 0 | AM10: ='HOJA RXH'!F6 -> 5 | AN10: =T10/30/10*AM10 -> 75 | AO10: ='HOJA RXH'!N6 -> 0 | AP10: =T10/30*AO10 -> 0 | AQ10: 0 | AR10: =((R10/$C$3)*(U10-V10))+AL10+AP10+AN10+AQ10 -> 75 | AS10: INTEGRA MIXTA | AT10: 0 | AU10: 0.0137 | AV10: =IF(AS10="ONP",VLOOKUP(AS10,TASAS!TAB_AFP,8,0)*AJ10,0) -> 0 | AW10: =IF(AS10<>"ONP",AJ10*$AW$8,0) -> 120 | AX10: =IF(AS10<>"ONP",AJ10*AT10,0) -> 0 | AY10: =IF(AU10<>"ONP",AJ10*AU10,0) -> 16.44 | AZ10: =+AX10+AY10+AW10 -> 136.44 | BA10: =+AZ10+AV10 -> 136.44 | BC10: =AJ10+AR10-BA10-BB10 -> 1138.56 | BD10: =ROUND(AJ10*$BD$8,2) -> 108 | BE10: =IF(K10="SI",AJ10*2.14%,0) -> 25.68 | BG10: =+P10*0.54% -> 24.3 | BJ10: =BC10-BH10+BI10 -> 1138.56
A11: 2 | B11: CISNEROS SUMA, ANDRES JUAN | D11: 9594305 | E11: 45413 | G11: MASCULINO | H11: MYPE INDETERM | I11: EMPLEADO | J11: NO | K11: SI | L11: NO | M11: 554671ACSNA9 | N11: ADMINISTRACIÓN | O11: GERENTE | P11: 2530 | Q11: 113 | R11: 750 | T11: =P11+Q11+R11+S11 -> 3393 | U11: ='HOJA RXH'!AH7 -> 15 | W11: ='HOJA RXH'!Z7 -> 0 | X11: =((P11+Q11)/$C$3)*W11 -> 0 | Y11: ='HOJA RXH'!AD7 -> 60 | Z11: =(T11/30/8/60*Y11) -> 14.1375 | AC11: =(P11/30)*V11 -> 0 | AH11: ='HOJA RXH'!V7 -> 0 | AJ11: =(((P11+Q11)/30)*U11)-Z11+AA11+AB11+AC11+AF11+AG11+AI11 -> 1307.3625 | AK11: ='HOJA RXH'!J7 -> 0 | AL11: =T11/30*AK11 -> 0 | AM11: ='HOJA RXH'!F7 -> 0 | AN11: =T11/30/10*AM11 -> 0 | AO11: ='HOJA RXH'!N7 -> 0 | AP11: =T11/30*AO11 -> 0 | AQ11: 0 | AR11: =((R11/$C$3)*(U11-V11))+AL11+AP11+AN11+AQ11 -> 375 | AS11: PRIMA MIXTA | AT11: 0 | AU11: 0.0137 | AV11: =IF(AS11="ONP",VLOOKUP(AS11,TASAS!TAB_AFP,8,0)*AJ11,0) -> 0 | AW11: =IF(AS11<>"ONP",AJ11*$AW$8,0) -> 130.73625 | AX11: =IF(AS11<>"ONP",AJ11*AT11,0) -> 0 | AY11: =IF(AU11<>"ONP",AJ11*AU11,0) -> 17.910866 | AZ11: =+AX11+AY11+AW11 -> 148.64712 | BA11: =+AZ11+AV11 -> 148.64712 | BC11: =AJ11+AR11-BA11-BB11 -> 1533.7154 | BD11: =ROUND(AJ11*$BD$8,2) -> 117.66 | BE11: =IF(K11="SI",AJ11*2.14%,0) -> 27.977558 | BG11: =+P11*0.54% -> 13.662 | BJ11: =BC11-BH11+BI11 -> 1533.7154
A12: 3 | B12: CISNEROS SUMA, EDGAR | C12: 28322 | D12: 28316078 | E12: 43983 | G12: MASCULINO | H12: MYPE INDETERM | I12: EMPLEADO | J12: NO | K12: SI | L12: NO | M12: 583201ECSNA0 | N12: PRODUCCION | O12: SUPERVISOR DE PRODUCCION | P12: 4000 | Q12: 113 | R12: 1000 | T12: =P12+Q12+R12+S12 -> 5113 | U12: ='HOJA RXH'!AH8 -> 15 | W12: ='HOJA RXH'!Z8 -> 0 | X12: =((P12+Q12)/$C$3)*W12 -> 0 | Y12: ='HOJA RXH'!AD8 -> 0 | Z12: =(T12/30/8/60*Y12) -> 0 | AH12: ='HOJA RXH'!V8 -> 0 | AJ12: =(((P12+Q12)/30)*U12)-Z12+AA12+AB12+AC12+AF12+AG12+AI12 -> 2056.5 | AK12: ='HOJA RXH'!J8 -> 2 | AL12: =T12/30*AK12 -> 340.86667 | AM12: ='HOJA RXH'!F8 -> 0 | AN12: =T12/30/10*AM12 -> 0 | AO12: ='HOJA RXH'!N8 -> 0 | AP12: =T12/30*AO12 -> 0 | AQ12: 0 | AR12: =((R12/$C$3)*(U12-V12))+AL12+AP12+AN12+AQ12 -> 840.86667 | AS12: PROFUTURO FLUJO | AT12: 0.0169 | AU12: 0.0137 | AV12: =IF(AS12="ONP",VLOOKUP(AS12,TASAS!TAB_AFP,8,0)*AJ12,0) -> 0 | AW12: =IF(AS12<>"ONP",AJ12*$AW$8,0) -> 205.65 | AX12: =IF(AS12<>"ONP",AJ12*AT12,0) -> 34.75485 | AY12: =IF(AU12<>"ONP",AJ12*AU12,0) -> 28.17405 | AZ12: =+AX12+AY12+AW12 -> 268.5789 | BA12: =+AZ12+AV12 -> 268.5789 | BC12: =AJ12+AR12-BA12-BB12 -> 2628.7878 | BD12: =ROUND(AJ12*$BD$8,2) -> 185.09 | BE12: =IF(K12="SI",AJ12*2.14%,0) -> 44.0091 | BG12: =+P12*0.54% -> 21.6 | BJ12: =BC12-BH12+BI12 -> 2628.7878
A13: 4 | B13: CORI ADAN RUTBEL | C13: 22411 | D13: 6596301 | E13: 40269 | G13: MASCULINO | H13: INDETERMINADO | I13: OBRERO | J13: NO | K13: SI | L13: NO | M13: 224091RCAIN8 | N13: AUTOPARTES | O13: TORNERO | P13: 1130 | Q13: 0 | R13: 600 | T13: =P13+Q13+R13+S13 -> 1730 | U13: ='HOJA RXH'!AH9 -> 14 | W13: ='HOJA RXH'!Z9 -> 1 | X13: =((P13+Q13)/$C$3)*W13 -> 37.666667 | Y13: ='HOJA RXH'!AD9 -> 171 | Z13: =(T13/30/8/60*Y13) -> 20.54375 | AH13: ='HOJA RXH'!V9 -> 0 | AJ13: =(((P13+Q13)/30)*U13)-Z13+AA13+AB13+AC13+AF13+AG13+AI13 -> 506.78958 | AK13: ='HOJA RXH'!J9 -> 0 | AL13: =T13/30*AK13 -> 0 | AM13: ='HOJA RXH'!F9 -> 0 | AN13: =T13/30/10*AM13 -> 0 | AO13: ='HOJA RXH'!N9 -> 0 | AP13: =T13/30*AO13 -> 0 | AQ13: 0 | AR13: =((R13/$C$3)*(U13-V13))+AL13+AP13+AN13+AQ13 -> 280 | AS13: PRIMA FLUJO | AT13: 0.016 | AU13: 0.0137 | AV13: =IF(AS13="ONP",VLOOKUP(AS13,TASAS!TAB_AFP,8,0)*AJ13,0) -> 0 | AW13: =IF(AS13<>"ONP",AJ13*$AW$8,0) -> 50.678958 | AX13: =IF(AS13<>"ONP",AJ13*AT13,0) -> 8.1086333 | AY13: =IF(AU13<>"ONP",AJ13*AU13,0) -> 6.9430173 | AZ13: =+AX13+AY13+AW13 -> 65.730609 | BA13: =+AZ13+AV13 -> 65.730609 | BC13: =AJ13+AR13-BA13-BB13 -> 721.05897 | BD13: =ROUND(AJ13*$BD$8,2) -> 45.61 | BE13: 44.99 | BG13: =+P13*0.54% -> 6.102 | BJ13: =BC13-BH13+BI13 -> 721.05897
A14: 5 | B14: GAVIDIA PEREIRA JAVIER | C14: 13/03/1969 | D14: 7717984 | E14: 46143 | G14: MASCULINO | H14: A PLAZO FIJO | I14: EMPLEADO | J14: NO | K14: SI | L14: NO | N14: ADMINISTRACIÓN | O14: ADMINISTRADOR GENERAL | P14: 6000 | T14: =P14+Q14+R14+S14 -> 6000 | U14: ='HOJA RXH'!AH10 -> 15 | W14: ='HOJA RXH'!Z10 -> 0 | X14: =((P14+Q14)/$C$3)*W14 -> 0 | Y14: ='HOJA RXH'!AD10 -> 0 | Z14: =(T14/30/8/60*Y14) -> 0 | AH14: ='HOJA RXH'!V10 -> 0 | AJ14: =(((P14+Q14)/30)*U14)-Z14+AA14+AB14+AC14+AF14+AG14+AI14 -> 3000 | AK14: ='HOJA RXH'!J10 -> 0 | AL14: =T14/30*AK14 -> 0 | AM14: ='HOJA RXH'!F10 -> 0 | AN14: =T14/30/10*AM14 -> 0 | AO14: ='HOJA RXH'!N10 -> 0 | AP14: =T14/30*AO14 -> 0 | AQ14: 0 | AR14: =((R14/$C$3)*(U14-V14))+AL14+AP14+AN14+AQ14 -> 0 | AS14: 0 | AV14: =IF(AS14="ONP",VLOOKUP(AS14,TASAS!TAB_AFP,8,0)*AJ14,0) -> 0 | AW14: 0 | AX14: =IF(AS14<>"ONP",AJ14*AT14,0) -> 0 | AY14: =IF(AU14<>"ONP",AJ14*AU14,0) -> 0 | AZ14: =+AX14+AY14+AW14 -> 0 | BA14: =+AZ14+AV14 -> 0 | BC14: =AJ14+AR14-BA14-BB14 -> 3000 | BD14: =ROUND(AJ14*$BD$8,2) -> 270 | BE14: =IF(K14="SI",AJ14*2.14%,0) -> 64.2 | BG14: =+P14*0.54% -> 32.4 | BJ14: =BC14-BH14+BI14 -> 3000
A15: 6 | B15: HIDALGO MOYA, LIZBETH SONIA | C15: 30319 | D15: 41705366 | E15: 40210 | G15: FEMENINO | H15: INDETERMINADO | I15: EMPLEADO | J15: SI | K15: NO | L15: NO | M15: 603170LHMAA7 | N15: LOGISTICA | O15: JEFA DE LOGISTICA | P15: =2000+1000 -> 3000 | Q15: 113 | R15: 1000 | T15: =P15+Q15+R15+S15 -> 4113 | U15: ='HOJA RXH'!AH11 -> 15 | W15: ='HOJA RXH'!Z11 -> 0 | X15: =((P15+Q15)/$C$3)*W15 -> 0 | Y15: ='HOJA RXH'!AD11 -> 0 | Z15: =(T15/30/8/60*Y15) -> 0 | AH15: ='HOJA RXH'!V11 -> 0 | AJ15: =(((P15+Q15)/30)*U15)-Z15+AA15+AB15+AC15+AF15+AG15+AI15 -> 1556.5 | AK15: ='HOJA RXH'!J11 -> 0 | AL15: =T15/30*AK15 -> 0 | AM15: ='HOJA RXH'!F11 -> 0 | AN15: =T15/30/10*AM15 -> 0 | AO15: ='HOJA RXH'!N11 -> 0 | AP15: =T15/30*AO15 -> 0 | AQ15: 0 | AR15: =((R15/$C$3)*(U15-V15))+AL15+AP15+AN15+AQ15 -> 500 | AS15: PROFUTURO MIXTA | AT15: 0 | AU15: 0.0137 | AV15: =IF(AS15="ONP",VLOOKUP(AS15,TASAS!TAB_AFP,8,0)*AJ15,0) -> 0 | AW15: =IF(AS15<>"ONP",AJ15*$AW$8,0) -> 155.65 | AX15: =IF(AS15<>"ONP",AJ15*AT15,0) -> 0 | AY15: =IF(AU15<>"ONP",AJ15*AU15,0) -> 21.32405 | AZ15: =+AX15+AY15+AW15 -> 176.97405 | BA15: =+AZ15+AV15 -> 176.97405 | BC15: =AJ15+AR15-BA15-BB15 -> 1879.5259 | BD15: =ROUND(AJ15*$BD$8,2) -> 140.09 | BE15: =IF(K15="SI",AJ15*2.14%,0) -> 0 | BG15: =+P15*0.54% -> 16.2 | BJ15: =BC15-BH15+BI15 -> 1879.5259
A16: 7 | B16: LAGOS HUAMANI NIDIA | C16: 35114 | D16: 76339850 | E16: 45152 | G16: FEMENINO | H16: MYPE CONTRAT | I16: EMPLEADO | J16: NO | K16: NO | L16: NO | M16: 651120NLHOM8 | N16: CONTABILIDAD | O16: AUXILIAR | P16: 1200 | R16: =300+300 -> 600 | T16: =P16+Q16+R16+S16 -> 1800 | U16: ='HOJA RXH'!AH12 -> 15 | W16: ='HOJA RXH'!Z12 -> 0 | X16: =((P16+Q16)/$C$3)*W16 -> 0 | Y16: ='HOJA RXH'!AD12 -> 839 | Z16: =(T16/30/8/60*Y16) -> 104.875 | AH16: ='HOJA RXH'!V12 -> 0 | AJ16: =(((P16+Q16)/30)*U16)-Z16+AA16+AB16+AC16+AF16+AG16+AI16 -> 495.125 | AK16: ='HOJA RXH'!J12 -> 0 | AL16: =T16/30*AK16 -> 0 | AM16: ='HOJA RXH'!F12 -> 0 | AN16: =T16/30/10*AM16 -> 0 | AO16: ='HOJA RXH'!N12 -> 0 | AP16: =T16/30*AO16 -> 0 | AQ16: 0 | AR16: =((R16/$C$3)*(U16-V16))+AL16+AP16+AN16+AQ16 -> 300 | AS16: INTEGRA MIXTA | AT16: 0 | AU16: 0.0137 | AV16: =IF(AS16="ONP",VLOOKUP(AS16,TASAS!TAB_AFP,8,0)*AJ16,0) -> 0 | AW16: =IF(AS16<>"ONP",AJ16*$AW$8,0) -> 49.5125 | AX16: =IF(AS16<>"ONP",AJ16*AT16,0) -> 0 | AY16: =IF(AU16<>"ONP",AJ16*AU16,0) -> 6.7832125 | AZ16: =+AX16+AY16+AW16 -> 56.295712 | BA16: =+AZ16+AV16 -> 56.295712 | BC16: =AJ16+AR16-BA16-BB16 -> 738.82929 | BD16: =ROUND(AJ16*$BD$8,2) -> 44.56 | BE16: =IF(K16="SI",AJ16*2.14%,0) -> 0 | BG16: =+P16*0.54% -> 6.48 | BJ16: =BC16-BH16+BI16 -> 738.82929
A17: 8 | B17: MERCADO SANCHEZ NORMA AURELIA | C17: 29693 | D17: 40878166 | E17: 38534 | G17: FEMENINO | H17: INDETERMINADO | I17: EMPLEADO | J17: NO | K17: NO | L17: NO | M17: 596910NMSCC9 | N17: VENTAS | O17: ASISTENTE DE VENTAS | P17: =1425+175+300 -> 1900 | Q17: 113 | T17: =P17+Q17+R17+S17 -> 2013 | U17: ='HOJA RXH'!AH13 -> 15 | W17: ='HOJA RXH'!Z13 -> 0 | X17: =((P17+Q17)/$C$3)*W17 -> 0 | Y17: ='HOJA RXH'!AD13 -> 663 | Z17: =(T17/30/8/60*Y17) -> 92.681875 | AH17: ='HOJA RXH'!V13 -> 0 | AJ17: =(((P17+Q17)/30)*U17)-Z17+AA17+AB17+AC17+AF17+AG17+AI17 -> 913.81812 | AK17: ='HOJA RXH'!J13 -> 0 | AL17: =T17/30*AK17 -> 0 | AM17: ='HOJA RXH'!F13 -> 1 | AN17: =T17/30/10*AM17 -> 6.71 | AO17: ='HOJA RXH'!N13 -> 0 | AP17: =T17/30*AO17 -> 0 | AQ17: 0 | AR17: =((R17/$C$3)*(U17-V17))+AL17+AP17+AN17+AQ17 -> 6.71 | AS17: PROFUTURO MIXTA | AT17: 0 | AU17: 0.0137 | AV17: =IF(AS17="ONP",VLOOKUP(AS17,TASAS!TAB_AFP,8,0)*AJ17,0) -> 0 | AW17: =IF(AS17<>"ONP",AJ17*$AW$8,0) -> 91.381812 | AX17: =IF(AS17<>"ONP",AJ17*AT17,0) -> 0 | AY17: =IF(AU17<>"ONP",AJ17*AU17,0) -> 12.519308 | AZ17: =+AX17+AY17+AW17 -> 103.90112 | BA17: =+AZ17+AV17 -> 103.90112 | BC17: =AJ17+AR17-BA17-BB17 -> 816.627 | BD17: =ROUND(AJ17*$BD$8,2) -> 82.24 | BE17: =IF(K17="SI",AJ17*2.14%,0) -> 0 | BG17: =+P17*0.54% -> 10.26 | BJ17: =BC17-BH17+BI17 -> 816.627
A18: 9 | B18: MONTENEGRO OBLITAS GROVER MANUEL | C18: 30536 | D18: 41974116 | E18: 43862 | G18: MASCULINO | H18: INDETERMINADO | I18: OBRERO | J18: SI | K18: SI | L18: NO | N18: CORTE DOBLEZ | O18: DOBLADOR | P18: 1130 | Q18: 113 | R18: =600+200+200 -> 1000 | T18: =P18+Q18+R18+S18 -> 2243 | U18: ='HOJA RXH'!AH14 -> 15 | W18: ='HOJA RXH'!Z14 -> 0 | X18: =((P18+Q18)/$C$3)*W18 -> 0 | Y18: ='HOJA RXH'!AD14 -> 22 | Z18: =(T18/30/8/60*Y18) -> 3.4268056 | AH18: ='HOJA RXH'!V14 -> 0 | AJ18: =(((P18+Q18)/30)*U18)-Z18+AA18+AB18+AC18+AF18+AG18+AI18 -> 618.07319 | AK18: ='HOJA RXH'!J14 -> 2 | AL18: =T18/30*AK18 -> 149.53333 | AM18: ='HOJA RXH'!F14 -> 10 | AN18: =T18/30/10*AM18 -> 74.766667 | AO18: ='HOJA RXH'!N14 -> 0 | AP18: =T18/30*AO18 -> 0 | AQ18: 0 | AR18: =((R18/$C$3)*(U18-V18))+AL18+AP18+AN18+AQ18 -> 724.3 | AS18: ONP | AV18: =IF(AS18="ONP",VLOOKUP(AS18,TASAS!TAB_AFP,8,0)*AJ18,0) -> 80.349515 | AW18: =IF(AS18<>"ONP",AJ18*$AW$8,0) -> 0 | AX18: =IF(AS18<>"ONP",AJ18*AT18,0) -> 0 | AY18: =IF(AU18<>"ONP",AJ18*AU18,0) -> 0 | AZ18: =+AX18+AY18+AW18 -> 0 | BA18: =+AZ18+AV18 -> 80.349515 | BC18: =AJ18+AR18-BA18-BB18 -> 1262.0237 | BD18: =ROUND(AJ18*$BD$8,2) -> 55.63 | BE18: =IF(K18="SI",AJ18*2.14%,0) -> 13.226766 | BG18: =+P18*0.54% -> 6.102 | BH18: 150 | BJ18: =BC18-BH18+BI18 -> 1112.0237 | BK18: 450 PRESTAMO/ADELANTO DE SUELDO
A19: 10 | B19: PEÑALOZA CAMPOS, FRANK KEVHIN | C19: 30680 | D19: 42137816 | E19: 40210 | G19: MASCULINO | H19: INDETERMINADO | I19: OBRERO | J19: NO | K19: SI | L19: NO | M19: 606781FPCAP2 | N19: ESTRUCTURA | O19: ARMADOR | P19: 1500 | Q19: 113 | R19: 1500 | T19: =P19+Q19+R19+S19 -> 3113 | U19: ='HOJA RXH'!AH15 -> 15 | W19: ='HOJA RXH'!Z15 -> 0 | X19: =((P19+Q19)/$C$3)*W19 -> 0 | Y19: ='HOJA RXH'!AD15 -> 0 | Z19: =(T19/30/8/60*Y19) -> 0 | AH19: ='HOJA RXH'!V15 -> 0 | AJ19: =(((P19+Q19)/30)*U19)-Z19+AA19+AB19+AC19+AF19+AG19+AI19 -> 806.5 | AK19: ='HOJA RXH'!J15 -> 2 | AL19: =T19/30*AK19 -> 207.53333 | AM19: ='HOJA RXH'!F15 -> 3 | AN19: =T19/30/10*AM19 -> 31.13 | AO19: ='HOJA RXH'!N15 -> 0 | AP19: =T19/30*AO19 -> 0 | AQ19: 0 | AR19: =((R19/$C$3)*(U19-V19))+AL19+AP19+AN19+AQ19 -> 988.66333 | AS19: PROFUTURO FLUJO | AT19: 0.0169 | AU19: 0.0137 | AV19: =IF(AS19="ONP",VLOOKUP(AS19,TASAS!TAB_AFP,8,0)*AJ19,0) -> 0 | AW19: =IF(AS19<>"ONP",AJ19*$AW$8,0) -> 80.65 | AX19: =IF(AS19<>"ONP",AJ19*AT19,0) -> 13.62985 | AY19: =IF(AU19<>"ONP",AJ19*AU19,0) -> 11.04905 | AZ19: =+AX19+AY19+AW19 -> 105.3289 | BA19: =+AZ19+AV19 -> 105.3289 | BC19: =AJ19+AR19-BA19-BB19 -> 1689.8344 | BD19: =ROUND(AJ19*$BD$8,2) -> 72.59 | BE19: =IF(K19="SI",AJ19*2.14%,0) -> 17.2591 | BG19: =+P19*0.54% -> 8.1 | BJ19: =BC19-BH19+BI19 -> 1689.8344
A20: 11 | B20: SANCHEZ MUEDAS FIDEL | C20: 25284 | D20: 19898777 | E20: 40788 | G20: MASCULINO | H20: INDETERMINADO | I20: EMPLEADO | J20: NO | K20: SI | L20: NO | M20: 252821FSMCD6 | N20: ALMACEN | O20: ALMACENERO | P20: 1200 | Q20: 0 | R20: 300 | T20: =P20+Q20+R20+S20 -> 1500 | U20: ='HOJA RXH'!AH16 -> 15 | W20: ='HOJA RXH'!Z16 -> 0 | X20: =((P20+Q20)/$C$3)*W20 -> 0 | Y20: ='HOJA RXH'!AD16 -> 55 | Z20: =(T20/30/8/60*Y20) -> 5.7291667 | AH20: ='HOJA RXH'!V16 -> 0 | AJ20: =(((P20+Q20)/30)*U20)-Z20+AA20+AB20+AC20+AF20+AG20+AI20 -> 594.27083 | AK20: ='HOJA RXH'!J16 -> 0 | AL20: =T20/30*AK20 -> 0 | AM20: ='HOJA RXH'!F16 -> 1 | AN20: =T20/30/10*AM20 -> 5 | AO20: ='HOJA RXH'!N16 -> 0 | AP20: =T20/30*AO20 -> 0 | AQ20: 0 | AR20: =((R20/$C$3)*(U20-V20))+AL20+AP20+AN20+AQ20 -> 155 | AS20: INTEGRA FLUJO | AT20: 0.0155 | AU20: 0.0137 | AV20: =IF(AS20="ONP",VLOOKUP(AS20,TASAS!TAB_AFP,8,0)*AJ20,0) -> 0 | AW20: =IF(AS20<>"ONP",AJ20*$AW$8,0) -> 59.427083 | AX20: =IF(AS20<>"ONP",AJ20*AT20,0) -> 9.2111979 | AY20: =IF(AU20<>"ONP",AJ20*AU20,0) -> 8.1415104 | AZ20: =+AX20+AY20+AW20 -> 76.779792 | BA20: =+AZ20+AV20 -> 76.779792 | BC20: =AJ20+AR20-BA20-BB20 -> 672.49104 | BD20: =ROUND(AJ20*$BD$8,2) -> 53.48 | BE20: =IF(K20="SI",AJ20*2.14%,0) -> 12.717396 | BG20: =+P20*0.54% -> 6.48 | BJ20: =BC20-BH20+BI20 -> 672.49104
A21: 12 | B21: SEVERICHE CARLOS ANGELICA JESUS | C21: 29010 | D21: 40247925 | E21: 41918 | G21: FEMENINO | H21: INDETERMINADO | I21: EMPLEADO | J21: SI | K21: NO | L21: NO | N21: CONTABILIDAD | O21: CONTADORA | P21: 4000 | Q21: 113 | R21: 0 | T21: =P21+Q21+R21+S21 -> 4113 | U21: ='HOJA RXH'!AH17 -> 15 | W21: ='HOJA RXH'!Z17 -> 0 | X21: =((P21+Q21)/$C$3)*W21 -> 0 | Y21: ='HOJA RXH'!AD17 -> 0 | Z21: =(T21/30/8/60*Y21) -> 0 | AH21: ='HOJA RXH'!V17 -> 0 | AJ21: =(((P21+Q21)/30)*U21)-Z21+AA21+AB21+AC21+AF21+AG21+AI21 -> 2056.5 | AK21: ='HOJA RXH'!J17 -> 0 | AL21: =T21/30*AK21 -> 0 | AM21: ='HOJA RXH'!F17 -> 0 | AN21: =T21/30/10*AM21 -> 0 | AO21: ='HOJA RXH'!N17 -> 0 | AP21: =T21/30*AO21 -> 0 | AQ21: 0 | AR21: =((R21/$C$3)*(U21-V21))+AL21+AP21+AN21+AQ21 -> 0 | AS21: ONP | AV21: =IF(AS21="ONP",VLOOKUP(AS21,TASAS!TAB_AFP,8,0)*AJ21,0) -> 267.345 | AW21: =IF(AS21<>"ONP",AJ21*$AW$8,0) -> 0 | AX21: =IF(AS21<>"ONP",AJ21*AT21,0) -> 0 | AY21: =IF(AU21<>"ONP",AJ21*AU21,0) -> 0 | AZ21: =+AX21+AY21+AW21 -> 0 | BA21: =+AZ21+AV21 -> 267.345 | BC21: =AJ21+AR21-BA21-BB21 -> 1789.155 | BD21: =ROUND(AJ21*$BD$8,2) -> 185.09 | BE21: =IF(K21="SI",AJ21*2.14%,0) -> 0 | BG21: =+P21*0.54% -> 21.6 | BJ21: =BC21-BH21+BI21 -> 1789.155
A22: 13 | B22: TENORIO MARTINEZ DE CISNEROS RUTH LOURDES | C22: 28961 | D22: 40986687 | E22: 44028 | G22: FEMENINO | H22: MYPE CONTRAT | I22: EMPLEADO | J22: NO | K22: NO | L22: NO | M22: 589590RTMOT3 | N22: ADMINISTRACION | O22: ASIST ADMINIST | P22: =3000+2000 -> 5000 | Q22: 113 | R22: 1000 | T22: =P22+Q22+R22+S22 -> 6113 | U22: ='HOJA RXH'!AH18 -> 15 | W22: ='HOJA RXH'!Z18 -> 0 | X22: =((P22+Q22)/$C$3)*W22 -> 0 | Y22: ='HOJA RXH'!AD18 -> 0 | Z22: =(T22/30/8/60*Y22) -> 0 | AH22: ='HOJA RXH'!V18 -> 0 | AJ22: =(((P22+Q22)/30)*U22)-Z22+AA22+AB22+AC22+AF22+AG22+AI22 -> 2556.5 | AK22: ='HOJA RXH'!J18 -> 0 | AL22: =T22/30*AK22 -> 0 | AM22: ='HOJA RXH'!F18 -> 0 | AN22: =T22/30/10*AM22 -> 0 | AO22: ='HOJA RXH'!N18 -> 0 | AP22: =T22/30*AO22 -> 0 | AQ22: 0 | AR22: =((R22/$C$3)*(U22-V22))+AL22+AP22+AN22+AQ22 -> 500 | AS22: INTEGRA MIXTA | AT22: 0 | AU22: 0.0137 | AV22: =IF(AS22="ONP",VLOOKUP(AS22,TASAS!TAB_AFP,8,0)*AJ22,0) -> 0 | AW22: =IF(AS22<>"ONP",AJ22*$AW$8,0) -> 255.65 | AX22: =IF(AS22<>"ONP",AJ22*AT22,0) -> 0 | AY22: =IF(AU22<>"ONP",AJ22*AU22,0) -> 35.02405 | AZ22: =+AX22+AY22+AW22 -> 290.67405 | BA22: =+AZ22+AV22 -> 290.67405 | BC22: =AJ22+AR22-BA22-BB22 -> 2765.8259 | BD22: =ROUND(AJ22*$BD$8,2) -> 230.09 | BE22: =IF(K22="SI",AJ22*2.14%,0) -> 0 | BG22: =+P22*0.54% -> 27 | BJ22: =BC22-BH22+BI22 -> 2765.8259
A23: 14 | B23: VASQUEZ CUNYAS, JOSE EDGAR | C23: 33135 | D23: 46586240 | E23: 45673 | G23: MASCULINO | H23: MYPE CONTRAT | I23: OBRERO | J23: NO | K23: SI | L23: NO | M23: 631331JVCQY3 | N23: PINTURA | O23: PINTOR | P23: 3000 | T23: =P23+Q23+R23+S23 -> 3000 | U23: ='HOJA RXH'!AH19 -> 15 | W23: ='HOJA RXH'!Z19 -> 0 | X23: =((P23+Q23)/$C$3)*W23 -> 0 | Y23: ='HOJA RXH'!AD19 -> 0 | Z23: =(T23/30/8/60*Y23) -> 0 | AG23: 300 | AH23: ='HOJA RXH'!V19 -> 0 | AJ23: =(((P23+Q23)/30)*U23)-Z23+AA23+AB23+AC23+AF23+AG23+AI23 -> 1800 | AK23: ='HOJA RXH'!J19 -> 2 | AL23: =T23/30*AK23 -> 200 | AM23: ='HOJA RXH'!F19 -> 3 | AN23: =T23/30/10*AM23 -> 30 | AO23: ='HOJA RXH'!N19 -> 0 | AP23: =T23/30*AO23 -> 0 | AQ23: 0 | AR23: =((R23/$C$3)*(U23-V23))+AL23+AP23+AN23+AQ23 -> 230 | AS23: INTEGRA MIXTA | AT23: 0 | AU23: 0.0137 | AV23: =IF(AS23="ONP",VLOOKUP(AS23,TASAS!TAB_AFP,8,0)*AJ23,0) -> 0 | AW23: =IF(AS23<>"ONP",AJ23*$AW$8,0) -> 180 | AX23: =IF(AS23<>"ONP",AJ23*AT23,0) -> 0 | AY23: =IF(AU23<>"ONP",AJ23*AU23,0) -> 24.66 | AZ23: =+AX23+AY23+AW23 -> 204.66 | BA23: =+AZ23+AV23 -> 204.66 | BC23: =AJ23+AR23-BA23-BB23 -> 1825.34 | BD23: =ROUND(AJ23*$BD$8,2) -> 162 | BE23: =IF(K23="SI",AJ23*2.14%,0) -> 38.52 | BG23: =+P23*0.54% -> 16.2 | BJ23: =BC23-BH23+BI23 -> 1825.34
A24: 15 | B24: ZACARIAS CORONEL MIGUEL ANGEL | C24: 17/03/1998 | D24: 74171661 | E24: 44835 | G24: MASCULINO | H24: MYPE CONTRAT | I24: OBRERO | J24: NO | K24: SI | L24: NO | M24: 658691MZCAO5 | N24: ESTRUCTURA | O24: ARMADOR | P24: 1600 | R24: =135+65+300 -> 500 | T24: =P24+Q24+R24+S24 -> 2100 | U24: ='HOJA RXH'!AH20 -> 13 | W24: ='HOJA RXH'!Z20 -> 2 | X24: =((P24+Q24)/$C$3)*W24 -> 106.66667 | Y24: ='HOJA RXH'!AD20 -> 60 | Z24: =(T24/30/8/60*Y24) -> 8.75 | AH24: ='HOJA RXH'!V20 -> 0 | AJ24: =(((P24+Q24)/30)*U24)-Z24+AA24+AB24+AC24+AF24+AG24+AI24 -> 684.58333 | AK24: ='HOJA RXH'!J20 -> 1 | AL24: =T24/30*AK24 -> 70 | AM24: ='HOJA RXH'!F20 -> 2 | AN24: =T24/30/10*AM24 -> 14 | AO24: ='HOJA RXH'!N20 -> 0 | AP24: =T24/30*AO24 -> 0 | AQ24: 0 | AR24: =((R24/$C$3)*(U24-V24))+AL24+AP24+AN24+AQ24 -> 300.66667 | AS24: PRIMA | AT24: 0 | AU24: 0.0137 | AV24: =IF(AS24="ONP",VLOOKUP(AS24,TASAS!TAB_AFP,8,0)*AJ24,0) -> 0 | AW24: =IF(AS24<>"ONP",AJ24*$AW$8,0) -> 68.458333 | AX24: =IF(AS24<>"ONP",AJ24*AT24,0) -> 0 | AY24: =IF(AU24<>"ONP",AJ24*AU24,0) -> 9.3787917 | AZ24: =+AX24+AY24+AW24 -> 77.837125 | BA24: =+AZ24+AV24 -> 77.837125 | BC24: =AJ24+AR24-BA24-BB24 -> 907.41287 | BD24: =ROUND(AJ24*$BD$8,2) -> 61.61 | BE24: =IF(K24="SI",AJ24*2.14%,0) -> 14.650083 | BG24: =+P24*0.54% -> 8.64 | BJ24: =BC24-BH24+BI24 -> 907.41287
P25: =SUM(P10:P24) -> 41690 | Q25: =SUM(Q10:Q24) -> 904 | R25: =SUM(R10:R24) -> 8250 | S25: =SUM(S10:S24) -> 0 | T25: =SUM(T10:T24) -> 50844 | U25: =SUM(U10:U24) -> 215 | V25: =SUM(V10:V24) -> 0 | W25: =SUM(W10:W24) -> 10 | ... AR25: =SUM(AR10:AR24) -> 5276.2067 | AT25: =SUM(AT10:AT24) -> 0.0653 | AU25: =SUM(AU10:AU24) -> 0.1644 | AV25: =SUM(AV10:AV24) -> 347.69452 | AW25: =SUM(AW10:AW24) -> 1447.7949 | AX25: =SUM(AX10:AX24) -> 65.704531 | AY25: =SUM(AY10:AY24) -> 198.34791 | AZ25: =SUM(AZ10:AZ24) -> 1711.8474 | BA25: =SUM(BA10:BA24) -> 2059.5419 | ... BJ25: =SUM(BJ10:BJ24) -> 23219.187

Sheet ASISTENCIA
D1: REFRIGERIO | M1: LEYENDA
A2: TURNO | B2: HR. ENTRADA | C2: HR. SALIDA | D2: HR. SALIDA (REFR.) | E2: HR. REGRESO (REFR,) | F2: TOTAL DE REFRIGERIO | G2: HRS. ESPERADAS | H2: MIN. ESPERADOS | M2: ESCRIBIR EN LA COLUMNA ASISTENCIA DIARIA | O2: COLUMNA SOLICITUD DEL SUPERVISOR
A3: 1 | B3: 0.30763889 | C3: 0.75 | D3: 0.5 | E3: 0.54166667 | F3: =E3-D3 -> 0.041666667 | G3: =C3-B3-F3 -> 0.40069444 | H3: =G3*1440 -> 577 | M3: DIA NORMAL | O3: NO
A4: 2 | B4: 0.33333333 | C4: 0.75 | D4: 0.5 | E4: 0.54166667 | F4: =E4-D4 -> 0.041666667 | G4: =C4-B4-F4 -> 0.375 | H4: =G4*1440 -> 540 | M4: SI ESTÁ DE VACACIONES | N4: VACACIONES | O4: SI
M5: SI FALTÓ | N5: FALTA
M6: SI ESTÁ DE LICENCIA | N6: LICENCIA
A7: CONSIDERACIONES | M7: SI JUSTFICÓ | N7: JUSTIFICADO
A8: 1 | B8: SOLO CAMBIAR LAS CELDAS DE HR. ENTRADA - SALIDA Y LA COLUMNA DE ASISTENCIA DIARIA. | M8: SI TRABAJÓ UN SABADO | N8: TRABAJO SABADO
M9: SI TRABAJÓ UN DOMINGO | N9: TRABAJO DOMINGO
A10: 2 | B10: SOLO CAMBIAR LA PRIMERA FECHA, LOS DIAS SIGUIENTES DE AMBAS QUINCENAS SE ACTUALIZAN AUTOMATICAMENTE. | M10: SI TRABAJÓ UN FERIADO | N10: TRABAJO FERIADO
M11: SI TRABAJÓ EL 1RO DE MAYO | N11: TRABAJO 1RO MAYO
M12: SI TRABAJÓ EL 1RO DE MAYO EN SU DIA LIBRE | N12: TRABAJO 1RO MAYO EN SU DIA LIBRE
D15: =IF(AND(DAY(D17)=1,MONTH(D17)=5),"⚠️ HOY ES 1 DE MAYO - PAGO DOBLE","") | M15: =IF(AND(DAY(M17)=1,MONTH(M17)=5),"⚠️ HOY ES 1 DE MAYO - PAGO DOBLE","") | V15: =IF(AND(DAY(V17)=1,MONTH(V17)=5),"⚠️ HOY ES 1 DE MAYO - PAGO DOBLE","") | AE15: =IF(AND(DAY(AE17)=1,MONTH(AE17)=5),"⚠️ HOY ES 1 DE MAYO - PAGO DOBLE","") | AN15: =IF(AND(DAY(AN17)=1,MONTH(AN17)=5),"⚠️ HOY ES 1 DE MAYO - PAGO DOBLE","") | AW15: =IF(AND(DAY(AW17)=1,MONTH(AW17)=5),"⚠️ HOY ES 1 DE MAYO - PAGO DOBLE","") | BF15: =IF(AND(DAY(BF17)=1,MONTH(BF17)=5),"⚠️ HOY ES 1 DE MAYO - PAGO DOBLE","") | BO15: =IF(AND(DAY(BO17)=1,MONTH(BO17)=5),"⚠️ HOY ES 1 DE MAYO - PAGO DOBLE","") | BX15: =IF(AND(DAY(BX17)=1,MONTH(BX17)=5),"⚠️ HOY ES 1 DE MAYO - PAGO DOBLE","") | CG15: =IF(AND(DAY(CG17)=1,MONTH(CG17)=5),"⚠️ HOY ES 1 DE MAYO - PAGO DOBLE","") | CP15: =IF(AND(DAY(CP17)=1,MONTH(CP17)=5),"⚠️ HOY ES 1 DE MAYO - PAGO DOBLE","") | CY15: =IF(AND(DAY(CY17)=1,MONTH(CY17)=5),"⚠️ HOY ES 1 DE MAYO - PAGO DOBLE","") | DH15: =IF(AND(DAY(DH17)=1,MONTH(DH17)=5),"⚠️ HOY ES 1 DE MAYO - PAGO DOBLE","") | DQ15: =IF(AND(DAY(DQ17)=1,MONTH(DQ17)=5),"⚠️ HOY ES 1 DE MAYO - PAGO DOBLE","") | DZ15: =IF(AND(DAY(DZ17)=1,MONTH(DZ17)=5),"⚠️ HOY ES 1 DE MAYO - PAGO DOBLE","") | EK15: CUADRO RESUMEN PRIMERA QUINCENA
A16: DATOS | D16: =UPPER(TEXT(D17,"DDDD")) -> LUNES | M16: =UPPER(TEXT(M17,"DDDD")) -> MARTES | V16: =UPPER(TEXT(V17,"DDDD")) -> MIÉRCOLES | AE16: =UPPER(TEXT(AE17,"DDDD")) -> JUEVES | AN16: =UPPER(TEXT(AN17,"DDDD")) -> VIERNES | AW16: =UPPER(TEXT(AW17,"DDDD")) -> SÁBADO | BF16: =UPPER(TEXT(BF17,"DDDD")) -> DOMINGO | BO16: =UPPER(TEXT(BO17,"DDDD")) -> LUNES | BX16: =UPPER(TEXT(BX17,"DDDD")) -> MARTES | CG16: =UPPER(TEXT(CG17,"DDDD")) -> MIÉRCOLES | CP16: =UPPER(TEXT(CP17,"DDDD")) -> JUEVES | CY16: =UPPER(TEXT(CY17,"DDDD")) -> VIERNES | DH16: =UPPER(TEXT(DH17,"DDDD")) -> SÁBADO | DQ16: =UPPER(TEXT(DQ17,"DDDD")) -> DOMINGO | DZ16: =UPPER(TEXT(DZ17,"DDDD")) -> LUNES | EK16: TARDANZA (MIN.) | EL16: CANT. HRS. EXTRA (MIN.) | EM16: CANT. HRS. EXTRA (DIAS) | EN16: FALTAS | EO16: DIAS TRABAJADOS | EP16: SABADO | EQ16: FERIADOS Y DOMINGOS | ER16: VACACIONES | ES16: LICENCIA HIJO ENFERMO
D17: 46174 | M17: =D17+1 -> 46175 | V17: =M17+1 -> 46176 | AE17: =V17+1 -> 46177 | AN17: =AE17+1 -> 46178 | AW17: =AN17+1 -> 46179 | BF17: =AW17+1 -> 46180 | BO17: =BF17+1 -> 46181 | BX17: =BO17+1 -> 46182 | CG17: =BX17+1 -> 46183 | CP17: =CG17+1 -> 46184 | CY17: =CP17+1 -> 46185 | DH17: =CY17+1 -> 46186 | DQ17: =DH17+1 -> 46187 | DZ17: =DQ17+1 -> 46188
A18: N° | B18: APELLIDO, NOMBRE | C18: TURNO | D18: HR. ENTRADA | E18: HR. SALIDA | F18: SOLICITUD DEL SUPERVISOR | G18: HRS. LAB. | H18: TARDANZA (MIN.) | I18: L - V (MIN. EXTRA) | J18: SAB. - DOM. EXTRA (MIN.) | K18: ASISTENCIA DIARIA | M18: HR. ENTRADA | N18: HR. SALIDA | O18: SOLICITUD DEL SUPERVISOR | P18: HRS. LAB. | Q18: TARDANZA (MIN.) | R18: L - V (MIN. EXTRA) | S18: SAB. - DOM. EXTRA (MIN.) | T18: ASISTENCIA DIARIA | V18: HR. ENTRADA | W18: HR. SALIDA | X18: SOLICITUD DEL SUPERVISOR | Y18: HRS. LAB. | Z18: TARDANZA (MIN.) | AA18: L - V (MIN. EXTRA) | AB18: SAB. - DOM. EXTRA (MIN.) | AC18: ASISTENCIA DIARIA | AE18: HR. ENTRADA | AF18: HR. SALIDA | AG18: SOLICITUD DEL SUPERVISOR | AH18: HRS. LAB. | AI18: TARDANZA (MIN.) | AJ18: L - V (MIN. EXTRA) | AK18: SAB. - DOM. EXTRA (MIN.) | AL18: ASISTENCIA DIARIA | AN18: HR. ENTRADA | AO18: HR. SALIDA | AP18: SOLICITUD DEL SUPERVISOR | AQ18: HRS. LAB. | AR18: TARDANZA (MIN.) | AS18: L - V (MIN. EXTRA) | AT18: SAB. - DOM. EXTRA (MIN.) | AU18: ASISTENCIA DIARIA | AW18: HR. ENTRADA | AX18: HR. SALIDA | AY18: SOLICITUD DEL SUPERVISOR | AZ18: HRS. LAB. | BA18: TARDANZA (MIN.) | BB18: L - V (MIN. EXTRA) | BC18: SAB. - DOM. EXTRA (MIN.) | BD18: ASISTENCIA DIARIA | BF18: HR. ENTRADA | BG18: HR. SALIDA | BH18: SOLICITUD DEL SUPERVISOR | BI18: HRS. LAB. | BJ18: TARDANZA (MIN.) | BK18: L - V (MIN. EXTRA) | BL18: SAB. - DOM. EXTRA (MIN.) | BM18: ASISTENCIA DIARIA | BO18: HR. ENTRADA | BP18: HR. SALIDA | BQ18: SOLICITUD DEL SUPERVISOR | BR18: HRS. LAB. | BS18: TARDANZA (MIN.) | BT18: L - V (MIN. EXTRA) | BU18: SAB. - DOM. EXTRA (MIN.) | BV18: ASISTENCIA DIARIA | BX18: HR. ENTRADA | BY18: HR. SALIDA | BZ18: SOLICITUD DEL SUPERVISOR | CA18: HRS. LAB. | CB18: TARDANZA (MIN.) | CC18: L - V (MIN. EXTRA) | CD18: SAB. - DOM. EXTRA (MIN.) | CE18: ASISTENCIA DIARIA | CG18: HR. ENTRADA | CH18: HR. SALIDA | CI18: SOLICITUD DEL SUPERVISOR | CJ18: HRS. LAB. | CK18: TARDANZA (MIN.) | CL18: L - V (MIN. EXTRA) | CM18: SAB. - DOM. EXTRA (MIN.) | CN18: ASISTENCIA DIARIA | CP18: HR. ENTRADA | CQ18: HR. SALIDA | CR18: SOLICITUD DEL SUPERVISOR | CS18: HRS. LAB. | CT18: TARDANZA (MIN.) | CU18: L - V (MIN. EXTRA) | CV18: SAB. - DOM. EXTRA (MIN.) | CW18: ASISTENCIA DIARIA | CY18: HR. ENTRADA | CZ18: HR. SALIDA | DA18: SOLICITUD DEL SUPERVISOR | DB18: HRS. LAB. | DC18: TARDANZA (MIN.) | DD18: L - V (MIN. EXTRA) | DE18: SAB. - DOM. EXTRA (MIN.) | DF18: ASISTENCIA DIARIA | DH18: HR. ENTRADA | DI18: HR. SALIDA | DJ18: SOLICITUD DEL SUPERVISOR | DK18: HRS. LAB. | DL18: TARDANZA (MIN.) | DM18: L - V (MIN. EXTRA) | DN18: SAB. - DOM. EXTRA (MIN.) | DO18: ASISTENCIA DIARIA | DQ18: HR. ENTRADA | DR18: HR. SALIDA | DS18: SOLICITUD DEL SUPERVISOR | DT18: HRS. LAB. | DU18: TARDANZA (MIN.) | DV18: L - V (MIN. EXTRA) | DW18: SAB. - DOM. EXTRA (MIN.) | DX18: ASISTENCIA DIARIA | DZ18: HR. ENTRADA | EA18: HR. SALIDA | EB18: SOLICITUD DEL SUPERVISOR | EC18: HRS. LAB. | ED18: TARDANZA (MIN.) | EE18: L - V (MIN. EXTRA) | EF18: SAB. - DOM. EXTRA (MIN.) | EG18: ASISTENCIA DIARIA
A19: 1 | B19: ='1RA QUINCENA JUNIO 26'!B10 -> CISNEROS PACOTAYPE KEVIN | C19: 2 | G19: =IF(OR(K19="VACACIONES",K19="FALTA",K19="LICENCIA",D19="",E19=""),"",IF(WEEKDAY($D$17,2)>5,E19-D19,IF(F19="NO",MIN(E19,CHOOSE($C19,$C$3,$C$4))-MAX(D19,CHOOSE($C19,$B$3,$B$4))-CHOOSE($C19,$F$3,$F$4),E19-D19-CHOOSE($C19,$F$3,$F$4)))) | H19: =IF(OR(K19="VACACIONES",K19="FALTA",K19="LICENCIA",D19="",E19="",WEEKDAY($D$17,2)>5),"", MAX(0,CHOOSE($C19,$H$3,$H$4)-(G19*1440)) ) | I19: =IF(OR(K19="VACACIONES",K19="FALTA",K19="LICENCIA",D19="",E19="",F19="NO",WEEKDAY($D$17,2)>5),"",MAX(0,IF(F19="SI", (G19*1440)-CHOOSE($C19,$H$3,$H$4) ))) | J19: =IF(OR(K19="VACACIONES",K19="FALTA",K19="LICENCIA",D19="",E19="",WEEKDAY($D$17,2)<=5),"",IF(WEEKDAY($D$17,2)>5,(G19*1440))) | K19: FALTA | P19: =IF(OR(T19="VACACIONES",T19="FALTA",T19="LICENCIA",M19="",N19=""),"",IF(WEEKDAY($M$17,2)>5,N19-M19,IF(O19="NO",MIN(N19,CHOOSE($C19,$C$3,$C$4))-MAX(M19,CHOOSE($C19,$B$3,$B$4))-CHOOSE($C19,$F$3,$F$4),N19-M19-CHOOSE($C19,$F$3,$F$4)))) | Q19: =IF(OR(T19="VACACIONES",T19="FALTA",T19="LICENCIA",M19="",N19="",WEEKDAY($M$17,2)>5),"", MAX(0,CHOOSE($C19,$H$3,$H$4)-(P19*1440)) ) | R19: =IF(OR(T19="VACACIONES",T19="FALTA",T19="LICENCIA",M19="",N19="",O19="NO",WEEKDAY($M$17,2)>5),"",MAX(0,IF(O19="SI", (P19*1440)-CHOOSE($C19,$H$3,$H$4) ))) | S19: =IF(OR(T19="VACACIONES",T19="FALTA",T19="LICENCIA",M19="",N19="",WEEKDAY($M$17,2)<=5),"",IF(WEEKDAY($M$17,2)>5,(P19*1440))) | T19: FALTA | Y19: =IF(OR(AC19="VACACIONES",AC19="FALTA",AC19="LICENCIA",V19="",W19=""),"",IF(WEEKDAY($V$17,2)>5,W19-V19,IF(X19="NO",MIN(W19,CHOOSE($C19,$C$3,$C$4))-MAX(V19,CHOOSE($C19,$B$3,$B$4))-CHOOSE($C19,$F$3,$F$4),W19-V19-CHOOSE($C19,$F$3,$F$4)))) | Z19: =IF(OR(AC19="VACACIONES",AC19="FALTA",AC19="LICENCIA",V19="",W19="",WEEKDAY($V$17,2)>5),"", MAX(0,CHOOSE($C19,$H$3,$H$4)-(Y19*1440)) ) | AA19: =IF(OR(AC19="VACACIONES",AC19="FALTA",AC19="LICENCIA",V19="",W19="",X19="NO",WEEKDAY($V$17,2)>5),"",MAX(0,IF(X19="SI", (Y19*1440)-CHOOSE($C19,$H$3,$H$4) ))) | AB19: =IF(OR(AC19="VACACIONES",AC19="FALTA",AC19="LICENCIA",V19="",W19="",WEEKDAY($V$17,2)<=5),"",IF(WEEKDAY($V$17,2)>5,(Y19*1440))) | AC19: FALTA | AH19: =IF(OR(AL19="VACACIONES",AL19="FALTA",AL19="LICENCIA",AE19="",AF19=""),"",IF(WEEKDAY($AE$17,2)>5,AF19-AE19,IF(AG19="NO",MIN(AF19,CHOOSE($C19,$C$3,$C$4))-MAX(AE19,CHOOSE($C19,$B$3,$B$4))-CHOOSE($C19,$F$3,$F$4),AF19-AE19-CHOOSE($C19,$F$3,$F$4)))) | AI19: =IF(OR(AL19="VACACIONES",AL19="FALTA",AL19="LICENCIA",AE19="",AF19="",WEEKDAY($AE$17,2)>5),"", MAX(0,CHOOSE($C19,$H$3,$H$4)-(AH19*1440)) ) | AJ19: =IF(OR(AL19="VACACIONES",AL19="FALTA",AL19="LICENCIA",AE19="",AF19="",AG19="NO",WEEKDAY($AE$17,2)>5),"",MAX(0,IF(AG19="SI", (AH19*1440)-CHOOSE($C19,$H$3,$H$4) ))) | AK19: =IF(OR(AL19="VACACIONES",AL19="FALTA",AL19="LICENCIA",AE19="",AF19="",WEEKDAY($AE$17,2)<=5),"",IF(WEEKDAY($AE$17,2)>5,(AH19*1440))) | AL19: FALTA | AQ19: =IF(OR(AU19="VACACIONES",AU19="FALTA",AU19="LICENCIA",AN19="",AO19=""),"",IF(WEEKDAY($AN$17,2)>5,AO19-AN19,IF(AP19="NO",MIN(AO19,CHOOSE($C19,$C$3,$C$4))-MAX(AN19,CHOOSE($C19,$B$3,$B$4))-CHOOSE($C19,$F$3,$F$4),AO19-AN19-CHOOSE($C19,$F$3,$F$4)))) | AR19: =IF(OR(AU19="VACACIONES",AU19="FALTA",AU19="LICENCIA",AN19="",AO19="",WEEKDAY($AN$17,2)>5),"", MAX(0,CHOOSE($C19,$H$3,$H$4)-(AQ19*1440)) ) | AS19: =IF(OR(AU19="VACACIONES",AU19="FALTA",AU19="LICENCIA",AN19="",AO19="",AP19="NO",WEEKDAY($AN$17,2)>5),"",MAX(0,IF(AP19="SI", (AQ19*1440)-CHOOSE($C19,$H$3,$H$4) ))) | AT19: =IF(OR(AU19="VACACIONES",AU19="FALTA",AU19="LICENCIA",AN19="",AO19="",WEEKDAY($AN$17,2)<=5),"",IF(WEEKDAY($AN$17,2)>5,(AQ19*1440))) | AU19: FALTA | AZ19: =IF(OR(BD19="VACACIONES",BD19="FALTA",BD19="LICENCIA",AW19="",AX19=""),"",IF(WEEKDAY($AW$17,2)>5,AX19-AW19,IF(AY19="NO",MIN(AX19,CHOOSE($C19,$C$3,$C$4))-MAX(AW19,CHOOSE($C19,$B$3,$B$4))-CHOOSE($C19,$F$3,$F$4),AX19-AW19-CHOOSE($C19,$F$3,$F$4)))) | BA19: =IF(OR(BD19="VACACIONES",BD19="FALTA",BD19="LICENCIA",AW19="",AX19="",WEEKDAY($AW$17,2)>5),"", MAX(0,CHOOSE($C19,$H$3,$H$4)-(AZ19*1440)) ) | BB19: =IF(OR(BD19="VACACIONES",BD19="FALTA",BD19="LICENCIA",AW19="",AX19="",AY19="NO",WEEKDAY($AW$17,2)>5),"",MAX(0,IF(AY19="SI", (AZ19*1440)-CHOOSE($C19,$H$3,$H$4) ))) | BC19: =IF(OR(BD19="VACACIONES",BD19="FALTA",BD19="LICENCIA",AW19="",AX19="",WEEKDAY($AW$17,2)<=5),"",IF(WEEKDAY($AW$17,2)>5,(AZ19*1440))) | BD19: FALTA | BI19: =IF(OR(BM19="VACACIONES",BM19="FALTA",BM19="LICENCIA",BF19="",BG19=""),"",IF(WEEKDAY($BF$17,2)>5,BG19-BF19,IF(BH19="NO",MIN(BG19,CHOOSE($C19,$C$3,$C$4))-MAX(BF19,CHOOSE($C19,$B$3,$B$4))-CHOOSE($C19,$F$3,$F$4),BG19-BF19-CHOOSE($C19,$F$3,$F$4)))) | BJ19: =IF(OR(BM19="VACACIONES",BM19="FALTA",BM19="LICENCIA",BF19="",BG19="",WEEKDAY($BF$17,2)>5),"", MAX(0,CHOOSE($C19,$H$3,$H$4)-(BI19*1440)) ) | BK19: =IF(OR(BM19="VACACIONES",BM19="FALTA",BM19="LICENCIA",BF19="",BG19="",BH19="NO",WEEKDAY($BF$17,2)>5),"",MAX(0,IF(BH19="SI", (BI19*1440)-CHOOSE($C19,$H$3,$H$4) ))) | BL19: =IF(OR(BM19="VACACIONES",BM19="FALTA",BM19="LICENCIA",BF19="",BG19="",WEEKDAY($BF$17,2)<=5),"",IF(WEEKDAY($BF$17,2)>5,(BI19*1440))) | BM19: FALTA | BO19: 0.36180556 | BP19: 0.78333333 | BQ19: SI | BR19: =IF(OR(BV19="VACACIONES",BV19="FALTA",BV19="LICENCIA",BO19="",BP19=""),"",IF(WEEKDAY($BO$17,2)>5,BP19-BO19,IF(BQ19="NO",MIN(BP19,CHOOSE($C19,$C$3,$C$4))-MAX(BO19,CHOOSE($C19,$B$3,$B$4))-CHOOSE($C19,$F$3,$F$4),BP19-BO19-CHOOSE($C19,$F$3,$F$4)))) -> 0.37986111 | BS19: =IF(OR(BV19="VACACIONES",BV19="FALTA",BV19="LICENCIA",BO19="",BP19="",WEEKDAY($BO$17,2)>5),"", MAX(0,CHOOSE($C19,$H$3,$H$4)-(BR19*1440)) ) -> 0 | BT19: =IF(OR(BV19="VACACIONES",BV19="FALTA",BV19="LICENCIA",BO19="",BP19="",BQ19="NO",WEEKDAY($BO$17,2)>5),"",MAX(0,IF(BQ19="SI", (BR19*1440)-CHOOSE($C19,$H$3,$H$4) ))) -> 7 | BU19: =IF(OR(BV19="VACACIONES",BV19="FALTA",BV19="LICENCIA",BO19="",BP19="",WEEKDAY($BO$17,2)<=5),"",IF(WEEKDAY($BO$17,2)>5,(BR19*1440))) | BX19: 0.36666667 | BY19: 0.83333333 | BZ19: SI | CA19: =IF(OR(CE19="VACACIONES",CE19="FALTA",CE19="LICENCIA",BX19="",BY19=""),"",IF(WEEKDAY($BX$17,2)>5,BY19-BX19,IF(BZ19="NO",MIN(BY19,CHOOSE($C19,$C$3,$C$4))-MAX(BX19,CHOOSE($C19,$B$3,$B$4))-CHOOSE($C19,$F$3,$F$4),BY19-BX19-CHOOSE($C19,$F$3,$F$4)))) -> 0.425 | CB19: =IF(OR(CE19="VACACIONES",CE19="FALTA",CE19="LICENCIA",BX19="",BY19="",WEEKDAY($BX$17,2)>5),"", MAX(0,CHOOSE($C19,$H$3,$H$4)-(CA19*1440)) ) -> 0 | CC19: =IF(OR(CE19="VACACIONES",CE19="FALTA",CE19="LICENCIA",BX19="",BY19="",BZ19="NO",WEEKDAY($BX$17,2)>5),"",MAX(0,IF(BZ19="SI", (CA19*1440)-CHOOSE($C19,$H$3,$H$4) ))) -> 72 | CD19: =IF(OR(CE19="VACACIONES",CE19="FALTA",CE19="LICENCIA",BX19="",BY19="",WEEKDAY($BX$17,2)<=5),"",IF(WEEKDAY($BX$17,2)>5,(CA19*1440))) | CG19: 0.375 | CH19: 0.80416667 | CI19: SI | CJ19: =IF(OR(CN19="VACACIONES",CN19="FALTA",CN19="LICENCIA",CG19="",CH19=""),"",IF(WEEKDAY($CG$17,2)>5,CH19-CG19,IF(CI19="NO",MIN(CH19,CHOOSE($C19,$C$3,$C$4))-MAX(CG19,CHOOSE($C19,$B$3,$B$4))-CHOOSE($C19,$F$3,$F$4),CH19-CG19-CHOOSE($C19,$F$3,$F$4)))) -> 0.3875 | CK19: =IF(OR(CN19="VACACIONES",CN19="FALTA",CN19="LICENCIA",CG19="",CH19="",WEEKDAY($CG$17,2)>5),"", MAX(0,CHOOSE($C19,$H$3,$H$4)-(CJ19*1440)) ) -> 0 | CL19: =IF(OR(CN19="VACACIONES",CN19="FALTA",CN19="LICENCIA",CG19="",CH19="",CI19="NO",WEEKDAY($CG$17,2)>5),"",MAX(0,IF(CI19="SI", (CJ19*1440)-CHOOSE($C19,$H$3,$H$4) ))) -> 18 | CM19: =IF(OR(CN19="VACACIONES",CN19="FALTA",CN19="LICENCIA",CG19="",CH19="",WEEKDAY($CG$17,2)<=5),"",IF(WEEKDAY($CG$17,2)>5,(CJ19*1440))) | CP19: 0.39236111 | CQ19: 0.82222222 | CR19: SI | CS19: =IF(OR(CW19="VACACIONES",CW19="FALTA",CW19="LICENCIA",CP19="",CQ19=""),"",IF(WEEKDAY($CP$17,2)>5,CQ19-CP19,IF(CR19="NO",MIN(CQ19,CHOOSE($C19,$C$3,$C$4))-MAX(CP19,CHOOSE($C19,$B$3,$B$4))-CHOOSE($C19,$F$3,$F$4),CQ19-CP19-CHOOSE($C19,$F$3,$F$4)))) -> 0.38819444 | CT19: =IF(OR(CW19="VACACIONES",CW19="FALTA",CW19="LICENCIA",CP19="",CQ19="",WEEKDAY($CP$17,2)>5),"", MAX(0,CHOOSE($C19,$H$3,$H$4)-(CS19*1440)) ) -> 0 | CU19: =IF(OR(CW19="VACACIONES",CW19="FALTA",CW19="LICENCIA",CP19="",CQ19="",CR19="NO",WEEKDAY($CP$17,2)>5),"",MAX(0,IF(CR19="SI", (CS19*1440)-CHOOSE($C19,$H$3,$H$4) ))) -> 19 | CV19: =IF(OR(CW19="VACACIONES",CW19="FALTA",CW19="LICENCIA",CP19="",CQ19="",WEEKDAY($CP$17,2)<=5),"",IF(WEEKDAY($CP$17,2)>5,(CS19*1440))) | CY19: 0.37361111 | CZ19: 0.80902778 | DA19: SI | DB19: =IF(OR(DF19="VACACIONES",DF19="FALTA",DF19="LICENCIA",CY19="",CZ19=""),"",IF(WEEKDAY($CY$17,2)>5,CZ19-CY19,IF(DA19="NO",MIN(CZ19,CHOOSE($C19,$C$3,$C$4))-MAX(CY19,CHOOSE($C19,$B$3,$B$4))-CHOOSE($C19,$F$3,$F$4),CZ19-CY19-CHOOSE($C19,$F$3,$F$4)))) -> 0.39375 | DC19: =IF(OR(DF19="VACACIONES",DF19="FALTA",DF19="LICENCIA",CY19="",CZ19="",WEEKDAY($CY$17,2)>5),"", MAX(0,CHOOSE($C19,$H$3,$H$4)-(DB19*1440)) ) -> 0 | DD19: =IF(OR(DF19="VACACIONES",DF19="FALTA",DF19="LICENCIA",CY19="",CZ19="",DA19="NO",WEEKDAY($CY$17,2)>5),"",MAX(0,IF(DA19="SI", (DB19*1440)-CHOOSE($C19,$H$3,$H$4) ))) -> 27 | DE19: =IF(OR(DF19="VACACIONES",DF19="FALTA",DF19="LICENCIA",CY19="",CZ19="",WEEKDAY($CY$17,2)<=5),"",IF(WEEKDAY($CY$17,2)>5,(DB19*1440))) | DK19: =IF(OR(DO19="VACACIONES",DO19="FALTA",DO19="LICENCIA",DH19="",DI19=""),"",IF(WEEKDAY($DH$17,2)>5,DI19-DH19,IF(DJ19="NO",MIN(DI19,CHOOSE($C19,$C$3,$C$4))-MAX(DH19,CHOOSE($C19,$B$3,$B$4))-CHOOSE($C19,$F$3,$F$4),DI19-DH19-CHOOSE($C19,$F$3,$F$4)))) | DL19: =IF(OR(DO19="VACACIONES",DO19="FALTA",DO19="LICENCIA",DH19="",DI19="",WEEKDAY($DH$17,2)>5),"", MAX(0,CHOOSE($C19,$H$3,$H$4)-(DK19*1440)) ) | DM19: =IF(OR(DO19="VACACIONES",DO19="FALTA",DO19="LICENCIA",DH19="",DI19="",DJ19="NO",WEEKDAY($DH$17,2)>5),"",MAX(0,IF(DJ19="SI", (DK19*1440)-CHOOSE($C19,$H$3,$H$4) ))) | DN19: =IF(OR(DO19="VACACIONES",DO19="FALTA",DO19="LICENCIA",DH19="",DI19="",WEEKDAY($DH$17,2)<=5),"",IF(WEEKDAY($DH$17,2)>5,(DK19*1440))) | DT19: =IF(OR(DX19="VACACIONES",DX19="FALTA",DX19="LICENCIA",DQ19="",DR19=""),"",IF(WEEKDAY($DQ$17,2)>5,DR19-DR19,IF(DS19="NO",MIN(DR19,CHOOSE($C19,$C$3,$C$4))-MAX(DQ19,CHOOSE($C19,$B$3,$B$4))-CHOOSE($C19,$F$3,$F$4),DR19-DQ19-CHOOSE($C19,$F$3,$F$4)))) | DU19: =IF(OR(DX19="VACACIONES",DX19="FALTA",DX19="LICENCIA",DQ19="",DR19="",WEEKDAY($DQ$17,2)>5),"", MAX(0,CHOOSE($C19,$H$3,$H$4)-(DT19*1440)) ) | DV19: =IF(OR(DX19="VACACIONES",DX19="FALTA",DX19="LICENCIA",DQ19="",DR19="",DS19="NO",WEEKDAY($DQ$17,2)>5),"",MAX(0,IF(DS19="SI", (DT19*1440)-CHOOSE($C19,$H$3,$H$4) ))) | DW19: =IF(OR(DX19="VACACIONES",DX19="FALTA",DX19="LICENCIA",DQ19="",DR19="",WEEKDAY($DQ$17,2)<=5),"",IF(WEEKDAY($DQ$17,2)>5,(DT19*1440))) | DZ19: 0.33333333 | EA19: 0.7875 | EB19: NO | EC19: =IF(OR(EG19="VACACIONES",EG19="FALTA",EG19="LICENCIA",DZ19="",EA19=""),"",IF(WEEKDAY($CY$17,2)>5,EA19-DZ19,IF(EB19="NO",MIN(EA19,CHOOSE($C19,$C$3,$C$4))-MAX(DZ19,CHOOSE($C19,$B$3,$B$4))-CHOOSE($C19,$F$3,$F$4),EA19-DZ19-CHOOSE($C19,$F$3,$F$4)))) -> 0.375 | ED19: =IF(OR(EG19="VACACIONES",EG19="FALTA",EG19="LICENCIA",DZ19="",EA19="",WEEKDAY($CY$17,2)>5),"", MAX(0,CHOOSE($C19,$H$3,$H$4)-(EC19*1440)) ) -> 0 | EE19: =IF(OR(EG19="VACACIONES",EG19="FALTA",EG19="LICENCIA",DZ19="",EA19="",EB19="NO",WEEKDAY($CY$17,2)>5),"",MAX(0,IF(EB19="SI", (EC19*1440)-CHOOSE($C19,$H$3,$H$4) ))) | EF19: =IF(OR(EG19="VACACIONES",EG19="FALTA",EG19="LICENCIA",DZ19="",EA19="",WEEKDAY($CY$17,2)<=5),"",IF(WEEKDAY($CY$17,2)>5,(EC19*1440))) | EK19: =SUM(H19,Q19,Z19,AI19,AR19,BA19,BJ19,BS19,CB19,CK19,CT19,DC19,DL19,DU19,ED19) -> 0 | EL19: 0 | EM19: =COUNTIF(I19,">0")+COUNTIF(J19,">0")+COUNTIF(R19,">0")+COUNTIF(S19,">0")++COUNTIF(AA19,">0")+COUNTIF(AB19,">0")+COUNTIF(AJ19,">0")+COUNTIF(AK19,">0")+COUNTIF(AS19,">0")+COUNTIF(AT19,">0")+COUNTIF(BB19,">0")+COUNTIF(BC19,">0")+COUNTIF(BK19,">0")+COUNTIF(BL19,">0")+COUNTIF(BT19,">0")+COUNTIF(BU19,">0")+COUNTIF(CC19,">0")+COUNTIF(CD19,">0")+COUNTIF(CL19,">0")+COUNTIF(CM19,">0")+COUNTIF(CU19,">0")+COUNTIF(CV19,">0")+COUNTIF(DD19,">0")+COUNTIF(DE19,">0")+COUNTIF(DM19,">0")+COUNTIF(DN19,">0")+COUNTIF(DV19,">0")+COUNTIF(DW19,">0")+COUNTIF(EE19,">0")+COUNTIF(EF19,">0") -> 5 | EN19: =COUNTIF(D19:EG19,"FALTA") -> 7 | EO19: =15-EN19 -> 8 | EP19: =COUNTIF(D19:EG19,"TRABAJO SABADO") -> 0 | EQ19: =COUNTIF(D19:EG19,"TRABAJO DOMINGO")+COUNTIF(D19:EG19,"TRABAJO FERIADO")+(COUNTIF(D19:EG19,"TRABAJO 1RO MAYO")*2)+((COUNTIF(D21:EG21,"TRABAJO 1RO MAYO EN SU DIA LIBRE")*2)*2) -> 0 | ER19: =COUNTIF(D19:EG19,"VACACIONES") -> 0 | ES19: =COUNTIF(D19:EG19,"LICENCIA") -> 0
A20: =A19+1 -> 2 | B20: ='1RA QUINCENA JUNIO 26'!B11 -> CISNEROS SUMA, ANDRES JUAN | C20: 1 | D20: 0.30763889 | E20: 0.75 | F20: NO | G20: =IF(OR(K20="VACACIONES",K20="FALTA",K20="LICENCIA",D20="",E20=""),"",IF(WEEKDAY($D$17,2)>5,E20-D20,IF(F20="NO",MIN(E20,CHOOSE($C20,$C$3,$C$4))-MAX(D20,CHOOSE($C20,$B$3,$B$4))-CHOOSE($C20,$F$3,$F$4),E20-D20-CHOOSE($C20,$F$3,$F$4)))) -> 0.40069444 | H20: =IF(OR(K20="VACACIONES",K20="FALTA",K20="LICENCIA",D20="",E20="",WEEKDAY($D$17,2)>5),"", MAX(0,CHOOSE($C20,$H$3,$H$4)-(G20*1440)) ) -> 0 | I20: =IF(OR(K20="VACACIONES",K20="FALTA",K20="LICENCIA",D20="",E20="",F20="NO",WEEKDAY($D$17,2)>5),"",MAX(0,IF(F20="SI", (G20*1440)-CHOOSE($C20,$H$3,$H$4) ))) | J20: =IF(OR(K20="VACACIONES",K20="FALTA",K20="LICENCIA",D20="",E20="",WEEKDAY($D$17,2)<=5),"",IF(WEEKDAY($D$17,2)>5,(G20*1440))) | M20: 0.30763889 | N20: 0.75 | O20: NO | P20: =IF(OR(T20="VACACIONES",T20="FALTA",T20="LICENCIA",M20="",N20=""),"",IF(WEEKDAY($M$17,2)>5,N20-M20,IF(O20="NO",MIN(N20,CHOOSE($C20,$C$3,$C$4))-MAX(M20,CHOOSE($C20,$B$3,$B$4))-CHOOSE($C20,$F$3,$F$4),N20-M20-CHOOSE($C20,$F$3,$F$4)))) -> 0.40069444 | Q20: =IF(OR(T20="VACACIONES",T20="FALTA",T20="LICENCIA",M20="",N20="",WEEKDAY($M$17,2)>5),"", MAX(0,CHOOSE($C20,$H$3,$H$4)-(P20*1440)) ) -> 0 | R20: =IF(OR(T20="VACACIONES",T20="FALTA",T20="LICENCIA",M20="",N20="",O20="NO",WEEKDAY($M$17,2)>5),"",MAX(0,IF(O20="SI", (P20*1440)-CHOOSE($C20,$H$3,$H$4) ))) | S20: =IF(OR(T20="VACACIONES",T20="FALTA",T20="LICENCIA",M20="",N20="",WEEKDAY($M$17,2)<=5),"",IF(WEEKDAY($M$17,2)>5,(P20*1440))) | V20: 0.30763889 | W20: 0.75 | X20: NO | Y20: =IF(OR(AC20="VACACIONES",AC20="FALTA",AC20="LICENCIA",V20="",W20=""),"",IF(WEEKDAY($V$17,2)>5,W20-V20,IF(X20="NO",MIN(W20,CHOOSE($C20,$C$3,$C$4))-MAX(V20,CHOOSE($C20,$B$3,$B$4))-CHOOSE($C20,$F$3,$F$4),W20-V20-CHOOSE($C20,$F$3,$F$4)))) -> 0.40069444 | Z20: =IF(OR(AC20="VACACIONES",AC20="FALTA",AC20="LICENCIA",V20="",W20="",WEEKDAY($V$17,2)>5),"", MAX(0,CHOOSE($C20,$H$3,$H$4)-(Y20*1440)) ) -> 0 | AA20: =IF(OR(AC20="VACACIONES",AC20="FALTA",AC20="LICENCIA",V20="",W20="",X20="NO",WEEKDAY($V$17,2)>5),"",MAX(0,IF(X20="SI", (Y20*1440)-CHOOSE($C20,$H$3,$H$4) ))) | AB20: =IF(OR(AC20="VACACIONES",AC20="FALTA",AC20="LICENCIA",V20="",W20="",WEEKDAY($V$17,2)<=5),"",IF(WEEKDAY($V$17,2)>5,(Y20*1440))) | AE20: 0.30763889 | AF20: 0.75 | AG20: NO | AH20: =IF(OR(AL20="VACACIONES",AL20="FALTA",AL20="LICENCIA",AE20="",AF20=""),"",IF(WEEKDAY($AE$17,2)>5,AF20-AE20,IF(AG20="NO",MIN(AF20,CHOOSE($C20,$C$3,$C$4))-MAX(AE20,CHOOSE($C20,$B$3,$B$4))-CHOOSE($C20,$F$3,$F$4),AF20-AE20-CHOOSE($C20,$F$3,$F$4)))) -> 0.40069444 | AI20: =IF(OR(AL20="VACACIONES",AL20="FALTA",AL20="LICENCIA",AE20="",AF20="",WEEKDAY($AE$17,2)>5),"", MAX(0,CHOOSE($C20,$H$3,$H$4)-(AH20*1440)) ) -> 0 | AJ20: =IF(OR(AL20="VACACIONES",AL20="FALTA",AL20="LICENCIA",AE20="",AF20="",AG20="NO",WEEKDAY($AE$17,2)>5),"",MAX(0,IF(AG20="SI", (AH20*1440)-CHOOSE($C20,$H$3,$H$4) ))) | AK20: =IF(OR(AL20="VACACIONES",AL20="FALTA",AL20="LICENCIA",AE20="",AF20="",WEEKDAY($AE$17,2)<=5),"",IF(WEEKDAY($AE$17,2)>5,(AH20*1440))) | AN20: 0.30763889 | AO20: 0.75 | AP20: NO | AQ20: =IF(OR(AU20="VACACIONES",AU20="FALTA",AU20="LICENCIA",AN20="",AO20=""),"",IF(WEEKDAY($AN$17,2)>5,AO20-AN20,IF(AP20="NO",MIN(AO20,CHOOSE($C20,$C$3,$C$4))-MAX(AN20,CHOOSE($C20,$B$3,$B$4))-CHOOSE($C20,$F$3,$F$4),AO20-AN20-CHOOSE($C20,$F$3,$F$4)))) -> 0.40069444 | AR20: =IF(OR(AU20="VACACIONES",AU20="FALTA",AU20="LICENCIA",AN20="",AO20="",WEEKDAY($AN$17,2)>5),"", MAX(0,CHOOSE($C20,$H$3,$H$4)-(AQ20*1440)) ) -> 0 | AS20: =IF(OR(AU20="VACACIONES",AU20="FALTA",AU20="LICENCIA",AN20="",AO20="",AP20="NO",WEEKDAY($AN$17,2)>5),"",MAX(0,IF(AP20="SI", (AQ20*1440)-CHOOSE($C20,$H$3,$H$4) ))) | AT20: =IF(OR(AU20="VACACIONES",AU20="FALTA",AU20="LICENCIA",AN20="",AO20="",WEEKDAY($AN$17,2)<=5),"",IF(WEEKDAY($AN$17,2)>5,(AQ20*1440))) | AZ20: =IF(OR(BD20="VACACIONES",BD20="FALTA",BD20="LICENCIA",AW20="",AX20=""),"",IF(WEEKDAY($AW$17,2)>5,AX20-AW20,IF(AY20="NO",MIN(AX20,CHOOSE($C20,$C$3,$C$4))-MAX(AW20,CHOOSE($C20,$B$3,$B$4))-CHOOSE($C20,$F$3,$F$4),AX20-AW20-CHOOSE($C20,$F$3,$F$4)))) | BA20: =IF(OR(BD20="VACACIONES",BD20="FALTA",BD20="LICENCIA",AW20="",AX20="",WEEKDAY($AW$17,2)>5),"", MAX(0,CHOOSE($C20,$H$3,$H$4)-(AZ20*1440)) ) | BB20: =IF(OR(BD20="VACACIONES",BD20="FALTA",BD20="LICENCIA",AW20="",AX20="",AY20="NO",WEEKDAY($AW$17,2)>5),"",MAX(0,IF(AY20="SI", (AZ20*1440)-CHOOSE($C20,$H$3,$H$4) ))) | BC20: =IF(OR(BD20="VACACIONES",BD20="FALTA",BD20="LICENCIA",AW20="",AX20="",WEEKDAY($AW$17,2)<=5),"",IF(WEEKDAY($AW$17,2)>5,(AZ20*1440))) | BI20: =IF(OR(BM20="VACACIONES",BM20="FALTA",BM20="LICENCIA",BF20="",BG20=""),"",IF(WEEKDAY($BF$17,2)>5,BG20-BF20,IF(BH20="NO",MIN(BG20,CHOOSE($C20,$C$3,$C$4))-MAX(BF20,CHOOSE($C20,$B$3,$B$4))-CHOOSE($C20,$F$3,$F$4),BG20-BF20-CHOOSE($C20,$F$3,$F$4)))) | BJ20: =IF(OR(BM20="VACACIONES",BM20="FALTA",BM20="LICENCIA",BF20="",BG20="",WEEKDAY($BF$17,2)>5),"", MAX(0,CHOOSE($C20,$H$3,$H$4)-(BI20*1440)) ) | BK20: =IF(OR(BM20="VACACIONES",BM20="FALTA",BM20="LICENCIA",BF20="",BG20="",BH20="NO",WEEKDAY($BF$17,2)>5),"",MAX(0,IF(BH20="SI", (BI20*1440)-CHOOSE($C20,$H$3,$H$4) ))) | BL20: =IF(OR(BM20="VACACIONES",BM20="FALTA",BM20="LICENCIA",BF20="",BG20="",WEEKDAY($BF$17,2)<=5),"",IF(WEEKDAY($BF$17,2)>5,(BI20*1440))) | BO20: 0.30763889 | BP20: 0.75 | BQ20: NO | BR20: =IF(OR(BV20="VACACIONES",BV20="FALTA",BV20="LICENCIA",BO20="",BP20=""),"",IF(WEEKDAY($BO$17,2)>5,BP20-BO20,IF(BQ20="NO",MIN(BP20,CHOOSE($C20,$C$3,$C$4))-MAX(BO20,CHOOSE($C20,$B$3,$B$4))-CHOOSE($C20,$F$3,$F$4),BP20-BO20-CHOOSE($C20,$F$3,$F$4)))) -> 0.40069444 | BS20: =IF(OR(BV20="VACACIONES",BV20="FALTA",BV20="LICENCIA",BO20="",BP20="",WEEKDAY($BO$17,2)>5),"", MAX(0,CHOOSE($C20,$H$3,$H$4)-(BR20*1440)) ) -> 0 | BT20: =IF(OR(BV20="VACACIONES",BV20="FALTA",BV20="LICENCIA",BO20="",BP20="",BQ20="NO",WEEKDAY($BO$17,2)>5),"",MAX(0,IF(BQ20="SI", (BR20*1440)-CHOOSE($C20,$H$3,$H$4) ))) | BU20: =IF(OR(BV20="VACACIONES",BV20="FALTA",BV20="LICENCIA",BO20="",BP20="",WEEKDAY($BO$17,2)<=5),"",IF(WEEKDAY($BO$17,2)>5,(BR20*1440))) | BX20: 0.30763889 | BY20: 0.75 | BZ20: NO | CA20: =IF(OR(CE20="VACACIONES",CE20="FALTA",CE20="LICENCIA",BX20="",BY20=""),"",IF(WEEKDAY($BX$17,2)>5,BY20-BX20,IF(BZ20="NO",MIN(BY20,CHOOSE($C20,$C$3,$C$4))-MAX(BX20,CHOOSE($C20,$B$3,$B$4))-CHOOSE($C20,$F$3,$F$4),BY20-BX20-CHOOSE($C20,$F$3,$F$4)))) -> 0.40069444 | CB20: =IF(OR(CE20="VACACIONES",CE20="FALTA",CE20="LICENCIA",BX20="",BY20="",WEEKDAY($BX$17,2)>5),"", MAX(0,CHOOSE($C20,$H$3,$H$4)-(CA20*1440)) ) -> 0 | CC20: =IF(OR(CE20="VACACIONES",CE20="FALTA",CE20="LICENCIA",BX20="",BY20="",BZ20="NO",WEEKDAY($BX$17,2)>5),"",MAX(0,IF(BZ20="SI", (CA20*1440)-CHOOSE($C20,$H$3,$H$4) ))) | CD20: =IF(OR(CE20="VACACIONES",CE20="FALTA",CE20="LICENCIA",BX20="",BY20="",WEEKDAY($BX$17,2)<=5),"",IF(WEEKDAY($BX$17,2)>5,(CA20*1440))) | CG20: 0.30763889 | CH20: 0.75 | CI20: NO | CJ20: =IF(OR(CN20="VACACIONES",CN20="FALTA",CN20="LICENCIA",CG20="",CH20=""),"",IF(WEEKDAY($CG$17,2)>5,CH20-CG20,IF(CI20="NO",MIN(CH20,CHOOSE($C20,$C$3,$C$4))-MAX(CG20,CHOOSE($C20,$B$3,$B$4))-CHOOSE($C20,$F$3,$F$4),CH20-CG20-CHOOSE($C20,$F$3,$F$4)))) -> 0.40069444 | CK20: =IF(OR(CN20="VACACIONES",CN20="FALTA",CN20="LICENCIA",CG20="",CH20="",WEEKDAY($CG$17,2)>5),"", MAX(0,CHOOSE($C20,$H$3,$H$4)-(CJ20*1440)) ) -> 0 | CL20: =IF(OR(CN20="VACACIONES",CN20="FALTA",CN20="LICENCIA",CG20="",CH20="",CI20="NO",WEEKDAY($CG$17,2)>5),"",MAX(0,IF(CI20="SI", (CJ20*1440)-CHOOSE($C20,$H$3,$H$4) ))) | CM20: =IF(OR(CN20="VACACIONES",CN20="FALTA",CN20="LICENCIA",CG20="",CH20="",WEEKDAY($CG$17,2)<=5),"",IF(WEEKDAY($CG$17,2)>5,(CJ20*1440))) | CP20: 0.30763889 | CQ20: 0.75 | CR20: NO | CS20: =IF(OR(CW20="VACACIONES",CW20="FALTA",CW20="LICENCIA",CP20="",CQ20=""),"",IF(WEEKDAY($CP$17,2)>5,CQ20-CP20,IF(CR20="NO",MIN(CQ20,CHOOSE($C20,$C$3,$C$4))-MAX(CP20,CHOOSE($C20,$B$3,$B$4))-CHOOSE($C20,$F$3,$F$4),CQ20-CP20-CHOOSE($C20,$F$3,$F$4)))) -> 0.40069444 | CT20: =IF(OR(CW20="VACACIONES",CW20="FALTA",CW20="LICENCIA",CP20="",CQ20="",WEEKDAY($CP$17,2)>5),"", MAX(0,CHOOSE($C20,$H$3,$H$4)-(CS20*1440)) ) -> 0 | CU20: =IF(OR(CW20="VACACIONES",CW20="FALTA",CW20="LICENCIA",CP20="",CQ20="",CR20="NO",WEEKDAY($CP$17,2)>5),"",MAX(0,IF(CR20="SI", (CS20*1440)-CHOOSE($C20,$H$3,$H$4) ))) | CV20: =IF(OR(CW20="VACACIONES",CW20="FALTA",CW20="LICENCIA",CP20="",CQ20="",WEEKDAY($CP$17,2)<=5),"",IF(WEEKDAY($CP$17,2)>5,(CS20*1440))) | CY20: 0.30763889 | CZ20: 0.75 | DA20: NO | DB20: =IF(OR(DF20="VACACIONES",DF20="FALTA",DF20="LICENCIA",CY20="",CZ20=""),"",IF(WEEKDAY($CY$17,2)>5,CZ20-CY20,IF(DA20="NO",MIN(CZ20,CHOOSE($C20,$C$3,$C$4))-MAX(CY20,CHOOSE($C20,$B$3,$B$4))-CHOOSE($C20,$F$3,$F$4),CZ20-CY20-CHOOSE($C20,$F$3,$F$4)))) -> 0.40069444 | DC20: =IF(OR(DF20="VACACIONES",DF20="FALTA",DF20="LICENCIA",CY20="",CZ20="",WEEKDAY($CY$17,2)>5),"", MAX(0,CHOOSE($C20,$H$3,$H$4)-(DB20*1440)) ) -> 0 | DD20: =IF(OR(DF20="VACACIONES",DF20="FALTA",DF20="LICENCIA",CY20="",CZ20="",DA20="NO",WEEKDAY($CY$17,2)>5),"",MAX(0,IF(DA20="SI", (DB20*1440)-CHOOSE($C20,$H$3,$H$4) ))) | DE20: =IF(OR(DF20="VACACIONES",DF20="FALTA",DF20="LICENCIA",CY20="",CZ20="",WEEKDAY($CY$17,2)<=5),"",IF(WEEKDAY($CY$17,2)>5,(DB20*1440))) | DK20: =IF(OR(DO20="VACACIONES",DO20="FALTA",DO20="LICENCIA",DH20="",DI20=""),"",IF(WEEKDAY($DH$17,2)>5,DI20-DH20,IF(DJ20="NO",MIN(DI20,CHOOSE($C20,$C$3,$C$4))-MAX(DH20,CHOOSE($C20,$B$3,$B$4))-CHOOSE($C20,$F$3,$F$4),DI20-DH20-CHOOSE($C20,$F$3,$F$4)))) | DL20: =IF(OR(DO20="VACACIONES",DO20="FALTA",DO20="LICENCIA",DH20="",DI20="",WEEKDAY($DH$17,2)>5),"", MAX(0,CHOOSE($C20,$H$3,$H$4)-(DK20*1440)) ) | DM20: =IF(OR(DO20="VACACIONES",DO20="FALTA",DO20="LICENCIA",DH20="",DI20="",DJ20="NO",WEEKDAY($DH$17,2)>5),"",MAX(0,IF(DJ20="SI", (DK20*1440)-CHOOSE($C20,$H$3,$H$4) ))) | DN20: =IF(OR(DO20="VACACIONES",DO20="FALTA",DO20="LICENCIA",DH20="",DI20="",WEEKDAY($DH$17,2)<=5),"",IF(WEEKDAY($DH$17,2)>5,(DK20*1440))) | DT20: =IF(OR(DX20="VACACIONES",DX20="FALTA",DX20="LICENCIA",DQ20="",DR20=""),"",IF(WEEKDAY($DQ$17,2)>5,DR20-DR20,IF(DS20="NO",MIN(DR20,CHOOSE($C20,$C$3,$C$4))-MAX(DQ20,CHOOSE($C20,$B$3,$B$4))-CHOOSE($C20,$F$3,$F$4),DR20-DQ20-CHOOSE($C20,$F$3,$F$4)))) | DU20: =IF(OR(DX20="VACACIONES",DX20="FALTA",DX20="LICENCIA",DQ20="",DR20="",WEEKDAY($DQ$17,2)>5),"", MAX(0,CHOOSE($C20,$H$3,$H$4)-(DT20*1440)) ) | DV20: =IF(OR(DX20="VACACIONES",DX20="FALTA",DX20="LICENCIA",DQ20="",DR20="",DS20="NO",WEEKDAY($DQ$17,2)>5),"",MAX(0,IF(DS20="SI", (DT20*1440)-CHOOSE($C20,$H$3,$H$4) ))) | DW20: =IF(OR(DX20="VACACIONES",DX20="FALTA",DX20="LICENCIA",DQ20="",DR20="",WEEKDAY($DQ$17,2)<=5),"",IF(WEEKDAY($DQ$17,2)>5,(DT20*1440))) | DZ20: 0.34930556 | EA20: 0.75 | EB20: NO | EC20: =IF(OR(EG20="VACACIONES",EG20="FALTA",EG20="LICENCIA",DZ20="",EA20=""),"",IF(WEEKDAY($CY$17,2)>5,EA20-DZ20,IF(EB20="NO",MIN(EA20,CHOOSE($C20,$C$3,$C$4))-MAX(DZ20,CHOOSE($C20,$B$3,$B$4))-CHOOSE($C20,$F$3,$F$4),EA20-DZ20-CHOOSE($C20,$F$3,$F$4)))) -> 0.35902778 | ED20: =IF(OR(EG20="VACACIONES",EG20="FALTA",EG20="LICENCIA",DZ20="",EA20="",WEEKDAY($CY$17,2)>5),"", MAX(0,CHOOSE($C20,$H$3,$H$4)-(EC20*1440)) ) -> 60 | EE20: =IF(OR(EG20="VACACIONES",EG20="FALTA",EG20="LICENCIA",DZ20="",EA20="",EB20="NO",WEEKDAY($CY$17,2)>5),"",MAX(0,IF(EB20="SI", (EC20*1440)-CHOOSE($C20,$H$3,$H$4) ))) | EF20: =IF(OR(EG20="VACACIONES",EG20="FALTA",EG20="LICENCIA",DZ20="",EA20="",WEEKDAY($CY$17,2)<=5),"",IF(WEEKDAY($CY$17,2)>5,(EC20*1440))) | EK20: =SUM(H20,Q20,Z20,AI20,AR20,BA20,BJ20,BS20,CB20,CK20,CT20,DC20,DL20,DU20,ED20) -> 60 | EL20: =SUM(I20,J20,R20,S20,AA20,AB20,AJ20,AK20,AS20,AT20,BB20,BC20,BK20,BL20,BT20,BU20,CC20,CD20,CL20,CM20,CU20,CV20,DD20,DE20,DM20,DN20,DV20,DW20,EE20,EF20) -> 0 | EM20: =COUNTIF(I20,">0")+COUNTIF(J20,">0")+COUNTIF(R20,">0")+COUNTIF(S20,">0")++COUNTIF(AA20,">0")+COUNTIF(AB20,">0")+COUNTIF(AJ20,">0")+COUNTIF(AK20,">0")+COUNTIF(AS20,">0")+COUNTIF(AT20,">0")+COUNTIF(BB20,">0")+COUNTIF(BC20,">0")+COUNTIF(BK20,">0")+COUNTIF(BL20,">0")+COUNTIF(BT20,">0")+COUNTIF(BU20,">0")+COUNTIF(CC20,">0")+COUNTIF(CD20,">0")+COUNTIF(CL20,">0")+COUNTIF(CM20,">0")+COUNTIF(CU20,">0")+COUNTIF(CV20,">0")+COUNTIF(DD20,">0")+COUNTIF(DE20,">0")+COUNTIF(DM20,">0")+COUNTIF(DN20,">0")+COUNTIF(DV20,">0")+COUNTIF(DW20,">0")+COUNTIF(EE20,">0")+COUNTIF(EF20,">0") -> 0 | EN20: =COUNTIF(D20:EG20,"FALTA") -> 0 | EO20: =15-EN20 -> 15 | EP20: =COUNTIF(D20:EG20,"TRABAJO SABADO") -> 0 | EQ20: =COUNTIF(D20:EG20,"TRABAJO DOMINGO")+COUNTIF(D20:EG20,"TRABAJO FERIADO")+(COUNTIF(D20:EG20,"TRABAJO 1RO MAYO")*2)+((COUNTIF(D22:EG22,"TRABAJO 1RO MAYO EN SU DIA LIBRE")*2)*2) -> 0 | ER20: =COUNTIF(D20:EG20,"VACACIONES") -> 0 | ES20: =COUNTIF(D20:EG20,"LICENCIA") -> 0
A21: =A20+1 -> 3 | B21: ='1RA QUINCENA JUNIO 26'!B12 -> CISNEROS SUMA, EDGAR | C21: 1 | D21: 0.31527778 | E21: 0.76180556 | F21: NO | G21: =IF(OR(K21="VACACIONES",K21="FALTA",K21="LICENCIA",D21="",E21=""),"",IF(WEEKDAY($D$17,2)>5,E21-D21,IF(F21="NO",MIN(E21,CHOOSE($C21,$C$3,$C$4))-MAX(D21,CHOOSE($C21,$B$3,$B$4))-CHOOSE($C21,$F$3,$F$4),E21-D21-CHOOSE($C21,$F$3,$F$4)))) -> 0.39305556 | H21: =IF(OR(K21="VACACIONES",K21="FALTA",K21="LICENCIA",D21="",E21="",WEEKDAY($D$17,2)>5),"", MAX(0,CHOOSE($C21,$H$3,$H$4)-(G21*1440)) ) -> 11 | I21: =IF(OR(K21="VACACIONES",K21="FALTA",K21="LICENCIA",D21="",E21="",F21="NO",WEEKDAY($D$17,2)>5),"",MAX(0,IF(F21="SI", (G21*1440)-CHOOSE($C21,$H$3,$H$4) ))) | J21: =IF(OR(K21="VACACIONES",K21="FALTA",K21="LICENCIA",D21="",E21="",WEEKDAY($D$17,2)<=5),"",IF(WEEKDAY($D$17,2)>5,(G21*1440))) | M21: 0.30902778 | N21: 0.75972222 | O21: NO | P21: =IF(OR(T21="VACACIONES",T21="FALTA",T21="LICENCIA",M21="",N21=""),"",IF(WEEKDAY($M$17,2)>5,N21-M21,IF(O21="NO",MIN(N21,CHOOSE($C21,$C$3,$C$4))-MAX(M21,CHOOSE($C21,$B$3,$B$4))-CHOOSE($C21,$F$3,$F$4),N21-M21-CHOOSE($C21,$F$3,$F$4)))) -> 0.39930556 | Q21: =IF(OR(T21="VACACIONES",T21="FALTA",T21="LICENCIA",M21="",N21="",WEEKDAY($M$17,2)>5),"", MAX(0,CHOOSE($C21,$H$3,$H$4)-(P21*1440)) ) -> 2 | R21: =IF(OR(T21="VACACIONES",T21="FALTA",T21="LICENCIA",M21="",N21="",O21="NO",WEEKDAY($M$17,2)>5),"",MAX(0,IF(O21="SI", (P21*1440)-CHOOSE($C21,$H$3,$H$4) ))) | S21: =IF(OR(T21="VACACIONES",T21="FALTA",T21="LICENCIA",M21="",N21="",WEEKDAY($M$17,2)<=5),"",IF(WEEKDAY($M$17,2)>5,(P21*1440))) | V21: 0.32361111 | W21: 0.76041667 | X21: NO | Y21: =IF(OR(AC21="VACACIONES",AC21="FALTA",AC21="LICENCIA",V21="",W21=""),"",IF(WEEKDAY($V$17,2)>5,W21-V21,IF(X21="NO",MIN(W21,CHOOSE($C21,$C$3,$C$4))-MAX(V21,CHOOSE($C21,$B$3,$B$4))-CHOOSE($C21,$F$3,$F$4),W21-V21-CHOOSE($C21,$F$3,$F$4)))) -> 0.38472222 | Z21: =IF(OR(AC21="VACACIONES",AC21="FALTA",AC21="LICENCIA",V21="",W21="",WEEKDAY($V$17,2)>5),"", MAX(0,CHOOSE($C21,$H$3,$H$4)-(Y21*1440)) ) -> 23 | AA21: =IF(OR(AC21="VACACIONES",AC21="FALTA",AC21="LICENCIA",V21="",W21="",X21="NO",WEEKDAY($V$17,2)>5),"",MAX(0,IF(X21="SI", (Y21*1440)-CHOOSE($C21,$H$3,$H$4) ))) | AB21: =IF(OR(AC21="VACACIONES",AC21="FALTA",AC21="LICENCIA",V21="",W21="",WEEKDAY($V$17,2)<=5),"",IF(WEEKDAY($V$17,2)>5,(Y21*1440))) | AE21: 0.31527778 | AF21: 0.75694444 | AG21: NO | AH21: =IF(OR(AL21="VACACIONES",AL21="FALTA",AL21="LICENCIA",AE21="",AF21=""),"",IF(WEEKDAY($AE$17,2)>5,AF21-AE21,IF(AG21="NO",MIN(AF21,CHOOSE($C21,$C$3,$C$4))-MAX(AE21,CHOOSE($C21,$B$3,$B$4))-CHOOSE($C21,$F$3,$F$4),AF21-AE21-CHOOSE($C21,$F$3,$F$4)))) -> 0.39305556 | AI21: =IF(OR(AL21="VACACIONES",AL21="FALTA",AL21="LICENCIA",AE21="",AF21="",WEEKDAY($AE$17,2)>5),"", MAX(0,CHOOSE($C21,$H$3,$H$4)-(AH21*1440)) ) -> 11 | AJ21: =IF(OR(AL21="VACACIONES",AL21="FALTA",AL21="LICENCIA",AE21="",AF21="",AG21="NO",WEEKDAY($AE$17,2)>5),"",MAX(0,IF(AG21="SI", (AH21*1440)-CHOOSE($C21,$H$3,$H$4) ))) | AK21: =IF(OR(AL21="VACACIONES",AL21="FALTA",AL21="LICENCIA",AE21="",AF21="",WEEKDAY($AE$17,2)<=5),"",IF(WEEKDAY($AE$17,2)>5,(AH21*1440))) | AN21: 0.31944444 | AO21: 0.76458333 | AP21: NO | AQ21: =IF(OR(AU21="VACACIONES",AU21="FALTA",AU21="LICENCIA",AN21="",AO21=""),"",IF(WEEKDAY($AN$17,2)>5,AO21-AN21,IF(AP21="NO",MIN(AO21,CHOOSE($C21,$C$3,$C$4))-MAX(AN21,CHOOSE($C21,$B$3,$B$4))-CHOOSE($C21,$F$3,$F$4),AO21-AN21-CHOOSE($C21,$F$3,$F$4)))) -> 0.38888889 | AR21: =IF(OR(AU21="VACACIONES",AU21="FALTA",AU21="LICENCIA",AN21="",AO21="",WEEKDAY($AN$17,2)>5),"", MAX(0,CHOOSE($C21,$H$3,$H$4)-(AQ21*1440)) ) -> 17 | AS21: =IF(OR(AU21="VACACIONES",AU21="FALTA",AU21="LICENCIA",AN21="",AO21="",AP21="NO",WEEKDAY($AN$17,2)>5),"",MAX(0,IF(AP21="SI", (AQ21*1440)-CHOOSE($C21,$H$3,$H$4) ))) | AT21: =IF(OR(AU21="VACACIONES",AU21="FALTA",AU21="LICENCIA",AN21="",AO21="",WEEKDAY($AN$17,2)<=5),"",IF(WEEKDAY($AN$17,2)>5,(AQ21*1440))) | AW21: 0.3125 | AX21: 0.54513889 | AZ21: =IF(OR(BD21="VACACIONES",BD21="FALTA",BD21="LICENCIA",AW21="",AX21=""),"",IF(WEEKDAY($AW$17,2)>5,AX21-AW21,IF(AY21="NO",MIN(AX21,CHOOSE($C21,$C$3,$C$4))-MAX(AW21,CHOOSE($C21,$B$3,$B$4))-CHOOSE($C21,$F$3,$F$4),AX21-AW21-CHOOSE($C21,$F$3,$F$4)))) -> 0.23263889 | BA21: =IF(OR(BD21="VACACIONES",BD21="FALTA",BD21="LICENCIA",AW21="",AX21="",WEEKDAY($AW$17,2)>5),"", MAX(0,CHOOSE($C21,$H$3,$H$4)-(AZ21*1440)) ) | BB21: =IF(OR(BD21="VACACIONES",BD21="FALTA",BD21="LICENCIA",AW21="",AX21="",AY21="NO",WEEKDAY($AW$17,2)>5),"",MAX(0,IF(AY21="SI", (AZ21*1440)-CHOOSE($C21,$H$3,$H$4) ))) | BC21: =IF(OR(BD21="VACACIONES",BD21="FALTA",BD21="LICENCIA",AW21="",AX21="",WEEKDAY($AW$17,2)<=5),"",IF(WEEKDAY($AW$17,2)>5,(AZ21*1440))) -> 335 | BD21: TRABAJO SABADO | BI21: =IF(OR(BM21="VACACIONES",BM21="FALTA",BM21="LICENCIA",BF21="",BG21=""),"",IF(WEEKDAY($BF$17,2)>5,BG21-BF21,IF(BH21="NO",MIN(BG21,CHOOSE($C21,$C$3,$C$4))-MAX(BF21,CHOOSE($C21,$B$3,$B$4))-CHOOSE($C21,$F$3,$F$4),BG21-BF21-CHOOSE($C21,$F$3,$F$4)))) | BJ21: =IF(OR(BM21="VACACIONES",BM21="FALTA",BM21="LICENCIA",BF21="",BG21="",WEEKDAY($BF$17,2)>5),"", MAX(0,CHOOSE($C21,$H$3,$H$4)-(BI21*1440)) ) | BK21: =IF(OR(BM21="VACACIONES",BM21="FALTA",BM21="LICENCIA",BF21="",BG21="",BH21="NO",WEEKDAY($BF$17,2)>5),"",MAX(0,IF(BH21="SI", (BI21*1440)-CHOOSE($C21,$H$3,$H$4) ))) | BL21: =IF(OR(BM21="VACACIONES",BM21="FALTA",BM21="LICENCIA",BF21="",BG21="",WEEKDAY($BF$17,2)<=5),"",IF(WEEKDAY($BF$17,2)>5,(BI21*1440))) | BO21: 0.32013889 | BP21: 0.69444444 | BQ21: NO | BR21: =IF(OR(BV21="VACACIONES",BV21="FALTA",BV21="LICENCIA",BO21="",BP21=""),"",IF(WEEKDAY($BO$17,2)>5,BP21-BO21,IF(BQ21="NO",MIN(BP21,CHOOSE($C21,$C$3,$C$4))-MAX(BO21,CHOOSE($C21,$B$3,$B$4))-CHOOSE($C21,$F$3,$F$4),BP21-BO21-CHOOSE($C21,$F$3,$F$4)))) -> 0.33263889 | BS21: =IF(OR(BV21="VACACIONES",BV21="FALTA",BV21="LICENCIA",BO21="",BP21="",WEEKDAY($BO$17,2)>5),"", MAX(0,CHOOSE($C21,$H$3,$H$4)-(BR21*1440)) ) -> 98 | BT21: =IF(OR(BV21="VACACIONES",BV21="FALTA",BV21="LICENCIA",BO21="",BP21="",BQ21="NO",WEEKDAY($BO$17,2)>5),"",MAX(0,IF(BQ21="SI", (BR21*1440)-CHOOSE($C21,$H$3,$H$4) ))) | BU21: =IF(OR(BV21="VACACIONES",BV21="FALTA",BV21="LICENCIA",BO21="",BP21="",WEEKDAY($BO$17,2)<=5),"",IF(WEEKDAY($BO$17,2)>5,(BR21*1440))) | BX21: 0.31666667 | BY21: 0.76111111 | BZ21: NO | CA21: =IF(OR(CE21="VACACIONES",CE21="FALTA",CE21="LICENCIA",BX21="",BY21=""),"",IF(WEEKDAY($BX$17,2)>5,BY21-BX21,IF(BZ21="NO",MIN(BY21,CHOOSE($C21,$C$3,$C$4))-MAX(BX21,CHOOSE($C21,$B$3,$B$4))-CHOOSE($C21,$F$3,$F$4),BY21-BX21-CHOOSE($C21,$F$3,$F$4)))) -> 0.39166667 | CB21: =IF(OR(CE21="VACACIONES",CE21="FALTA",CE21="LICENCIA",BX21="",BY21="",WEEKDAY($BX$17,2)>5),"", MAX(0,CHOOSE($C21,$H$3,$H$4)-(CA21*1440)) ) -> 13 | CC21: =IF(OR(CE21="VACACIONES",CE21="FALTA",CE21="LICENCIA",BX21="",BY21="",BZ21="NO",WEEKDAY($BX$17,2)>5),"",MAX(0,IF(BZ21="SI", (CA21*1440)-CHOOSE($C21,$H$3,$H$4) ))) | CD21: =IF(OR(CE21="VACACIONES",CE21="FALTA",CE21="LICENCIA",BX21="",BY21="",WEEKDAY($BX$17,2)<=5),"",IF(WEEKDAY($BX$17,2)>5,(CA21*1440))) | CG21: 0.32986111 | CH21: 0.75902778 | CI21: NO | CJ21: =IF(OR(CN21="VACACIONES",CN21="FALTA",CN21="LICENCIA",CG21="",CH21=""),"",IF(WEEKDAY($CG$17,2)>5,CH21-CG21,IF(CI21="NO",MIN(CH21,CHOOSE($C21,$C$3,$C$4))-MAX(CG21,CHOOSE($C21,$B$3,$B$4))-CHOOSE($C21,$F$3,$F$4),CH21-CG21-CHOOSE($C21,$F$3,$F$4)))) -> 0.37847222 | CK21: =IF(OR(CN21="VACACIONES",CN21="FALTA",CN21="LICENCIA",CG21="",CH21="",WEEKDAY($CG$17,2)>5),"", MAX(0,CHOOSE($C21,$H$3,$H$4)-(CJ21*1440)) ) -> 32 | CL21: =IF(OR(CN21="VACACIONES",CN21="FALTA",CN21="LICENCIA",CG21="",CH21="",CI21="NO",WEEKDAY($CG$17,2)>5),"",MAX(0,IF(CI21="SI", (CJ21*1440)-CHOOSE($C21,$H$3,$H$4) ))) | CM21: =IF(OR(CN21="VACACIONES",CN21="FALTA",CN21="LICENCIA",CG21="",CH21="",WEEKDAY($CG$17,2)<=5),"",IF(WEEKDAY($CG$17,2)>5,(CJ21*1440))) | CP21: 0.3125 | CQ21: 0.76388889 | CR21: NO | CS21: =IF(OR(CW21="VACACIONES",CW21="FALTA",CW21="LICENCIA",CP21="",CQ21=""),"",IF(WEEKDAY($CP$17,2)>5,CQ21-CP21,IF(CR21="NO",MIN(CQ21,CHOOSE($C21,$C$3,$C$4))-MAX(CP21,CHOOSE($C21,$B$3,$B$4))-CHOOSE($C21,$F$3,$F$4),CQ21-CP21-CHOOSE($C21,$F$3,$F$4)))) -> 0.39583333 | CT21: =IF(OR(CW21="VACACIONES",CW21="FALTA",CW21="LICENCIA",CP21="",CQ21="",WEEKDAY($CP$17,2)>5),"", MAX(0,CHOOSE($C21,$H$3,$H$4)-(CS21*1440)) ) -> 7 | CU21: =IF(OR(CW21="VACACIONES",CW21="FALTA",CW21="LICENCIA",CP21="",CQ21="",CR21="NO",WEEKDAY($CP$17,2)>5),"",MAX(0,IF(CR21="SI", (CS21*1440)-CHOOSE($C21,$H$3,$H$4) ))) | CV21: =IF(OR(CW21="VACACIONES",CW21="FALTA",CW21="LICENCIA",CP21="",CQ21="",WEEKDAY($CP$17,2)<=5),"",IF(WEEKDAY($CP$17,2)>5,(CS21*1440))) | CY21: 0.31180556 | CZ21: 0.76319444 | DA21: NO | DB21: =IF(OR(DF21="VACACIONES",DF21="FALTA",DF21="LICENCIA",CY21="",CZ21=""),"",IF(WEEKDAY($CY$17,2)>5,CZ21-CY21,IF(DA21="NO",MIN(CZ21,CHOOSE($C21,$C$3,$C$4))-MAX(CY21,CHOOSE($C21,$B$3,$B$4))-CHOOSE($C21,$F$3,$F$4),CZ21-CY21-CHOOSE($C21,$F$3,$F$4)))) -> 0.39652778 | DC21: =IF(OR(DF21="VACACIONES",DF21="FALTA",DF21="LICENCIA",CY21="",CZ21="",WEEKDAY($CY$17,2)>5),"", MAX(0,CHOOSE($C21,$H$3,$H$4)-(DB21*1440)) ) -> 6 | DD21: =IF(OR(DF21="VACACIONES",DF21="FALTA",DF21="LICENCIA",CY21="",CZ21="",DA21="NO",WEEKDAY($CY$17,2)>5),"",MAX(0,IF(DA21="SI", (DB21*1440)-CHOOSE($C21,$H$3,$H$4) ))) | DE21: =IF(OR(DF21="VACACIONES",DF21="FALTA",DF21="LICENCIA",CY21="",CZ21="",WEEKDAY($CY$17,2)<=5),"",IF(WEEKDAY($CY$17,2)>5,(DB21*1440))) | DH21: 0.3125 | DI21: 0.54861111 | DK21: =IF(OR(DO21="VACACIONES",DO21="FALTA",DO21="LICENCIA",DH21="",DI21=""),"",IF(WEEKDAY($DH$17,2)>5,DI21-DH21,IF(DJ21="NO",MIN(DI21,CHOOSE($C21,$C$3,$C$4))-MAX(DH21,CHOOSE($C21,$B$3,$B$4))-CHOOSE($C21,$F$3,$F$4),DI21-DH21-CHOOSE($C21,$F$3,$F$4)))) -> 0.23611111 | DL21: =IF(OR(DO21="VACACIONES",DO21="FALTA",DO21="LICENCIA",DH21="",DI21="",WEEKDAY($DH$17,2)>5),"", MAX(0,CHOOSE($C21,$H$3,$H$4)-(DK21*1440)) ) | DM21: =IF(OR(DO21="VACACIONES",DO21="FALTA",DO21="LICENCIA",DH21="",DI21="",DJ21="NO",WEEKDAY($DH$17,2)>5),"",MAX(0,IF(DJ21="SI", (DK21*1440)-CHOOSE($C21,$H$3,$H$4) ))) | DN21: =IF(OR(DO21="VACACIONES",DO21="FALTA",DO21="LICENCIA",DH21="",DI21="",WEEKDAY($DH$17,2)<=5),"",IF(WEEKDAY($DH$17,2)>5,(DK21*1440))) -> 340 | DO21: TRABAJO SABADO | DT21: =IF(OR(DX21="VACACIONES",DX21="FALTA",DX21="LICENCIA",DQ21="",DR21=""),"",IF(WEEKDAY($DQ$17,2)>5,DR21-DR21,IF(DS21="NO",MIN(DR21,CHOOSE($C21,$C$3,$C$4))-MAX(DQ21,CHOOSE($C21,$B$3,$B$4))-CHOOSE($C21,$F$3,$F$4),DR21-DQ21-CHOOSE($C21,$F$3,$F$4)))) | DU21: =IF(OR(DX21="VACACIONES",DX21="FALTA",DX21="LICENCIA",DQ21="",DR21="",WEEKDAY($DQ$17,2)>5),"", MAX(0,CHOOSE($C21,$H$3,$H$4)-(DT21*1440)) ) | DV21: =IF(OR(DX21="VACACIONES",DX21="FALTA",DX21="LICENCIA",DQ21="",DR21="",DS21="NO",WEEKDAY($DQ$17,2)>5),"",MAX(0,IF(DS21="SI", (DT21*1440)-CHOOSE($C21,$H$3,$H$4) ))) | DW21: =IF(OR(DX21="VACACIONES",DX21="FALTA",DX21="LICENCIA",DQ21="",DR21="",WEEKDAY($DQ$17,2)<=5),"",IF(WEEKDAY($DQ$17,2)>5,(DT21*1440))) | DZ21: 0.31458333 | EA21: 0.76319444 | EB21: NO | EC21: =IF(OR(EG21="VACACIONES",EG21="FALTA",EG21="LICENCIA",DZ21="",EA21=""),"",IF(WEEKDAY($CY$17,2)>5,EA21-DZ21,IF(EB21="NO",MIN(EA21,CHOOSE($C21,$C$3,$C$4))-MAX(DZ21,CHOOSE($C21,$B$3,$B$4))-CHOOSE($C21,$F$3,$F$4),EA21-DZ21-CHOOSE($C21,$F$3,$F$4)))) -> 0.39375 | ED21: =IF(OR(EG21="VACACIONES",EG21="FALTA",EG21="LICENCIA",DZ21="",EA21="",WEEKDAY($CY$17,2)>5),"", MAX(0,CHOOSE($C21,$H$3,$H$4)-(EC21*1440)) ) -> 10 | EE21: =IF(OR(EG21="VACACIONES",EG21="FALTA",EG21="LICENCIA",DZ21="",EA21="",EB21="NO",WEEKDAY($CY$17,2)>5),"",MAX(0,IF(EB21="SI", (EC21*1440)-CHOOSE($C21,$H$3,$H$4) ))) | EF21: =IF(OR(EG21="VACACIONES",EG21="FALTA",EG21="LICENCIA",DZ21="",EA21="",WEEKDAY($CY$17,2)<=5),"",IF(WEEKDAY($CY$17,2)>5,(EC21*1440))) | EK21: 0 | EL21: =SUM(I21,R21,AA21,AJ21,AS21,BB21,BK21,BT21,CC21,CL21,CU21,DD21,DM21,DV21,EE21) -> 0 | EM21: 0 | EN21: =COUNTIF(D21:EG21,"FALTA") -> 0 | EO21: =15-EN21 -> 15 | EP21: =COUNTIF(D21:EG21,"TRABAJO SABADO") -> 2 | EQ21: =COUNTIF(D21:EG21,"TRABAJO DOMINGO")+COUNTIF(D21:EG21,"TRABAJO FERIADO")+(COUNTIF(D21:EG21,"TRABAJO 1RO MAYO")*2)+((COUNTIF(D23:EG23,"TRABAJO 1RO MAYO EN SU DIA LIBRE")*2)*2) -> 0 | ER21: =COUNTIF(D21:EG21,"VACACIONES") -> 0 | ES21: =COUNTIF(D21:EG21,"LICENCIA") -> 0
A22: =A21+1 -> 4 | B22: ='1RA QUINCENA JUNIO 26'!B13 -> CORI ADAN RUTBEL | C22: 1 | D22: 0.30763889 | E22: 0.77083333 | F22: NO | G22: =IF(OR(K22="VACACIONES",K22="FALTA",K22="LICENCIA",D22="",E22=""),"",IF(WEEKDAY($D$17,2)>5,E22-D22,IF(F22="NO",MIN(E22,CHOOSE($C22,$C$3,$C$4))-MAX(D22,CHOOSE($C22,$B$3,$B$4))-CHOOSE($C22,$F$3,$F$4),E22-D22-CHOOSE($C22,$F$3,$F$4)))) -> 0.40069444 | H22: =IF(OR(K22="VACACIONES",K22="FALTA",K22="LICENCIA",D22="",E22="",WEEKDAY($D$17,2)>5),"", MAX(0,CHOOSE($C22,$H$3,$H$4)-(G22*1440)) ) -> 0 | I22: =IF(OR(K22="VACACIONES",K22="FALTA",K22="LICENCIA",D22="",E22="",F22="NO",WEEKDAY($D$17,2)>5),"",MAX(0,IF(F22="SI", (G22*1440)-CHOOSE($C22,$H$3,$H$4) ))) | J22: =IF(OR(K22="VACACIONES",K22="FALTA",K22="LICENCIA",D22="",E22="",WEEKDAY($D$17,2)<=5),"",IF(WEEKDAY($D$17,2)>5,(G22*1440))) | M22: 0.30763889 | N22: 0.76944444 | O22: NO | P22: =IF(OR(T22="VACACIONES",T22="FALTA",T22="LICENCIA",M22="",N22=""),"",IF(WEEKDAY($M$17,2)>5,N22-M22,IF(O22="NO",MIN(N22,CHOOSE($C22,$C$3,$C$4))-MAX(M22,CHOOSE($C22,$B$3,$B$4))-CHOOSE($C22,$F$3,$F$4),N22-M22-CHOOSE($C22,$F$3,$F$4)))) -> 0.40069444 | Q22: =IF(OR(T22="VACACIONES",T22="FALTA",T22="LICENCIA",M22="",N22="",WEEKDAY($M$17,2)>5),"", MAX(0,CHOOSE($C22,$H$3,$H$4)-(P22*1440)) ) -> 0 | R22: =IF(OR(T22="VACACIONES",T22="FALTA",T22="LICENCIA",M22="",N22="",O22="NO",WEEKDAY($M$17,2)>5),"",MAX(0,IF(O22="SI", (P22*1440)-CHOOSE($C22,$H$3,$H$4) ))) | S22: =IF(OR(T22="VACACIONES",T22="FALTA",T22="LICENCIA",M22="",N22="",WEEKDAY($M$17,2)<=5),"",IF(WEEKDAY($M$17,2)>5,(P22*1440))) | V22: 0.30763889 | W22: 0.76041667 | X22: NO | Y22: =IF(OR(AC22="VACACIONES",AC22="FALTA",AC22="LICENCIA",V22="",W22=""),"",IF(WEEKDAY($V$17,2)>5,W22-V22,IF(X22="NO",MIN(W22,CHOOSE($C22,$C$3,$C$4))-MAX(V22,CHOOSE($C22,$B$3,$B$4))-CHOOSE($C22,$F$3,$F$4),W22-V22-CHOOSE($C22,$F$3,$F$4)))) -> 0.40069444 | Z22: =IF(OR(AC22="VACACIONES",AC22="FALTA",AC22="LICENCIA",V22="",W22="",WEEKDAY($V$17,2)>5),"", MAX(0,CHOOSE($C22,$H$3,$H$4)-(Y22*1440)) ) -> 0 | AA22: =IF(OR(AC22="VACACIONES",AC22="FALTA",AC22="LICENCIA",V22="",W22="",X22="NO",WEEKDAY($V$17,2)>5),"",MAX(0,IF(X22="SI", (Y22*1440)-CHOOSE($C22,$H$3,$H$4) ))) | AB22: =IF(OR(AC22="VACACIONES",AC22="FALTA",AC22="LICENCIA",V22="",W22="",WEEKDAY($V$17,2)<=5),"",IF(WEEKDAY($V$17,2)>5,(Y22*1440))) | AE22: 0.30763889 | AF22: 0.76875 | AG22: NO | AH22: =IF(OR(AL22="VACACIONES",AL22="FALTA",AL22="LICENCIA",AE22="",AF22=""),"",IF(WEEKDAY($AE$17,2)>5,AF22-AE22,IF(AG22="NO",MIN(AF22,CHOOSE($C22,$C$3,$C$4))-MAX(AE22,CHOOSE($C22,$B$3,$B$4))-CHOOSE($C22,$F$3,$F$4),AF22-AE22-CHOOSE($C22,$F$3,$F$4)))) -> 0.40069444 | AI22: =IF(OR(AL22="VACACIONES",AL22="FALTA",AL22="LICENCIA",AE22="",AF22="",WEEKDAY($AE$17,2)>5),"", MAX(0,CHOOSE($C22,$H$3,$H$4)-(AH22*1440)) ) -> 0 | AJ22: =IF(OR(AL22="VACACIONES",AL22="FALTA",AL22="LICENCIA",AE22="",AF22="",AG22="NO",WEEKDAY($AE$17,2)>5),"",MAX(0,IF(AG22="SI", (AH22*1440)-CHOOSE($C22,$H$3,$H$4) ))) | AK22: =IF(OR(AL22="VACACIONES",AL22="FALTA",AL22="LICENCIA",AE22="",AF22="",WEEKDAY($AE$17,2)<=5),"",IF(WEEKDAY($AE$17,2)>5,(AH22*1440))) | AN22: 0.30763889 | AO22: 0.77083333 | AP22: NO | AQ22: =IF(OR(AU22="VACACIONES",AU22="FALTA",AU22="LICENCIA",AN22="",AO22=""),"",IF(WEEKDAY($AN$17,2)>5,AO22-AN22,IF(AP22="NO",MIN(AO22,CHOOSE($C22,$C$3,$C$4))-MAX(AN22,CHOOSE($C22,$B$3,$B$4))-CHOOSE($C22,$F$3,$F$4),AO22-AN22-CHOOSE($C22,$F$3,$F$4)))) -> 0.40069444 | AR22: =IF(OR(AU22="VACACIONES",AU22="FALTA",AU22="LICENCIA",AN22="",AO22="",WEEKDAY($AN$17,2)>5),"", MAX(0,CHOOSE($C22,$H$3,$H$4)-(AQ22*1440)) ) -> 0 | AS22: =IF(OR(AU22="VACACIONES",AU22="FALTA",AU22="LICENCIA",AN22="",AO22="",AP22="NO",WEEKDAY($AN$17,2)>5),"",MAX(0,IF(AP22="SI", (AQ22*1440)-CHOOSE($C22,$H$3,$H$4) ))) | AT22: =IF(OR(AU22="VACACIONES",AU22="FALTA",AU22="LICENCIA",AN22="",AO22="",WEEKDAY($AN$17,2)<=5),"",IF(WEEKDAY($AN$17,2)>5,(AQ22*1440))) | AZ22: =IF(OR(BD22="VACACIONES",BD22="FALTA",BD22="LICENCIA",AW22="",AX22=""),"",IF(WEEKDAY($AW$17,2)>5,AX22-AW22,IF(AY22="NO",MIN(AX22,CHOOSE($C22,$C$3,$C$4))-MAX(AW22,CHOOSE($C22,$B$3,$B$4))-CHOOSE($C22,$F$3,$F$4),AX22-AW22-CHOOSE($C22,$F$3,$F$4)))) | BA22: =IF(OR(BD22="VACACIONES",BD22="FALTA",BD22="LICENCIA",AW22="",AX22="",WEEKDAY($AW$17,2)>5),"", MAX(0,CHOOSE($C22,$H$3,$H$4)-(AZ22*1440)) ) | BB22: =IF(OR(BD22="VACACIONES",BD22="FALTA",BD22="LICENCIA",AW22="",AX22="",AY22="NO",WEEKDAY($AW$17,2)>5),"",MAX(0,IF(AY22="SI", (AZ22*1440)-CHOOSE($C22,$H$3,$H$4) ))) | BC22: =IF(OR(BD22="VACACIONES",BD22="FALTA",BD22="LICENCIA",AW22="",AX22="",WEEKDAY($AW$17,2)<=5),"",IF(WEEKDAY($AW$17,2)>5,(AZ22*1440))) | BI22: =IF(OR(BM22="VACACIONES",BM22="FALTA",BM22="LICENCIA",BF22="",BG22=""),"",IF(WEEKDAY($BF$17,2)>5,BG22-BF22,IF(BH22="NO",MIN(BG22,CHOOSE($C22,$C$3,$C$4))-MAX(BF22,CHOOSE($C22,$B$3,$B$4))-CHOOSE($C22,$F$3,$F$4),BG22-BF22-CHOOSE($C22,$F$3,$F$4)))) | BJ22: =IF(OR(BM22="VACACIONES",BM22="FALTA",BM22="LICENCIA",BF22="",BG22="",WEEKDAY($BF$17,2)>5),"", MAX(0,CHOOSE($C22,$H$3,$H$4)-(BI22*1440)) ) | BK22: =IF(OR(BM22="VACACIONES",BM22="FALTA",BM22="LICENCIA",BF22="",BG22="",BH22="NO",WEEKDAY($BF$17,2)>5),"",MAX(0,IF(BH22="SI", (BI22*1440)-CHOOSE($C22,$H$3,$H$4) ))) | BL22: =IF(OR(BM22="VACACIONES",BM22="FALTA",BM22="LICENCIA",BF22="",BG22="",WEEKDAY($BF$17,2)<=5),"",IF(WEEKDAY($BF$17,2)>5,(BI22*1440))) | BO22: 0.30763889 | BP22: 0.77222222 | BQ22: NO | BR22: =IF(OR(BV22="VACACIONES",BV22="FALTA",BV22="LICENCIA",BO22="",BP22=""),"",IF(WEEKDAY($BO$17,2)>5,BP22-BO22,IF(BQ22="NO",MIN(BP22,CHOOSE($C22,$C$3,$C$4))-MAX(BO22,CHOOSE($C22,$B$3,$B$4))-CHOOSE($C22,$F$3,$F$4),BP22-BO22-CHOOSE($C22,$F$3,$F$4)))) -> 0.40069444 | BS22: =IF(OR(BV22="VACACIONES",BV22="FALTA",BV22="LICENCIA",BO22="",BP22="",WEEKDAY($BO$17,2)>5),"", MAX(0,CHOOSE($C22,$H$3,$H$4)-(BR22*1440)) ) -> 0 | BT22: =IF(OR(BV22="VACACIONES",BV22="FALTA",BV22="LICENCIA",BO22="",BP22="",BQ22="NO",WEEKDAY($BO$17,2)>5),"",MAX(0,IF(BQ22="SI", (BR22*1440)-CHOOSE($C22,$H$3,$H$4) ))) | BU22: =IF(OR(BV22="VACACIONES",BV22="FALTA",BV22="LICENCIA",BO22="",BP22="",WEEKDAY($BO$17,2)<=5),"",IF(WEEKDAY($BO$17,2)>5,(BR22*1440))) | BX22: 0.30763889 | BY22: 0.76944444 | BZ22: NO | CA22: =IF(OR(CE22="VACACIONES",CE22="FALTA",CE22="LICENCIA",BX22="",BY22=""),"",IF(WEEKDAY($BX$17,2)>5,BY22-BX22,IF(BZ22="NO",MIN(BY22,CHOOSE($C22,$C$3,$C$4))-MAX(BX22,CHOOSE($C22,$B$3,$B$4))-CHOOSE($C22,$F$3,$F$4),BY22-BX22-CHOOSE($C22,$F$3,$F$4)))) -> 0.40069444 | CB22: =IF(OR(CE22="VACACIONES",CE22="FALTA",CE22="LICENCIA",BX22="",BY22="",WEEKDAY($BX$17,2)>5),"", MAX(0,CHOOSE($C22,$H$3,$H$4)-(CA22*1440)) ) -> 0 | CC22: =IF(OR(CE22="VACACIONES",CE22="FALTA",CE22="LICENCIA",BX22="",BY22="",BZ22="NO",WEEKDAY($BX$17,2)>5),"",MAX(0,IF(BZ22="SI", (CA22*1440)-CHOOSE($C22,$H$3,$H$4) ))) | CD22: =IF(OR(CE22="VACACIONES",CE22="FALTA",CE22="LICENCIA",BX22="",BY22="",WEEKDAY($BX$17,2)<=5),"",IF(WEEKDAY($BX$17,2)>5,(CA22*1440))) | CG22: 0.28472222 | CH22: 0.76736111 | CI22: NO | CJ22: =IF(OR(CN22="VACACIONES",CN22="FALTA",CN22="LICENCIA",CG22="",CH22=""),"",IF(WEEKDAY($CG$17,2)>5,CH22-CG22,IF(CI22="NO",MIN(CH22,CHOOSE($C22,$C$3,$C$4))-MAX(CG22,CHOOSE($C22,$B$3,$B$4))-CHOOSE($C22,$F$3,$F$4),CH22-CG22-CHOOSE($C22,$F$3,$F$4)))) -> 0.40069444 | CK22: =IF(OR(CN22="VACACIONES",CN22="FALTA",CN22="LICENCIA",CG22="",CH22="",WEEKDAY($CG$17,2)>5),"", MAX(0,CHOOSE($C22,$H$3,$H$4)-(CJ22*1440)) ) -> 0 | CL22: =IF(OR(CN22="VACACIONES",CN22="FALTA",CN22="LICENCIA",CG22="",CH22="",CI22="NO",WEEKDAY($CG$17,2)>5),"",MAX(0,IF(CI22="SI", (CJ22*1440)-CHOOSE($C22,$H$3,$H$4) ))) | CM22: =IF(OR(CN22="VACACIONES",CN22="FALTA",CN22="LICENCIA",CG22="",CH22="",WEEKDAY($CG$17,2)<=5),"",IF(WEEKDAY($CG$17,2)>5,(CJ22*1440))) | CP22: 0.42638889 | CQ22: 0.76388889 | CR22: NO | CS22: =IF(OR(CW22="VACACIONES",CW22="FALTA",CW22="LICENCIA",CP22="",CQ22=""),"",IF(WEEKDAY($CP$17,2)>5,CQ22-CP22,IF(CR22="NO",MIN(CQ22,CHOOSE($C22,$C$3,$C$4))-MAX(CP22,CHOOSE($C22,$B$3,$B$4))-CHOOSE($C22,$F$3,$F$4),CQ22-CP22-CHOOSE($C22,$F$3,$F$4)))) -> 0.28194444 | CT22: =IF(OR(CW22="VACACIONES",CW22="FALTA",CW22="LICENCIA",CP22="",CQ22="",WEEKDAY($CP$17,2)>5),"", MAX(0,CHOOSE($C22,$H$3,$H$4)-(CS22*1440)) ) -> 171 | CU22: =IF(OR(CW22="VACACIONES",CW22="FALTA",CW22="LICENCIA",CP22="",CQ22="",CR22="NO",WEEKDAY($CP$17,2)>5),"",MAX(0,IF(CR22="SI", (CS22*1440)-CHOOSE($C22,$H$3,$H$4) ))) | CV22: =IF(OR(CW22="VACACIONES",CW22="FALTA",CW22="LICENCIA",CP22="",CQ22="",WEEKDAY($CP$17,2)<=5),"",IF(WEEKDAY($CP$17,2)>5,(CS22*1440))) | CY22: 0.29027778 | CZ22: 0.77708333 | DA22: NO | DB22: =IF(OR(DF22="VACACIONES",DF22="FALTA",DF22="LICENCIA",CY22="",CZ22=""),"",IF(WEEKDAY($CY$17,2)>5,CZ22-CY22,IF(DA22="NO",MIN(CZ22,CHOOSE($C22,$C$3,$C$4))-MAX(CY22,CHOOSE($C22,$B$3,$B$4))-CHOOSE($C22,$F$3,$F$4),CZ22-CY22-CHOOSE($C22,$F$3,$F$4)))) -> 0.40069444 | DC22: =IF(OR(DF22="VACACIONES",DF22="FALTA",DF22="LICENCIA",CY22="",CZ22="",WEEKDAY($CY$17,2)>5),"", MAX(0,CHOOSE($C22,$H$3,$H$4)-(DB22*1440)) ) -> 0 | DD22: =IF(OR(DF22="VACACIONES",DF22="FALTA",DF22="LICENCIA",CY22="",CZ22="",DA22="NO",WEEKDAY($CY$17,2)>5),"",MAX(0,IF(DA22="SI", (DB22*1440)-CHOOSE($C22,$H$3,$H$4) ))) | DE22: =IF(OR(DF22="VACACIONES",DF22="FALTA",DF22="LICENCIA",CY22="",CZ22="",WEEKDAY($CY$17,2)<=5),"",IF(WEEKDAY($CY$17,2)>5,(DB22*1440))) | DK22: =IF(OR(DO22="VACACIONES",DO22="FALTA",DO22="LICENCIA",DH22="",DI22=""),"",IF(WEEKDAY($DH$17,2)>5,DI22-DH22,IF(DJ22="NO",MIN(DI22,CHOOSE($C22,$C$3,$C$4))-MAX(DH22,CHOOSE($C22,$B$3,$B$4))-CHOOSE($C22,$F$3,$F$4),DI22-DH22-CHOOSE($C22,$F$3,$F$4)))) | DL22: =IF(OR(DO22="VACACIONES",DO22="FALTA",DO22="LICENCIA",DH22="",DI22="",WEEKDAY($DH$17,2)>5),"", MAX(0,CHOOSE($C22,$H$3,$H$4)-(DK22*1440)) ) | DM22: =IF(OR(DO22="VACACIONES",DO22="FALTA",DO22="LICENCIA",DH22="",DI22="",DJ22="NO",WEEKDAY($DH$17,2)>5),"",MAX(0,IF(DJ22="SI", (DK22*1440)-CHOOSE($C22,$H$3,$H$4) ))) | DN22: =IF(OR(DO22="VACACIONES",DO22="FALTA",DO22="LICENCIA",DH22="",DI22="",WEEKDAY($DH$17,2)<=5),"",IF(WEEKDAY($DH$17,2)>5,(DK22*1440))) | DT22: =IF(OR(DX22="VACACIONES",DX22="FALTA",DX22="LICENCIA",DQ22="",DR22=""),"",IF(WEEKDAY($DQ$17,2)>5,DR22-DR22,IF(DS22="NO",MIN(DR22,CHOOSE($C22,$C$3,$C$4))-MAX(DQ22,CHOOSE($C22,$B$3,$B$4))-CHOOSE($C22,$F$3,$F$4),DR22-DQ22-CHOOSE($C22,$F$3,$F$4)))) | DU22: =IF(OR(DX22="VACACIONES",DX22="FALTA",DX22="LICENCIA",DQ22="",DR22="",WEEKDAY($DQ$17,2)>5),"", MAX(0,CHOOSE($C22,$H$3,$H$4)-(DT22*1440)) ) | DV22: =IF(OR(DX22="VACACIONES",DX22="FALTA",DX22="LICENCIA",DQ22="",DR22="",DS22="NO",WEEKDAY($DQ$17,2)>5),"",MAX(0,IF(DS22="SI", (DT22*1440)-CHOOSE($C22,$H$3,$H$4) ))) | DW22: =IF(OR(DX22="VACACIONES",DX22="FALTA",DX22="LICENCIA",DQ22="",DR22="",WEEKDAY($DQ$17,2)<=5),"",IF(WEEKDAY($DQ$17,2)>5,(DT22*1440))) | EB22: NO | EC22: =IF(OR(EG22="VACACIONES",EG22="FALTA",EG22="LICENCIA",DZ22="",EA22=""),"",IF(WEEKDAY($CY$17,2)>5,EA22-DZ22,IF(EB22="NO",MIN(EA22,CHOOSE($C22,$C$3,$C$4))-MAX(DZ22,CHOOSE($C22,$B$3,$B$4))-CHOOSE($C22,$F$3,$F$4),EA22-DZ22-CHOOSE($C22,$F$3,$F$4)))) | ED22: =IF(OR(EG22="VACACIONES",EG22="FALTA",EG22="LICENCIA",DZ22="",EA22="",WEEKDAY($CY$17,2)>5),"", MAX(0,CHOOSE($C22,$H$3,$H$4)-(EC22*1440)) ) | EE22: =IF(OR(EG22="VACACIONES",EG22="FALTA",EG22="LICENCIA",DZ22="",EA22="",EB22="NO",WEEKDAY($CY$17,2)>5),"",MAX(0,IF(EB22="SI", (EC22*1440)-CHOOSE($C22,$H$3,$H$4) ))) | EF22: =IF(OR(EG22="VACACIONES",EG22="FALTA",EG22="LICENCIA",DZ22="",EA22="",WEEKDAY($CY$17,2)<=5),"",IF(WEEKDAY($CY$17,2)>5,(EC22*1440))) | EG22: FALTA | EK22: =SUM(H22,Q22,Z22,AI22,AR22,BA22,BJ22,BS22,CB22,CK22,CT22,DC22,DL22,DU22,ED22) -> 171 | EL22: =SUM(I22,J22,R22,S22,AA22,AB22,AJ22,AK22,AS22,AT22,BB22,BC22,BK22,BL22,BT22,BU22,CC22,CD22,CL22,CM22,CU22,CV22,DD22,DE22,DM22,DN22,DV22,DW22,EE22,EF22) -> 0 | EM22: =COUNTIF(I22,">0")+COUNTIF(J22,">0")+COUNTIF(R22,">0")+COUNTIF(S22,">0")++COUNTIF(AA22,">0")+COUNTIF(AB22,">0")+COUNTIF(AJ22,">0")+COUNTIF(AK22,">0")+COUNTIF(AS22,">0")+COUNTIF(AT22,">0")+COUNTIF(BB22,">0")+COUNTIF(BC22,">0")+COUNTIF(BK22,">0")+COUNTIF(BL22,">0")+COUNTIF(BT22,">0")+COUNTIF(BU22,">0")+COUNTIF(CC22,">0")+COUNTIF(CD22,">0")+COUNTIF(CL22,">0")+COUNTIF(CM22,">0")+COUNTIF(CU22,">0")+COUNTIF(CV22,">0")+COUNTIF(DD22,">0")+COUNTIF(DE22,">0")+COUNTIF(DM22,">0")+COUNTIF(DN22,">0")+COUNTIF(DV22,">0")+COUNTIF(DW22,">0")+COUNTIF(EE22,">0")+COUNTIF(EF22,">0") -> 0 | EN22: =COUNTIF(D22:EG22,"FALTA") -> 1 | EO22: =15-EN22 -> 14 | EP22: =COUNTIF(D22:EG22,"TRABAJO SABADO") -> 0 | EQ22: =COUNTIF(D22:EG22,"TRABAJO DOMINGO")+COUNTIF(D22:EG22,"TRABAJO FERIADO")+(COUNTIF(D22:EG22,"TRABAJO 1RO MAYO")*2)+((COUNTIF(D24:EG24,"TRABAJO 1RO MAYO EN SU DIA LIBRE")*2)*2) -> 0 | ER22: =COUNTIF(D22:EG22,"VACACIONES") -> 0 | ES22: =COUNTIF(D22:EG22,"LICENCIA") -> 0
A23: =A22+1 -> 5 | B23: ='1RA QUINCENA JUNIO 26'!B14 -> GAVIDIA PEREIRA JAVIER | C23: 2 | D23: 0.33333333 | E23: 0.75 | F23: NO | G23: =IF(OR(K23="VACACIONES",K23="FALTA",K23="LICENCIA",D23="",E23=""),"",IF(WEEKDAY($D$17,2)>5,E23-D23,IF(F23="NO",MIN(E23,CHOOSE($C23,$C$3,$C$4))-MAX(D23,CHOOSE($C23,$B$3,$B$4))-CHOOSE($C23,$F$3,$F$4),E23-D23-CHOOSE($C23,$F$3,$F$4)))) -> 0.375 | H23: =IF(OR(K23="VACACIONES",K23="FALTA",K23="LICENCIA",D23="",E23="",WEEKDAY($D$17,2)>5),"", MAX(0,CHOOSE($C23,$H$3,$H$4)-(G23*1440)) ) -> 0 | I23: =IF(OR(K23="VACACIONES",K23="FALTA",K23="LICENCIA",D23="",E23="",F23="NO",WEEKDAY($D$17,2)>5),"",MAX(0,IF(F23="SI", (G23*1440)-CHOOSE($C23,$H$3,$H$4) ))) | J23: =IF(OR(K23="VACACIONES",K23="FALTA",K23="LICENCIA",D23="",E23="",WEEKDAY($D$17,2)<=5),"",IF(WEEKDAY($D$17,2)>5,(G23*1440))) | M23: 0.33333333 | N23: 0.75 | O23: NO | P23: =IF(OR(T23="VACACIONES",T23="FALTA",T23="LICENCIA",M23="",N23=""),"",IF(WEEKDAY($M$17,2)>5,N23-M23,IF(O23="NO",MIN(N23,CHOOSE($C23,$C$3,$C$4))-MAX(M23,CHOOSE($C23,$B$3,$B$4))-CHOOSE($C23,$F$3,$F$4),N23-M23-CHOOSE($C23,$F$3,$F$4)))) -> 0.375 | Q23: =IF(OR(T23="VACACIONES",T23="FALTA",T23="LICENCIA",M23="",N23="",WEEKDAY($M$17,2)>5),"", MAX(0,CHOOSE($C23,$H$3,$H$4)-(P23*1440)) ) -> 0 | R23: =IF(OR(T23="VACACIONES",T23="FALTA",T23="LICENCIA",M23="",N23="",O23="NO",WEEKDAY($M$17,2)>5),"",MAX(0,IF(O23="SI", (P23*1440)-CHOOSE($C23,$H$3,$H$4) ))) | S23: =IF(OR(T23="VACACIONES",T23="FALTA",T23="LICENCIA",M23="",N23="",WEEKDAY($M$17,2)<=5),"",IF(WEEKDAY($M$17,2)>5,(P23*1440))) | V23: 0.33333333 | W23: 0.75 | X23: NO | Y23: =IF(OR(AC23="VACACIONES",AC23="FALTA",AC23="LICENCIA",V23="",W23=""),"",IF(WEEKDAY($V$17,2)>5,W23-V23,IF(X23="NO",MIN(W23,CHOOSE($C23,$C$3,$C$4))-MAX(V23,CHOOSE($C23,$B$3,$B$4))-CHOOSE($C23,$F$3,$F$4),W23-V23-CHOOSE($C23,$F$3,$F$4)))) -> 0.375 | Z23: =IF(OR(AC23="VACACIONES",AC23="FALTA",AC23="LICENCIA",V23="",W23="",WEEKDAY($V$17,2)>5),"", MAX(0,CHOOSE($C23,$H$3,$H$4)-(Y23*1440)) ) -> 0 | AA23: =IF(OR(AC23="VACACIONES",AC23="FALTA",AC23="LICENCIA",V23="",W23="",X23="NO",WEEKDAY($V$17,2)>5),"",MAX(0,IF(X23="SI", (Y23*1440)-CHOOSE($C23,$H$3,$H$4) ))) | AB23: =IF(OR(AC23="VACACIONES",AC23="FALTA",AC23="LICENCIA",V23="",W23="",WEEKDAY($V$17,2)<=5),"",IF(WEEKDAY($V$17,2)>5,(Y23*1440))) | AE23: 0.33333333 | AF23: 0.75 | AG23: NO | AH23: =IF(OR(AL23="VACACIONES",AL23="FALTA",AL23="LICENCIA",AE23="",AF23=""),"",IF(WEEKDAY($AE$17,2)>5,AF23-AE23,IF(AG23="NO",MIN(AF23,CHOOSE($C23,$C$3,$C$4))-MAX(AE23,CHOOSE($C23,$B$3,$B$4))-CHOOSE($C23,$F$3,$F$4),AF23-AE23-CHOOSE($C23,$F$3,$F$4)))) -> 0.375 | AI23: =IF(OR(AL23="VACACIONES",AL23="FALTA",AL23="LICENCIA",AE23="",AF23="",WEEKDAY($AE$17,2)>5),"", MAX(0,CHOOSE($C23,$H$3,$H$4)-(AH23*1440)) ) -> 0 | AJ23: =IF(OR(AL23="VACACIONES",AL23="FALTA",AL23="LICENCIA",AE23="",AF23="",AG23="NO",WEEKDAY($AE$17,2)>5),"",MAX(0,IF(AG23="SI", (AH23*1440)-CHOOSE($C23,$H$3,$H$4) ))) | AK23: =IF(OR(AL23="VACACIONES",AL23="FALTA",AL23="LICENCIA",AE23="",AF23="",WEEKDAY($AE$17,2)<=5),"",IF(WEEKDAY($AE$17,2)>5,(AH23*1440))) | AN23: 0.33333333 | AO23: 0.75 | AP23: NO | AQ23: =IF(OR(AU23="VACACIONES",AU23="FALTA",AU23="LICENCIA",AN23="",AO23=""),"",IF(WEEKDAY($AN$17,2)>5,AO23-AN23,IF(AP23="NO",MIN(AO23,CHOOSE($C23,$C$3,$C$4))-MAX(AN23,CHOOSE($C23,$B$3,$B$4))-CHOOSE($C23,$F$3,$F$4),AO23-AN23-CHOOSE($C23,$F$3,$F$4)))) -> 0.375 | AR23: =IF(OR(AU23="VACACIONES",AU23="FALTA",AU23="LICENCIA",AN23="",AO23="",WEEKDAY($AN$17,2)>5),"", MAX(0,CHOOSE($C23,$H$3,$H$4)-(AQ23*1440)) ) -> 0 | AS23: =IF(OR(AU23="VACACIONES",AU23="FALTA",AU23="LICENCIA",AN23="",AO23="",AP23="NO",WEEKDAY($AN$17,2)>5),"",MAX(0,IF(AP23="SI", (AQ23*1440)-CHOOSE($C23,$H$3,$H$4) ))) | AT23: =IF(OR(AU23="VACACIONES",AU23="FALTA",AU23="LICENCIA",AN23="",AO23="",WEEKDAY($AN$17,2)<=5),"",IF(WEEKDAY($AN$17,2)>5,(AQ23*1440))) | AZ23: =IF(OR(BD23="VACACIONES",BD23="FALTA",BD23="LICENCIA",AW23="",AX23=""),"",IF(WEEKDAY($AW$17,2)>5,AX23-AW23,IF(AY23="NO",MIN(AX23,CHOOSE($C23,$C$3,$C$4))-MAX(AW23,CHOOSE($C23,$B$3,$B$4))-CHOOSE($C23,$F$3,$F$4),AX23-AW23-CHOOSE($C23,$F$3,$F$4)))) | BA23: =IF(OR(BD23="VACACIONES",BD23="FALTA",BD23="LICENCIA",AW23="",AX23="",WEEKDAY($AW$17,2)>5),"", MAX(0,CHOOSE($C23,$H$3,$H$4)-(AZ23*1440)) ) | BB23: =IF(OR(BD23="VACACIONES",BD23="FALTA",BD23="LICENCIA",AW23="",AX23="",AY23="NO",WEEKDAY($AW$17,2)>5),"",MAX(0,IF(AY23="SI", (AZ23*1440)-CHOOSE($C23,$H$3,$H$4) ))) | BC23: =IF(OR(BD23="VACACIONES",BD23="FALTA",BD23="LICENCIA",AW23="",AX23="",WEEKDAY($AW$17,2)<=5),"",IF(WEEKDAY($AW$17,2)>5,(AZ23*1440))) | BI23: =IF(OR(BM23="VACACIONES",BM23="FALTA",BM23="LICENCIA",BF23="",BG23=""),"",IF(WEEKDAY($BF$17,2)>5,BG23-BF23,IF(BH23="NO",MIN(BG23,CHOOSE($C23,$C$3,$C$4))-MAX(BF23,CHOOSE($C23,$B$3,$B$4))-CHOOSE($C23,$F$3,$F$4),BG23-BF23-CHOOSE($C23,$F$3,$F$4)))) | BJ23: =IF(OR(BM23="VACACIONES",BM23="FALTA",BM23="LICENCIA",BF23="",BG23="",WEEKDAY($BF$17,2)>5),"", MAX(0,CHOOSE($C23,$H$3,$H$4)-(BI23*1440)) ) | BK23: =IF(OR(BM23="VACACIONES",BM23="FALTA",BM23="LICENCIA",BF23="",BG23="",BH23="NO",WEEKDAY($BF$17,2)>5),"",MAX(0,IF(BH23="SI", (BI23*1440)-CHOOSE($C23,$H$3,$H$4) ))) | BL23: =IF(OR(BM23="VACACIONES",BM23="FALTA",BM23="LICENCIA",BF23="",BG23="",WEEKDAY($BF$17,2)<=5),"",IF(WEEKDAY($BF$17,2)>5,(BI23*1440))) | BO23: 0.33333333 | BP23: 0.75 | BQ23: NO | BR23: =IF(OR(BV23="VACACIONES",BV23="FALTA",BV23="LICENCIA",BO23="",BP23=""),"",IF(WEEKDAY($BO$17,2)>5,BP23-BO23,IF(BQ23="NO",MIN(BP23,CHOOSE($C23,$C$3,$C$4))-MAX(BO23,CHOOSE($C23,$B$3,$B$4))-CHOOSE($C23,$F$3,$F$4),BP23-BO23-CHOOSE($C23,$F$3,$F$4)))) -> 0.375 | BS23: =IF(OR(BV23="VACACIONES",BV23="FALTA",BV23="LICENCIA",BO23="",BP23="",WEEKDAY($BO$17,2)>5),"", MAX(0,CHOOSE($C23,$H$3,$H$4)-(BR23*1440)) ) -> 0 | BT23: =IF(OR(BV23="VACACIONES",BV23="FALTA",BV23="LICENCIA",BO23="",BP23="",BQ23="NO",WEEKDAY($BO$17,2)>5),"",MAX(0,IF(BQ23="SI", (BR23*1440)-CHOOSE($C23,$H$3,$H$4) ))) | BU23: =IF(OR(BV23="VACACIONES",BV23="FALTA",BV23="LICENCIA",BO23="",BP23="",WEEKDAY($BO$17,2)<=5),"",IF(WEEKDAY($BO$17,2)>5,(BR23*1440))) | BX23: 0.33333333 | BY23: 0.75 | BZ23: NO | CA23: =IF(OR(CE23="VACACIONES",CE23="FALTA",CE23="LICENCIA",BX23="",BY23=""),"",IF(WEEKDAY($BX$17,2)>5,BY23-BX23,IF(BZ23="NO",MIN(BY23,CHOOSE($C23,$C$3,$C$4))-MAX(BX23,CHOOSE($C23,$B$3,$B$4))-CHOOSE($C23,$F$3,$F$4),BY23-BX23-CHOOSE($C23,$F$3,$F$4)))) -> 0.375 | CB23: =IF(OR(CE23="VACACIONES",CE23="FALTA",CE23="LICENCIA",BX23="",BY23="",WEEKDAY($BX$17,2)>5),"", MAX(0,CHOOSE($C23,$H$3,$H$4)-(CA23*1440)) ) -> 0 | CC23: =IF(OR(CE23="VACACIONES",CE23="FALTA",CE23="LICENCIA",BX23="",BY23="",BZ23="NO",WEEKDAY($BX$17,2)>5),"",MAX(0,IF(BZ23="SI", (CA23*1440)-CHOOSE($C23,$H$3,$H$4) ))) | CD23: =IF(OR(CE23="VACACIONES",CE23="FALTA",CE23="LICENCIA",BX23="",BY23="",WEEKDAY($BX$17,2)<=5),"",IF(WEEKDAY($BX$17,2)>5,(CA23*1440))) | CG23: 0.33333333 | CH23: 0.75 | CI23: NO | CJ23: =IF(OR(CN23="VACACIONES",CN23="FALTA",CN23="LICENCIA",CG23="",CH23=""),"",IF(WEEKDAY($CG$17,2)>5,CH23-CG23,IF(CI23="NO",MIN(CH23,CHOOSE($C23,$C$3,$C$4))-MAX(CG23,CHOOSE($C23,$B$3,$B$4))-CHOOSE($C23,$F$3,$F$4),CH23-CG23-CHOOSE($C23,$F$3,$F$4)))) -> 0.375 | CK23: =IF(OR(CN23="VACACIONES",CN23="FALTA",CN23="LICENCIA",CG23="",CH23="",WEEKDAY($CG$17,2)>5),"", MAX(0,CHOOSE($C23,$H$3,$H$4)-(CJ23*1440)) ) -> 0 | CL23: =IF(OR(CN23="VACACIONES",CN23="FALTA",CN23="LICENCIA",CG23="",CH23="",CI23="NO",WEEKDAY($CG$17,2)>5),"",MAX(0,IF(CI23="SI", (CJ23*1440)-CHOOSE($C23,$H$3,$H$4) ))) | CM23: =IF(OR(CN23="VACACIONES",CN23="FALTA",CN23="LICENCIA",CG23="",CH23="",WEEKDAY($CG$17,2)<=5),"",IF(WEEKDAY($CG$17,2)>5,(CJ23*1440))) | CP23: 0.33333333 | CQ23: 0.75 | CR23: NO | CS23: =IF(OR(CW23="VACACIONES",CW23="FALTA",CW23="LICENCIA",CP23="",CQ23=""),"",IF(WEEKDAY($CP$17,2)>5,CQ23-CP23,IF(CR23="NO",MIN(CQ23,CHOOSE($C23,$C$3,$C$4))-MAX(CP23,CHOOSE($C23,$B$3,$B$4))-CHOOSE($C23,$F$3,$F$4),CQ23-CP23-CHOOSE($C23,$F$3,$F$4)))) -> 0.375 | CT23: =IF(OR(CW23="VACACIONES",CW23="FALTA",CW23="LICENCIA",CP23="",CQ23="",WEEKDAY($CP$17,2)>5),"", MAX(0,CHOOSE($C23,$H$3,$H$4)-(CS23*1440)) ) -> 0 | CU23: =IF(OR(CW23="VACACIONES",CW23="FALTA",CW23="LICENCIA",CP23="",CQ23="",CR23="NO",WEEKDAY($CP$17,2)>5),"",MAX(0,IF(CR23="SI", (CS23*1440)-CHOOSE($C23,$H$3,$H$4) ))) | CV23: =IF(OR(CW23="VACACIONES",CW23="FALTA",CW23="LICENCIA",CP23="",CQ23="",WEEKDAY($CP$17,2)<=5),"",IF(WEEKDAY($CP$17,2)>5,(CS23*1440))) | CY23: 0.33333333 | CZ23: 0.75 | DA23: NO | DB23: =IF(OR(DF23="VACACIONES",DF23="FALTA",DF23="LICENCIA",CY23="",CZ23=""),"",IF(WEEKDAY($CY$17,2)>5,CZ23-CY23,IF(DA23="NO",MIN(CZ23,CHOOSE($C23,$C$3,$C$4))-MAX(CY23,CHOOSE($C23,$B$3,$B$4))-CHOOSE($C23,$F$3,$F$4),CZ23-CY23-CHOOSE($C23,$F$3,$F$4)))) -> 0.375 | DC23: =IF(OR(DF23="VACACIONES",DF23="FALTA",DF23="LICENCIA",CY23="",CZ23="",WEEKDAY($CY$17,2)>5),"", MAX(0,CHOOSE($C23,$H$3,$H$4)-(DB23*1440)) ) -> 0 | DD23: =IF(OR(DF23="VACACIONES",DF23="FALTA",DF23="LICENCIA",CY23="",CZ23="",DA23="NO",WEEKDAY($CY$17,2)>5),"",MAX(0,IF(DA23="SI", (DB23*1440)-CHOOSE($C23,$H$3,$H$4) ))) | DE23: =IF(OR(DF23="VACACIONES",DF23="FALTA",DF23="LICENCIA",CY23="",CZ23="",WEEKDAY($CY$17,2)<=5),"",IF(WEEKDAY($CY$17,2)>5,(DB23*1440))) | DK23: =IF(OR(DO23="VACACIONES",DO23="FALTA",DO23="LICENCIA",DH23="",DI23=""),"",IF(WEEKDAY($DH$17,2)>5,DI23-DH23,IF(DJ23="NO",MIN(DI23,CHOOSE($C23,$C$3,$C$4))-MAX(DH23,CHOOSE($C23,$B$3,$B$4))-CHOOSE($C23,$F$3,$F$4),DI23-DH23-CHOOSE($C23,$F$3,$F$4)))) | DL23: =IF(OR(DO23="VACACIONES",DO23="FALTA",DO23="LICENCIA",DH23="",DI23="",WEEKDAY($DH$17,2)>5),"", MAX(0,CHOOSE($C23,$H$3,$H$4)-(DK23*1440)) ) | DM23: =IF(OR(DO23="VACACIONES",DO23="FALTA",DO23="LICENCIA",DH23="",DI23="",DJ23="NO",WEEKDAY($DH$17,2)>5),"",MAX(0,IF(DJ23="SI", (DK23*1440)-CHOOSE($C23,$H$3,$H$4) ))) | DN23: =IF(OR(DO23="VACACIONES",DO23="FALTA",DO23="LICENCIA",DH23="",DI23="",WEEKDAY($DH$17,2)<=5),"",IF(WEEKDAY($DH$17,2)>5,(DK23*1440))) | DT23: =IF(OR(DX23="VACACIONES",DX23="FALTA",DX23="LICENCIA",DQ23="",DR23=""),"",IF(WEEKDAY($DQ$17,2)>5,DR23-DR23,IF(DS23="NO",MIN(DR23,CHOOSE($C23,$C$3,$C$4))-MAX(DQ23,CHOOSE($C23,$B$3,$B$4))-CHOOSE($C23,$F$3,$F$4),DR23-DQ23-CHOOSE($C23,$F$3,$F$4)))) | DU23: =IF(OR(DX23="VACACIONES",DX23="FALTA",DX23="LICENCIA",DQ23="",DR23="",WEEKDAY($DQ$17,2)>5),"", MAX(0,CHOOSE($C23,$H$3,$H$4)-(DT23*1440)) ) | DV23: =IF(OR(DX23="VACACIONES",DX23="FALTA",DX23="LICENCIA",DQ23="",DR23="",DS23="NO",WEEKDAY($DQ$17,2)>5),"",MAX(0,IF(DS23="SI", (DT23*1440)-CHOOSE($C23,$H$3,$H$4) ))) | DW23: =IF(OR(DX23="VACACIONES",DX23="FALTA",DX23="LICENCIA",DQ23="",DR23="",WEEKDAY($DQ$17,2)<=5),"",IF(WEEKDAY($DQ$17,2)>5,(DT23*1440))) | DZ23: 0.33333333 | EA23: 0.75 | EB23: NO | EC23: =IF(OR(EG23="VACACIONES",EG23="FALTA",EG23="LICENCIA",DZ23="",EA23=""),"",IF(WEEKDAY($CY$17,2)>5,EA23-DZ23,IF(EB23="NO",MIN(EA23,CHOOSE($C23,$C$3,$C$4))-MAX(DZ23,CHOOSE($C23,$B$3,$B$4))-CHOOSE($C23,$F$3,$F$4),EA23-DZ23-CHOOSE($C23,$F$3,$F$4)))) -> 0.375 | ED23: =IF(OR(EG23="VACACIONES",EG23="FALTA",EG23="LICENCIA",DZ23="",EA23="",WEEKDAY($CY$17,2)>5),"", MAX(0,CHOOSE($C23,$H$3,$H$4)-(EC23*1440)) ) -> 0 | EE23: =IF(OR(EG23="VACACIONES",EG23="FALTA",EG23="LICENCIA",DZ23="",EA23="",EB23="NO",WEEKDAY($CY$17,2)>5),"",MAX(0,IF(EB23="SI", (EC23*1440)-CHOOSE($C23,$H$3,$H$4) ))) | EF23: =IF(OR(EG23="VACACIONES",EG23="FALTA",EG23="LICENCIA",DZ23="",EA23="",WEEKDAY($CY$17,2)<=5),"",IF(WEEKDAY($CY$17,2)>5,(EC23*1440))) | EK23: =SUM(H23,Q23,Z23,AI23,AR23,BA23,BJ23,BS23,CB23,CK23,CT23,DC23,DL23,DU23,ED23) -> 0 | EL23: =SUM(I23,J23,R23,S23,AA23,AB23,AJ23,AK23,AS23,AT23,BB23,BC23,BK23,BL23,BT23,BU23,CC23,CD23,CL23,CM23,CU23,CV23,DD23,DE23,DM23,DN23,DV23,DW23,EE23,EF23) -> 0 | EM23: =COUNTIF(I23,">0")+COUNTIF(J23,">0")+COUNTIF(R23,">0")+COUNTIF(S23,">0")++COUNTIF(AA23,">0")+COUNTIF(AB23,">0")+COUNTIF(AJ23,">0")+COUNTIF(AK23,">0")+COUNTIF(AS23,">0")+COUNTIF(AT23,">0")+COUNTIF(BB23,">0")+COUNTIF(BC23,">0")+COUNTIF(BK23,">0")+COUNTIF(BL23,">0")+COUNTIF(BT23,">0")+COUNTIF(BU23,">0")+COUNTIF(CC23,">0")+COUNTIF(CD23,">0")+COUNTIF(CL23,">0")+COUNTIF(CM23,">0")+COUNTIF(CU23,">0")+COUNTIF(CV23,">0")+COUNTIF(DD23,">0")+COUNTIF(DE23,">0")+COUNTIF(DM23,">0")+COUNTIF(DN23,">0")+COUNTIF(DV23,">0")+COUNTIF(DW23,">0")+COUNTIF(EE23,">0")+COUNTIF(EF23,">0") -> 0 | EN23: =COUNTIF(D23:EG23,"FALTA") -> 0 | EO23: =15-EN23 -> 15 | EP23: =COUNTIF(D23:EG23,"TRABAJO SABADO") -> 0 | EQ23: =COUNTIF(D23:EG23,"TRABAJO DOMINGO")+COUNTIF(D23:EG23,"TRABAJO FERIADO")+(COUNTIF(D23:EG23,"TRABAJO 1RO MAYO")*2)+((COUNTIF(D25:EG25,"TRABAJO 1RO MAYO EN SU DIA LIBRE")*2)*2) -> 0 | ER23: =COUNTIF(D23:EG23,"VACACIONES") -> 0 | ES23: =COUNTIF(D23:EG23,"LICENCIA") -> 0
A24: =A23+1 -> 6 | B24: ='1RA QUINCENA JUNIO 26'!B15 -> HIDALGO MOYA, LIZBETH SONIA | C24: 2 | D24: 0.38888889 | E24: 0.75 | F24: NO | G24: =IF(OR(K24="VACACIONES",K24="FALTA",K24="LICENCIA",D24="",E24=""),"",IF(WEEKDAY($D$17,2)>5,E24-D24,IF(F24="NO",MIN(E24,CHOOSE($C24,$C$3,$C$4))-MAX(D24,CHOOSE($C24,$B$3,$B$4))-CHOOSE($C24,$F$3,$F$4),E24-D24-CHOOSE($C24,$F$3,$F$4)))) -> 0.31944444 | H24: =IF(OR(K24="VACACIONES",K24="FALTA",K24="LICENCIA",D24="",E24="",WEEKDAY($D$17,2)>5),"", MAX(0,CHOOSE($C24,$H$3,$H$4)-(G24*1440)) ) -> 80 | I24: =IF(OR(K24="VACACIONES",K24="FALTA",K24="LICENCIA",D24="",E24="",F24="NO",WEEKDAY($D$17,2)>5),"",MAX(0,IF(F24="SI", (G24*1440)-CHOOSE($C24,$H$3,$H$4) ))) | J24: =IF(OR(K24="VACACIONES",K24="FALTA",K24="LICENCIA",D24="",E24="",WEEKDAY($D$17,2)<=5),"",IF(WEEKDAY($D$17,2)>5,(G24*1440))) | M24: 0.40555556 | N24: 0.75972222 | O24: NO | P24: =IF(OR(T24="VACACIONES",T24="FALTA",T24="LICENCIA",M24="",N24=""),"",IF(WEEKDAY($M$17,2)>5,N24-M24,IF(O24="NO",MIN(N24,CHOOSE($C24,$C$3,$C$4))-MAX(M24,CHOOSE($C24,$B$3,$B$4))-CHOOSE($C24,$F$3,$F$4),N24-M24-CHOOSE($C24,$F$3,$F$4)))) -> 0.30277778 | Q24: =IF(OR(T24="VACACIONES",T24="FALTA",T24="LICENCIA",M24="",N24="",WEEKDAY($M$17,2)>5),"", MAX(0,CHOOSE($C24,$H$3,$H$4)-(P24*1440)) ) -> 104 | R24: =IF(OR(T24="VACACIONES",T24="FALTA",T24="LICENCIA",M24="",N24="",O24="NO",WEEKDAY($M$17,2)>5),"",MAX(0,IF(O24="SI", (P24*1440)-CHOOSE($C24,$H$3,$H$4) ))) | S24: =IF(OR(T24="VACACIONES",T24="FALTA",T24="LICENCIA",M24="",N24="",WEEKDAY($M$17,2)<=5),"",IF(WEEKDAY($M$17,2)>5,(P24*1440))) | V24: 0.41319444 | W24: 0.76041667 | X24: NO | Y24: =IF(OR(AC24="VACACIONES",AC24="FALTA",AC24="LICENCIA",V24="",W24=""),"",IF(WEEKDAY($V$17,2)>5,W24-V24,IF(X24="NO",MIN(W24,CHOOSE($C24,$C$3,$C$4))-MAX(V24,CHOOSE($C24,$B$3,$B$4))-CHOOSE($C24,$F$3,$F$4),W24-V24-CHOOSE($C24,$F$3,$F$4)))) -> 0.29513889 | Z24: =IF(OR(AC24="VACACIONES",AC24="FALTA",AC24="LICENCIA",V24="",W24="",WEEKDAY($V$17,2)>5),"", MAX(0,CHOOSE($C24,$H$3,$H$4)-(Y24*1440)) ) -> 115 | AA24: =IF(OR(AC24="VACACIONES",AC24="FALTA",AC24="LICENCIA",V24="",W24="",X24="NO",WEEKDAY($V$17,2)>5),"",MAX(0,IF(X24="SI", (Y24*1440)-CHOOSE($C24,$H$3,$H$4) ))) | AB24: =IF(OR(AC24="VACACIONES",AC24="FALTA",AC24="LICENCIA",V24="",W24="",WEEKDAY($V$17,2)<=5),"",IF(WEEKDAY($V$17,2)>5,(Y24*1440))) | AE24: 0.33333333 | AF24: 0.75 | AG24: NO | AH24: =IF(OR(AL24="VACACIONES",AL24="FALTA",AL24="LICENCIA",AE24="",AF24=""),"",IF(WEEKDAY($AE$17,2)>5,AF24-AE24,IF(AG24="NO",MIN(AF24,CHOOSE($C24,$C$3,$C$4))-MAX(AE24,CHOOSE($C24,$B$3,$B$4))-CHOOSE($C24,$F$3,$F$4),AF24-AE24-CHOOSE($C24,$F$3,$F$4)))) -> 0.375 | AI24: =IF(OR(AL24="VACACIONES",AL24="FALTA",AL24="LICENCIA",AE24="",AF24="",WEEKDAY($AE$17,2)>5),"", MAX(0,CHOOSE($C24,$H$3,$H$4)-(AH24*1440)) ) -> 0 | AJ24: =IF(OR(AL24="VACACIONES",AL24="FALTA",AL24="LICENCIA",AE24="",AF24="",AG24="NO",WEEKDAY($AE$17,2)>5),"",MAX(0,IF(AG24="SI", (AH24*1440)-CHOOSE($C24,$H$3,$H$4) ))) | AK24: =IF(OR(AL24="VACACIONES",AL24="FALTA",AL24="LICENCIA",AE24="",AF24="",WEEKDAY($AE$17,2)<=5),"",IF(WEEKDAY($AE$17,2)>5,(AH24*1440))) | AN24: 0.4 | AO24: 0.76458333 | AP24: NO | AQ24: =IF(OR(AU24="VACACIONES",AU24="FALTA",AU24="LICENCIA",AN24="",AO24=""),"",IF(WEEKDAY($AN$17,2)>5,AO24-AN24,IF(AP24="NO",MIN(AO24,CHOOSE($C24,$C$3,$C$4))-MAX(AN24,CHOOSE($C24,$B$3,$B$4))-CHOOSE($C24,$F$3,$F$4),AO24-AN24-CHOOSE($C24,$F$3,$F$4)))) -> 0.30833333 | AR24: =IF(OR(AU24="VACACIONES",AU24="FALTA",AU24="LICENCIA",AN24="",AO24="",WEEKDAY($AN$17,2)>5),"", MAX(0,CHOOSE($C24,$H$3,$H$4)-(AQ24*1440)) ) -> 96 | AS24: =IF(OR(AU24="VACACIONES",AU24="FALTA",AU24="LICENCIA",AN24="",AO24="",AP24="NO",WEEKDAY($AN$17,2)>5),"",MAX(0,IF(AP24="SI", (AQ24*1440)-CHOOSE($C24,$H$3,$H$4) ))) | AT24: =IF(OR(AU24="VACACIONES",AU24="FALTA",AU24="LICENCIA",AN24="",AO24="",WEEKDAY($AN$17,2)<=5),"",IF(WEEKDAY($AN$17,2)>5,(AQ24*1440))) | AZ24: =IF(OR(BD24="VACACIONES",BD24="FALTA",BD24="LICENCIA",AW24="",AX24=""),"",IF(WEEKDAY($AW$17,2)>5,AX24-AW24,IF(AY24="NO",MIN(AX24,CHOOSE($C24,$C$3,$C$4))-MAX(AW24,CHOOSE($C24,$B$3,$B$4))-CHOOSE($C24,$F$3,$F$4),AX24-AW24-CHOOSE($C24,$F$3,$F$4)))) | BA24: =IF(OR(BD24="VACACIONES",BD24="FALTA",BD24="LICENCIA",AW24="",AX24="",WEEKDAY($AW$17,2)>5),"", MAX(0,CHOOSE($C24,$H$3,$H$4)-(AZ24*1440)) ) | BB24: =IF(OR(BD24="VACACIONES",BD24="FALTA",BD24="LICENCIA",AW24="",AX24="",AY24="NO",WEEKDAY($AW$17,2)>5),"",MAX(0,IF(AY24="SI", (AZ24*1440)-CHOOSE($C24,$H$3,$H$4) ))) | BC24: =IF(OR(BD24="VACACIONES",BD24="FALTA",BD24="LICENCIA",AW24="",AX24="",WEEKDAY($AW$17,2)<=5),"",IF(WEEKDAY($AW$17,2)>5,(AZ24*1440))) | BI24: =IF(OR(BM24="VACACIONES",BM24="FALTA",BM24="LICENCIA",BF24="",BG24=""),"",IF(WEEKDAY($BF$17,2)>5,BG24-BF24,IF(BH24="NO",MIN(BG24,CHOOSE($C24,$C$3,$C$4))-MAX(BF24,CHOOSE($C24,$B$3,$B$4))-CHOOSE($C24,$F$3,$F$4),BG24-BF24-CHOOSE($C24,$F$3,$F$4)))) | BJ24: =IF(OR(BM24="VACACIONES",BM24="FALTA",BM24="LICENCIA",BF24="",BG24="",WEEKDAY($BF$17,2)>5),"", MAX(0,CHOOSE($C24,$H$3,$H$4)-(BI24*1440)) ) | BK24: =IF(OR(BM24="VACACIONES",BM24="FALTA",BM24="LICENCIA",BF24="",BG24="",BH24="NO",WEEKDAY($BF$17,2)>5),"",MAX(0,IF(BH24="SI", (BI24*1440)-CHOOSE($C24,$H$3,$H$4) ))) | BL24: =IF(OR(BM24="VACACIONES",BM24="FALTA",BM24="LICENCIA",BF24="",BG24="",WEEKDAY($BF$17,2)<=5),"",IF(WEEKDAY($BF$17,2)>5,(BI24*1440))) | BO24: 0.42777778 | BP24: 0.65277778 | BQ24: NO | BR24: =IF(OR(BV24="VACACIONES",BV24="FALTA",BV24="LICENCIA",BO24="",BP24=""),"",IF(WEEKDAY($BO$17,2)>5,BP24-BO24,IF(BQ24="NO",MIN(BP24,CHOOSE($C24,$C$3,$C$4))-MAX(BO24,CHOOSE($C24,$B$3,$B$4))-CHOOSE($C24,$F$3,$F$4),BP24-BO24-CHOOSE($C24,$F$3,$F$4)))) -> 0.18333333 | BS24: =IF(OR(BV24="VACACIONES",BV24="FALTA",BV24="LICENCIA",BO24="",BP24="",WEEKDAY($BO$17,2)>5),"", MAX(0,CHOOSE($C24,$H$3,$H$4)-(BR24*1440)) ) -> 276 | BT24: =IF(OR(BV24="VACACIONES",BV24="FALTA",BV24="LICENCIA",BO24="",BP24="",BQ24="NO",WEEKDAY($BO$17,2)>5),"",MAX(0,IF(BQ24="SI", (BR24*1440)-CHOOSE($C24,$H$3,$H$4) ))) | BU24: =IF(OR(BV24="VACACIONES",BV24="FALTA",BV24="LICENCIA",BO24="",BP24="",WEEKDAY($BO$17,2)<=5),"",IF(WEEKDAY($BO$17,2)>5,(BR24*1440))) | BX24: 0.33333333 | BY24: 0.75 | BZ24: NO | CA24: =IF(OR(CE24="VACACIONES",CE24="FALTA",CE24="LICENCIA",BX24="",BY24=""),"",IF(WEEKDAY($BX$17,2)>5,BY24-BX24,IF(BZ24="NO",MIN(BY24,CHOOSE($C24,$C$3,$C$4))-MAX(BX24,CHOOSE($C24,$B$3,$B$4))-CHOOSE($C24,$F$3,$F$4),BY24-BX24-CHOOSE($C24,$F$3,$F$4)))) -> 0.375 | CB24: =IF(OR(CE24="VACACIONES",CE24="FALTA",CE24="LICENCIA",BX24="",BY24="",WEEKDAY($BX$17,2)>5),"", MAX(0,CHOOSE($C24,$H$3,$H$4)-(CA24*1440)) ) -> 0 | CC24: =IF(OR(CE24="VACACIONES",CE24="FALTA",CE24="LICENCIA",BX24="",BY24="",BZ24="NO",WEEKDAY($BX$17,2)>5),"",MAX(0,IF(BZ24="SI", (CA24*1440)-CHOOSE($C24,$H$3,$H$4) ))) | CD24: =IF(OR(CE24="VACACIONES",CE24="FALTA",CE24="LICENCIA",BX24="",BY24="",WEEKDAY($BX$17,2)<=5),"",IF(WEEKDAY($BX$17,2)>5,(CA24*1440))) | CG24: 0.40555556 | CH24: 0.75902778 | CI24: NO | CJ24: =IF(OR(CN24="VACACIONES",CN24="FALTA",CN24="LICENCIA",CG24="",CH24=""),"",IF(WEEKDAY($CG$17,2)>5,CH24-CG24,IF(CI24="NO",MIN(CH24,CHOOSE($C24,$C$3,$C$4))-MAX(CG24,CHOOSE($C24,$B$3,$B$4))-CHOOSE($C24,$F$3,$F$4),CH24-CG24-CHOOSE($C24,$F$3,$F$4)))) -> 0.30277778 | CK24: =IF(OR(CN24="VACACIONES",CN24="FALTA",CN24="LICENCIA",CG24="",CH24="",WEEKDAY($CG$17,2)>5),"", MAX(0,CHOOSE($C24,$H$3,$H$4)-(CJ24*1440)) ) -> 104 | CL24: =IF(OR(CN24="VACACIONES",CN24="FALTA",CN24="LICENCIA",CG24="",CH24="",CI24="NO",WEEKDAY($CG$17,2)>5),"",MAX(0,IF(CI24="SI", (CJ24*1440)-CHOOSE($C24,$H$3,$H$4) ))) | CM24: =IF(OR(CN24="VACACIONES",CN24="FALTA",CN24="LICENCIA",CG24="",CH24="",WEEKDAY($CG$17,2)<=5),"",IF(WEEKDAY($CG$17,2)>5,(CJ24*1440))) | CP24: 0.42638889 | CQ24: 0.76388889 | CR24: NO | CS24: =IF(OR(CW24="VACACIONES",CW24="FALTA",CW24="LICENCIA",CP24="",CQ24=""),"",IF(WEEKDAY($CP$17,2)>5,CQ24-CP24,IF(CR24="NO",MIN(CQ24,CHOOSE($C24,$C$3,$C$4))-MAX(CP24,CHOOSE($C24,$B$3,$B$4))-CHOOSE($C24,$F$3,$F$4),CQ24-CP24-CHOOSE($C24,$F$3,$F$4)))) -> 0.28194444 | CT24: =IF(OR(CW24="VACACIONES",CW24="FALTA",CW24="LICENCIA",CP24="",CQ24="",WEEKDAY($CP$17,2)>5),"", MAX(0,CHOOSE($C24,$H$3,$H$4)-(CS24*1440)) ) -> 134 | CU24: =IF(OR(CW24="VACACIONES",CW24="FALTA",CW24="LICENCIA",CP24="",CQ24="",CR24="NO",WEEKDAY($CP$17,2)>5),"",MAX(0,IF(CR24="SI", (CS24*1440)-CHOOSE($C24,$H$3,$H$4) ))) | CV24: =IF(OR(CW24="VACACIONES",CW24="FALTA",CW24="LICENCIA",CP24="",CQ24="",WEEKDAY($CP$17,2)<=5),"",IF(WEEKDAY($CP$17,2)>5,(CS24*1440))) | CY24: 0.40277778 | CZ24: 0.75833333 | DA24: NO | DB24: =IF(OR(DF24="VACACIONES",DF24="FALTA",DF24="LICENCIA",CY24="",CZ24=""),"",IF(WEEKDAY($CY$17,2)>5,CZ24-CY24,IF(DA24="NO",MIN(CZ24,CHOOSE($C24,$C$3,$C$4))-MAX(CY24,CHOOSE($C24,$B$3,$B$4))-CHOOSE($C24,$F$3,$F$4),CZ24-CY24-CHOOSE($C24,$F$3,$F$4)))) -> 0.30555556 | DC24: =IF(OR(DF24="VACACIONES",DF24="FALTA",DF24="LICENCIA",CY24="",CZ24="",WEEKDAY($CY$17,2)>5),"", MAX(0,CHOOSE($C24,$H$3,$H$4)-(DB24*1440)) ) -> 100 | DD24: =IF(OR(DF24="VACACIONES",DF24="FALTA",DF24="LICENCIA",CY24="",CZ24="",DA24="NO",WEEKDAY($CY$17,2)>5),"",MAX(0,IF(DA24="SI", (DB24*1440)-CHOOSE($C24,$H$3,$H$4) ))) | DE24: =IF(OR(DF24="VACACIONES",DF24="FALTA",DF24="LICENCIA",CY24="",CZ24="",WEEKDAY($CY$17,2)<=5),"",IF(WEEKDAY($CY$17,2)>5,(DB24*1440))) | DK24: =IF(OR(DO24="VACACIONES",DO24="FALTA",DO24="LICENCIA",DH24="",DI24=""),"",IF(WEEKDAY($DH$17,2)>5,DI24-DH24,IF(DJ24="NO",MIN(DI24,CHOOSE($C24,$C$3,$C$4))-MAX(DH24,CHOOSE($C24,$B$3,$B$4))-CHOOSE($C24,$F$3,$F$4),DI24-DH24-CHOOSE($C24,$F$3,$F$4)))) | DL24: =IF(OR(DO24="VACACIONES",DO24="FALTA",DO24="LICENCIA",DH24="",DI24="",WEEKDAY($DH$17,2)>5),"", MAX(0,CHOOSE($C24,$H$3,$H$4)-(DK24*1440)) ) | DM24: =IF(OR(DO24="VACACIONES",DO24="FALTA",DO24="LICENCIA",DH24="",DI24="",DJ24="NO",WEEKDAY($DH$17,2)>5),"",MAX(0,IF(DJ24="SI", (DK24*1440)-CHOOSE($C24,$H$3,$H$4) ))) | DN24: =IF(OR(DO24="VACACIONES",DO24="FALTA",DO24="LICENCIA",DH24="",DI24="",WEEKDAY($DH$17,2)<=5),"",IF(WEEKDAY($DH$17,2)>5,(DK24*1440))) | DT24: =IF(OR(DX24="VACACIONES",DX24="FALTA",DX24="LICENCIA",DQ24="",DR24=""),"",IF(WEEKDAY($DQ$17,2)>5,DR24-DR24,IF(DS24="NO",MIN(DR24,CHOOSE($C24,$C$3,$C$4))-MAX(DQ24,CHOOSE($C24,$B$3,$B$4))-CHOOSE($C24,$F$3,$F$4),DR24-DQ24-CHOOSE($C24,$F$3,$F$4)))) | DU24: =IF(OR(DX24="VACACIONES",DX24="FALTA",DX24="LICENCIA",DQ24="",DR24="",WEEKDAY($DQ$17,2)>5),"", MAX(0,CHOOSE($C24,$H$3,$H$4)-(DT24*1440)) ) | DV24: =IF(OR(DX24="VACACIONES",DX24="FALTA",DX24="LICENCIA",DQ24="",DR24="",DS24="NO",WEEKDAY($DQ$17,2)>5),"",MAX(0,IF(DS24="SI", (DT24*1440)-CHOOSE($C24,$H$3,$H$4) ))) | DW24: =IF(OR(DX24="VACACIONES",DX24="FALTA",DX24="LICENCIA",DQ24="",DR24="",WEEKDAY($DQ$17,2)<=5),"",IF(WEEKDAY($DQ$17,2)>5,(DT24*1440))) | DZ24: 0.39097222 | EA24: 0.75833333 | EB24: NO | EC24: =IF(OR(EG24="VACACIONES",EG24="FALTA",EG24="LICENCIA",DZ24="",EA24=""),"",IF(WEEKDAY($CY$17,2)>5,EA24-DZ24,IF(EB24="NO",MIN(EA24,CHOOSE($C24,$C$3,$C$4))-MAX(DZ24,CHOOSE($C24,$B$3,$B$4))-CHOOSE($C24,$F$3,$F$4),EA24-DZ24-CHOOSE($C24,$F$3,$F$4)))) -> 0.31736111 | ED24: =IF(OR(EG24="VACACIONES",EG24="FALTA",EG24="LICENCIA",DZ24="",EA24="",WEEKDAY($CY$17,2)>5),"", MAX(0,CHOOSE($C24,$H$3,$H$4)-(EC24*1440)) ) -> 83 | EE24: =IF(OR(EG24="VACACIONES",EG24="FALTA",EG24="LICENCIA",DZ24="",EA24="",EB24="NO",WEEKDAY($CY$17,2)>5),"",MAX(0,IF(EB24="SI", (EC24*1440)-CHOOSE($C24,$H$3,$H$4) ))) | EF24: =IF(OR(EG24="VACACIONES",EG24="FALTA",EG24="LICENCIA",DZ24="",EA24="",WEEKDAY($CY$17,2)<=5),"",IF(WEEKDAY($CY$17,2)>5,(EC24*1440))) | EK24: 0 | EL24: =SUM(I24,J24,R24,S24,AA24,AB24,AJ24,AK24,AS24,AT24,BB24,BC24,BK24,BL24,BT24,BU24,CC24,CD24,CL24,CM24,CU24,CV24,DD24,DE24,DM24,DN24,DV24,DW24,EE24,EF24) -> 0 | EM24: =COUNTIF(I24,">0")+COUNTIF(J24,">0")+COUNTIF(R24,">0")+COUNTIF(S24,">0")++COUNTIF(AA24,">0")+COUNTIF(AB24,">0")+COUNTIF(AJ24,">0")+COUNTIF(AK24,">0")+COUNTIF(AS24,">0")+COUNTIF(AT24,">0")+COUNTIF(BB24,">0")+COUNTIF(BC24,">0")+COUNTIF(BK24,">0")+COUNTIF(BL24,">0")+COUNTIF(BT24,">0")+COUNTIF(BU24,">0")+COUNTIF(CC24,">0")+COUNTIF(CD24,">0")+COUNTIF(CL24,">0")+COUNTIF(CM24,">0")+COUNTIF(CU24,">0")+COUNTIF(CV24,">0")+COUNTIF(DD24,">0")+COUNTIF(DE24,">0")+COUNTIF(DM24,">0")+COUNTIF(DN24,">0")+COUNTIF(DV24,">0")+COUNTIF(DW24,">0")+COUNTIF(EE24,">0")+COUNTIF(EF24,">0") -> 0 | EN24: =COUNTIF(D24:EG24,"FALTA") -> 0 | EO24: =15-EN24 -> 15 | EP24: =COUNTIF(D24:EG24,"TRABAJO SABADO") -> 0 | EQ24: =COUNTIF(D24:EG24,"TRABAJO DOMINGO")+COUNTIF(D24:EG24,"TRABAJO FERIADO")+(COUNTIF(D24:EG24,"TRABAJO 1RO MAYO")*2)+((COUNTIF(D26:EG26,"TRABAJO 1RO MAYO EN SU DIA LIBRE")*2)*2) -> 0 | ER24: =COUNTIF(D24:EG24,"VACACIONES") -> 0 | ES24: =COUNTIF(D24:EG24,"LICENCIA") -> 0
A25: =A24+1 -> 7 | B25: ='1RA QUINCENA JUNIO 26'!B16 -> LAGOS HUAMANI NIDIA | C25: 2 | D25: 0.38055556 | E25: 0.76388889 | F25: NO | G25: =IF(OR(K25="VACACIONES",K25="FALTA",K25="LICENCIA",D25="",E25=""),"",IF(WEEKDAY($D$17,2)>5,E25-D25,IF(F25="NO",MIN(E25,CHOOSE($C25,$C$3,$C$4))-MAX(D25,CHOOSE($C25,$B$3,$B$4))-CHOOSE($C25,$F$3,$F$4),E25-D25-CHOOSE($C25,$F$3,$F$4)))) -> 0.32777778 | H25: =IF(OR(K25="VACACIONES",K25="FALTA",K25="LICENCIA",D25="",E25="",WEEKDAY($D$17,2)>5),"", MAX(0,CHOOSE($C25,$H$3,$H$4)-(G25*1440)) ) -> 68 | I25: =IF(OR(K25="VACACIONES",K25="FALTA",K25="LICENCIA",D25="",E25="",F25="NO",WEEKDAY($D$17,2)>5),"",MAX(0,IF(F25="SI", (G25*1440)-CHOOSE($C25,$H$3,$H$4) ))) | J25: =IF(OR(K25="VACACIONES",K25="FALTA",K25="LICENCIA",D25="",E25="",WEEKDAY($D$17,2)<=5),"",IF(WEEKDAY($D$17,2)>5,(G25*1440))) | M25: 0.38194444 | N25: 0.75972222 | O25: NO | P25: =IF(OR(T25="VACACIONES",T25="FALTA",T25="LICENCIA",M25="",N25=""),"",IF(WEEKDAY($M$17,2)>5,N25-M25,IF(O25="NO",MIN(N25,CHOOSE($C25,$C$3,$C$4))-MAX(M25,CHOOSE($C25,$B$3,$B$4))-CHOOSE($C25,$F$3,$F$4),N25-M25-CHOOSE($C25,$F$3,$F$4)))) -> 0.32638889 | Q25: =IF(OR(T25="VACACIONES",T25="FALTA",T25="LICENCIA",M25="",N25="",WEEKDAY($M$17,2)>5),"", MAX(0,CHOOSE($C25,$H$3,$H$4)-(P25*1440)) ) -> 70 | R25: =IF(OR(T25="VACACIONES",T25="FALTA",T25="LICENCIA",M25="",N25="",O25="NO",WEEKDAY($M$17,2)>5),"",MAX(0,IF(O25="SI", (P25*1440)-CHOOSE($C25,$H$3,$H$4) ))) | S25: =IF(OR(T25="VACACIONES",T25="FALTA",T25="LICENCIA",M25="",N25="",WEEKDAY($M$17,2)<=5),"",IF(WEEKDAY($M$17,2)>5,(P25*1440))) | V25: 0.39930556 | W25: 0.76041667 | X25: NO | Y25: =IF(OR(AC25="VACACIONES",AC25="FALTA",AC25="LICENCIA",V25="",W25=""),"",IF(WEEKDAY($V$17,2)>5,W25-V25,IF(X25="NO",MIN(W25,CHOOSE($C25,$C$3,$C$4))-MAX(V25,CHOOSE($C25,$B$3,$B$4))-CHOOSE($C25,$F$3,$F$4),W25-V25-CHOOSE($C25,$F$3,$F$4)))) -> 0.30902778 | Z25: =IF(OR(AC25="VACACIONES",AC25="FALTA",AC25="LICENCIA",V25="",W25="",WEEKDAY($V$17,2)>5),"", MAX(0,CHOOSE($C25,$H$3,$H$4)-(Y25*1440)) ) -> 95 | AA25: =IF(OR(AC25="VACACIONES",AC25="FALTA",AC25="LICENCIA",V25="",W25="",X25="NO",WEEKDAY($V$17,2)>5),"",MAX(0,IF(X25="SI", (Y25*1440)-CHOOSE($C25,$H$3,$H$4) ))) | AB25: =IF(OR(AC25="VACACIONES",AC25="FALTA",AC25="LICENCIA",V25="",W25="",WEEKDAY($V$17,2)<=5),"",IF(WEEKDAY($V$17,2)>5,(Y25*1440))) | AE25: 0.39375 | AF25: 0.75694444 | AG25: NO | AH25: =IF(OR(AL25="VACACIONES",AL25="FALTA",AL25="LICENCIA",AE25="",AF25=""),"",IF(WEEKDAY($AE$17,2)>5,AF25-AE25,IF(AG25="NO",MIN(AF25,CHOOSE($C25,$C$3,$C$4))-MAX(AE25,CHOOSE($C25,$B$3,$B$4))-CHOOSE($C25,$F$3,$F$4),AF25-AE25-CHOOSE($C25,$F$3,$F$4)))) -> 0.31458333 | AI25: =IF(OR(AL25="VACACIONES",AL25="FALTA",AL25="LICENCIA",AE25="",AF25="",WEEKDAY($AE$17,2)>5),"", MAX(0,CHOOSE($C25,$H$3,$H$4)-(AH25*1440)) ) -> 87 | AJ25: =IF(OR(AL25="VACACIONES",AL25="FALTA",AL25="LICENCIA",AE25="",AF25="",AG25="NO",WEEKDAY($AE$17,2)>5),"",MAX(0,IF(AG25="SI", (AH25*1440)-CHOOSE($C25,$H$3,$H$4) ))) | AK25: =IF(OR(AL25="VACACIONES",AL25="FALTA",AL25="LICENCIA",AE25="",AF25="",WEEKDAY($AE$17,2)<=5),"",IF(WEEKDAY($AE$17,2)>5,(AH25*1440))) | AN25: 0.39513889 | AO25: 0.76458333 | AP25: NO | AQ25: =IF(OR(AU25="VACACIONES",AU25="FALTA",AU25="LICENCIA",AN25="",AO25=""),"",IF(WEEKDAY($AN$17,2)>5,AO25-AN25,IF(AP25="NO",MIN(AO25,CHOOSE($C25,$C$3,$C$4))-MAX(AN25,CHOOSE($C25,$B$3,$B$4))-CHOOSE($C25,$F$3,$F$4),AO25-AN25-CHOOSE($C25,$F$3,$F$4)))) -> 0.31319444 | AR25: =IF(OR(AU25="VACACIONES",AU25="FALTA",AU25="LICENCIA",AN25="",AO25="",WEEKDAY($AN$17,2)>5),"", MAX(0,CHOOSE($C25,$H$3,$H$4)-(AQ25*1440)) ) -> 89 | AS25: =IF(OR(AU25="VACACIONES",AU25="FALTA",AU25="LICENCIA",AN25="",AO25="",AP25="NO",WEEKDAY($AN$17,2)>5),"",MAX(0,IF(AP25="SI", (AQ25*1440)-CHOOSE($C25,$H$3,$H$4) ))) | AT25: =IF(OR(AU25="VACACIONES",AU25="FALTA",AU25="LICENCIA",AN25="",AO25="",WEEKDAY($AN$17,2)<=5),"",IF(WEEKDAY($AN$17,2)>5,(AQ25*1440))) | AZ25: =IF(OR(BD25="VACACIONES",BD25="FALTA",BD25="LICENCIA",AW25="",AX25=""),"",IF(WEEKDAY($AW$17,2)>5,AX25-AW25,IF(AY25="NO",MIN(AX25,CHOOSE($C25,$C$3,$C$4))-MAX(AW25,CHOOSE($C25,$B$3,$B$4))-CHOOSE($C25,$F$3,$F$4),AX25-AW25-CHOOSE($C25,$F$3,$F$4)))) | BA25: =IF(OR(BD25="VACACIONES",BD25="FALTA",BD25="LICENCIA",AW25="",AX25="",WEEKDAY($AW$17,2)>5),"", MAX(0,CHOOSE($C25,$H$3,$H$4)-(AZ25*1440)) ) | BB25: =IF(OR(BD25="VACACIONES",BD25="FALTA",BD25="LICENCIA",AW25="",AX25="",AY25="NO",WEEKDAY($AW$17,2)>5),"",MAX(0,IF(AY25="SI", (AZ25*1440)-CHOOSE($C25,$H$3,$H$4) ))) | BC25: =IF(OR(BD25="VACACIONES",BD25="FALTA",BD25="LICENCIA",AW25="",AX25="",WEEKDAY($AW$17,2)<=5),"",IF(WEEKDAY($AW$17,2)>5,(AZ25*1440))) | BI25: =IF(OR(BM25="VACACIONES",BM25="FALTA",BM25="LICENCIA",BF25="",BG25=""),"",IF(WEEKDAY($BF$17,2)>5,BG25-BF25,IF(BH25="NO",MIN(BG25,CHOOSE($C25,$C$3,$C$4))-MAX(BF25,CHOOSE($C25,$B$3,$B$4))-CHOOSE($C25,$F$3,$F$4),BG25-BF25-CHOOSE($C25,$F$3,$F$4)))) | BJ25: =IF(OR(BM25="VACACIONES",BM25="FALTA",BM25="LICENCIA",BF25="",BG25="",WEEKDAY($BF$17,2)>5),"", MAX(0,CHOOSE($C25,$H$3,$H$4)-(BI25*1440)) ) | BK25: =IF(OR(BM25="VACACIONES",BM25="FALTA",BM25="LICENCIA",BF25="",BG25="",BH25="NO",WEEKDAY($BF$17,2)>5),"",MAX(0,IF(BH25="SI", (BI25*1440)-CHOOSE($C25,$H$3,$H$4) ))) | BL25: =IF(OR(BM25="VACACIONES",BM25="FALTA",BM25="LICENCIA",BF25="",BG25="",WEEKDAY($BF$17,2)<=5),"",IF(WEEKDAY($BF$17,2)>5,(BI25*1440))) | BO25: 0.39305556 | BP25: 0.75694444 | BQ25: NO | BR25: =IF(OR(BV25="VACACIONES",BV25="FALTA",BV25="LICENCIA",BO25="",BP25=""),"",IF(WEEKDAY($BO$17,2)>5,BP25-BO25,IF(BQ25="NO",MIN(BP25,CHOOSE($C25,$C$3,$C$4))-MAX(BO25,CHOOSE($C25,$B$3,$B$4))-CHOOSE($C25,$F$3,$F$4),BP25-BO25-CHOOSE($C25,$F$3,$F$4)))) -> 0.31527778 | BS25: =IF(OR(BV25="VACACIONES",BV25="FALTA",BV25="LICENCIA",BO25="",BP25="",WEEKDAY($BO$17,2)>5),"", MAX(0,CHOOSE($C25,$H$3,$H$4)-(BR25*1440)) ) -> 86 | BT25: =IF(OR(BV25="VACACIONES",BV25="FALTA",BV25="LICENCIA",BO25="",BP25="",BQ25="NO",WEEKDAY($BO$17,2)>5),"",MAX(0,IF(BQ25="SI", (BR25*1440)-CHOOSE($C25,$H$3,$H$4) ))) | BU25: =IF(OR(BV25="VACACIONES",BV25="FALTA",BV25="LICENCIA",BO25="",BP25="",WEEKDAY($BO$17,2)<=5),"",IF(WEEKDAY($BO$17,2)>5,(BR25*1440))) | BX25: 0.39097222 | BY25: 0.76041667 | BZ25: NO | CA25: =IF(OR(CE25="VACACIONES",CE25="FALTA",CE25="LICENCIA",BX25="",BY25=""),"",IF(WEEKDAY($BX$17,2)>5,BY25-BX25,IF(BZ25="NO",MIN(BY25,CHOOSE($C25,$C$3,$C$4))-MAX(BX25,CHOOSE($C25,$B$3,$B$4))-CHOOSE($C25,$F$3,$F$4),BY25-BX25-CHOOSE($C25,$F$3,$F$4)))) -> 0.31736111 | CB25: =IF(OR(CE25="VACACIONES",CE25="FALTA",CE25="LICENCIA",BX25="",BY25="",WEEKDAY($BX$17,2)>5),"", MAX(0,CHOOSE($C25,$H$3,$H$4)-(CA25*1440)) ) -> 83 | CC25: =IF(OR(CE25="VACACIONES",CE25="FALTA",CE25="LICENCIA",BX25="",BY25="",BZ25="NO",WEEKDAY($BX$17,2)>5),"",MAX(0,IF(BZ25="SI", (CA25*1440)-CHOOSE($C25,$H$3,$H$4) ))) | CD25: =IF(OR(CE25="VACACIONES",CE25="FALTA",CE25="LICENCIA",BX25="",BY25="",WEEKDAY($BX$17,2)<=5),"",IF(WEEKDAY($BX$17,2)>5,(CA25*1440))) | CG25: 0.41111111 | CH25: 0.75902778 | CI25: NO | CJ25: =IF(OR(CN25="VACACIONES",CN25="FALTA",CN25="LICENCIA",CG25="",CH25=""),"",IF(WEEKDAY($CG$17,2)>5,CH25-CG25,IF(CI25="NO",MIN(CH25,CHOOSE($C25,$C$3,$C$4))-MAX(CG25,CHOOSE($C25,$B$3,$B$4))-CHOOSE($C25,$F$3,$F$4),CH25-CG25-CHOOSE($C25,$F$3,$F$4)))) -> 0.29722222 | CK25: =IF(OR(CN25="VACACIONES",CN25="FALTA",CN25="LICENCIA",CG25="",CH25="",WEEKDAY($CG$17,2)>5),"", MAX(0,CHOOSE($C25,$H$3,$H$4)-(CJ25*1440)) ) -> 112 | CL25: =IF(OR(CN25="VACACIONES",CN25="FALTA",CN25="LICENCIA",CG25="",CH25="",CI25="NO",WEEKDAY($CG$17,2)>5),"",MAX(0,IF(CI25="SI", (CJ25*1440)-CHOOSE($C25,$H$3,$H$4) ))) | CM25: =IF(OR(CN25="VACACIONES",CN25="FALTA",CN25="LICENCIA",CG25="",CH25="",WEEKDAY($CG$17,2)<=5),"",IF(WEEKDAY($CG$17,2)>5,(CJ25*1440))) | CP25: 0.36527778 | CQ25: 0.76388889 | CR25: NO | CS25: =IF(OR(CW25="VACACIONES",CW25="FALTA",CW25="LICENCIA",CP25="",CQ25=""),"",IF(WEEKDAY($CP$17,2)>5,CQ25-CP25,IF(CR25="NO",MIN(CQ25,CHOOSE($C25,$C$3,$C$4))-MAX(CP25,CHOOSE($C25,$B$3,$B$4))-CHOOSE($C25,$F$3,$F$4),CQ25-CP25-CHOOSE($C25,$F$3,$F$4)))) -> 0.34305556 | CT25: =IF(OR(CW25="VACACIONES",CW25="FALTA",CW25="LICENCIA",CP25="",CQ25="",WEEKDAY($CP$17,2)>5),"", MAX(0,CHOOSE($C25,$H$3,$H$4)-(CS25*1440)) ) -> 46 | CU25: =IF(OR(CW25="VACACIONES",CW25="FALTA",CW25="LICENCIA",CP25="",CQ25="",CR25="NO",WEEKDAY($CP$17,2)>5),"",MAX(0,IF(CR25="SI", (CS25*1440)-CHOOSE($C25,$H$3,$H$4) ))) | CV25: =IF(OR(CW25="VACACIONES",CW25="FALTA",CW25="LICENCIA",CP25="",CQ25="",WEEKDAY($CP$17,2)<=5),"",IF(WEEKDAY($CP$17,2)>5,(CS25*1440))) | CY25: 0.36319444 | CZ25: 0.76319444 | DA25: NO | DB25: =IF(OR(DF25="VACACIONES",DF25="FALTA",DF25="LICENCIA",CY25="",CZ25=""),"",IF(WEEKDAY($CY$17,2)>5,CZ25-CY25,IF(DA25="NO",MIN(CZ25,CHOOSE($C25,$C$3,$C$4))-MAX(CY25,CHOOSE($C25,$B$3,$B$4))-CHOOSE($C25,$F$3,$F$4),CZ25-CY25-CHOOSE($C25,$F$3,$F$4)))) -> 0.34513889 | DC25: =IF(OR(DF25="VACACIONES",DF25="FALTA",DF25="LICENCIA",CY25="",CZ25="",WEEKDAY($CY$17,2)>5),"", MAX(0,CHOOSE($C25,$H$3,$H$4)-(DB25*1440)) ) -> 43 | DD25: =IF(OR(DF25="VACACIONES",DF25="FALTA",DF25="LICENCIA",CY25="",CZ25="",DA25="NO",WEEKDAY($CY$17,2)>5),"",MAX(0,IF(DA25="SI", (DB25*1440)-CHOOSE($C25,$H$3,$H$4) ))) | DE25: =IF(OR(DF25="VACACIONES",DF25="FALTA",DF25="LICENCIA",CY25="",CZ25="",WEEKDAY($CY$17,2)<=5),"",IF(WEEKDAY($CY$17,2)>5,(DB25*1440))) | DK25: =IF(OR(DO25="VACACIONES",DO25="FALTA",DO25="LICENCIA",DH25="",DI25=""),"",IF(WEEKDAY($DH$17,2)>5,DI25-DH25,IF(DJ25="NO",MIN(DI25,CHOOSE($C25,$C$3,$C$4))-MAX(DH25,CHOOSE($C25,$B$3,$B$4))-CHOOSE($C25,$F$3,$F$4),DI25-DH25-CHOOSE($C25,$F$3,$F$4)))) | DL25: =IF(OR(DO25="VACACIONES",DO25="FALTA",DO25="LICENCIA",DH25="",DI25="",WEEKDAY($DH$17,2)>5),"", MAX(0,CHOOSE($C25,$H$3,$H$4)-(DK25*1440)) ) | DM25: =IF(OR(DO25="VACACIONES",DO25="FALTA",DO25="LICENCIA",DH25="",DI25="",DJ25="NO",WEEKDAY($DH$17,2)>5),"",MAX(0,IF(DJ25="SI", (DK25*1440)-CHOOSE($C25,$H$3,$H$4) ))) | DN25: =IF(OR(DO25="VACACIONES",DO25="FALTA",DO25="LICENCIA",DH25="",DI25="",WEEKDAY($DH$17,2)<=5),"",IF(WEEKDAY($DH$17,2)>5,(DK25*1440))) | DT25: =IF(OR(DX25="VACACIONES",DX25="FALTA",DX25="LICENCIA",DQ25="",DR25=""),"",IF(WEEKDAY($DQ$17,2)>5,DR25-DR25,IF(DS25="NO",MIN(DR25,CHOOSE($C25,$C$3,$C$4))-MAX(DQ25,CHOOSE($C25,$B$3,$B$4))-CHOOSE($C25,$F$3,$F$4),DR25-DQ25-CHOOSE($C25,$F$3,$F$4)))) | DU25: =IF(OR(DX25="VACACIONES",DX25="FALTA",DX25="LICENCIA",DQ25="",DR25="",WEEKDAY($DQ$17,2)>5),"", MAX(0,CHOOSE($C25,$H$3,$H$4)-(DT25*1440)) ) | DV25: =IF(OR(DX25="VACACIONES",DX25="FALTA",DX25="LICENCIA",DQ25="",DR25="",DS25="NO",WEEKDAY($DQ$17,2)>5),"",MAX(0,IF(DS25="SI", (DT25*1440)-CHOOSE($C25,$H$3,$H$4) ))) | DW25: =IF(OR(DX25="VACACIONES",DX25="FALTA",DX25="LICENCIA",DQ25="",DR25="",WEEKDAY($DQ$17,2)<=5),"",IF(WEEKDAY($DQ$17,2)>5,(DT25*1440))) | DZ25: 0.375 | EA25: 0.76319444 | EB25: NO | EC25: =IF(OR(EG25="VACACIONES",EG25="FALTA",EG25="LICENCIA",DZ25="",EA25=""),"",IF(WEEKDAY($CY$17,2)>5,EA25-DZ25,IF(EB25="NO",MIN(EA25,CHOOSE($C25,$C$3,$C$4))-MAX(DZ25,CHOOSE($C25,$B$3,$B$4))-CHOOSE($C25,$F$3,$F$4),EA25-DZ25-CHOOSE($C25,$F$3,$F$4)))) -> 0.33333333 | ED25: =IF(OR(EG25="VACACIONES",EG25="FALTA",EG25="LICENCIA",DZ25="",EA25="",WEEKDAY($CY$17,2)>5),"", MAX(0,CHOOSE($C25,$H$3,$H$4)-(EC25*1440)) ) -> 60 | EE25: =IF(OR(EG25="VACACIONES",EG25="FALTA",EG25="LICENCIA",DZ25="",EA25="",EB25="NO",WEEKDAY($CY$17,2)>5),"",MAX(0,IF(EB25="SI", (EC25*1440)-CHOOSE($C25,$H$3,$H$4) ))) | EF25: =IF(OR(EG25="VACACIONES",EG25="FALTA",EG25="LICENCIA",DZ25="",EA25="",WEEKDAY($CY$17,2)<=5),"",IF(WEEKDAY($CY$17,2)>5,(EC25*1440))) | EK25: =SUM(H25,Q25,Z25,AI25,AR25,BA25,BJ25,BS25,CB25,CK25,CT25,DC25,DL25,DU25,ED25) -> 839 | EL25: =SUM(I25,J25,R25,S25,AA25,AB25,AJ25,AK25,AS25,AT25,BB25,BC25,BK25,BL25,BT25,BU25,CC25,CD25,CL25,CM25,CU25,CV25,DD25,DE25,DM25,DN25,DV25,DW25,EE25,EF25) -> 0 | EM25: =COUNTIF(I25,">0")+COUNTIF(J25,">0")+COUNTIF(R25,">0")+COUNTIF(S25,">0")++COUNTIF(AA25,">0")+COUNTIF(AB25,">0")+COUNTIF(AJ25,">0")+COUNTIF(AK25,">0")+COUNTIF(AS25,">0")+COUNTIF(AT25,">0")+COUNTIF(BB25,">0")+COUNTIF(BC25,">0")+COUNTIF(BK25,">0")+COUNTIF(BL25,">0")+COUNTIF(BT25,">0")+COUNTIF(BU25,">0")+COUNTIF(CC25,">0")+COUNTIF(CD25,">0")+COUNTIF(CL25,">0")+COUNTIF(CM25,">0")+COUNTIF(CU25,">0")+COUNTIF(CV25,">0")+COUNTIF(DD25,">0")+COUNTIF(DE25,">0")+COUNTIF(DM25,">0")+COUNTIF(DN25,">0")+COUNTIF(DV25,">0")+COUNTIF(DW25,">0")+COUNTIF(EE25,">0")+COUNTIF(EF25,">0") -> 0 | EN25: =COUNTIF(D25:EG25,"FALTA") -> 0 | EO25: =15-EN25 -> 15 | EP25: =COUNTIF(D25:EG25,"TRABAJO SABADO") -> 0 | EQ25: =COUNTIF(D25:EG25,"TRABAJO DOMINGO")+COUNTIF(D25:EG25,"TRABAJO FERIADO")+(COUNTIF(D25:EG25,"TRABAJO 1RO MAYO")*2)+((COUNTIF(D27:EG27,"TRABAJO 1RO MAYO EN SU DIA LIBRE")*2)*2) -> 0 | ER25: =COUNTIF(D25:EG25,"VACACIONES") -> 0 | ES25: =COUNTIF(D25:EG25,"LICENCIA") -> 0
A26: =A25+1 -> 8 | B26: ='1RA QUINCENA JUNIO 26'!B17 -> MERCADO SANCHEZ NORMA AURELIA | C26: 2 | D26: 0.37083333 | E26: 0.76388889 | F26: NO | G26: =IF(OR(K26="VACACIONES",K26="FALTA",K26="LICENCIA",D26="",E26=""),"",IF(WEEKDAY($D$17,2)>5,E26-D26,IF(F26="NO",MIN(E26,CHOOSE($C26,$C$3,$C$4))-MAX(D26,CHOOSE($C26,$B$3,$B$4))-CHOOSE($C26,$F$3,$F$4),E26-D26-CHOOSE($C26,$F$3,$F$4)))) -> 0.3375 | H26: =IF(OR(K26="VACACIONES",K26="FALTA",K26="LICENCIA",D26="",E26="",WEEKDAY($D$17,2)>5),"", MAX(0,CHOOSE($C26,$H$3,$H$4)-(G26*1440)) ) -> 54 | I26: =IF(OR(K26="VACACIONES",K26="FALTA",K26="LICENCIA",D26="",E26="",F26="NO",WEEKDAY($D$17,2)>5),"",MAX(0,IF(F26="SI", (G26*1440)-CHOOSE($C26,$H$3,$H$4) ))) | J26: =IF(OR(K26="VACACIONES",K26="FALTA",K26="LICENCIA",D26="",E26="",WEEKDAY($D$17,2)<=5),"",IF(WEEKDAY($D$17,2)>5,(G26*1440))) | M26: 0.38333333 | N26: 0.75972222 | O26: NO | P26: =IF(OR(T26="VACACIONES",T26="FALTA",T26="LICENCIA",M26="",N26=""),"",IF(WEEKDAY($M$17,2)>5,N26-M26,IF(O26="NO",MIN(N26,CHOOSE($C26,$C$3,$C$4))-MAX(M26,CHOOSE($C26,$B$3,$B$4))-CHOOSE($C26,$F$3,$F$4),N26-M26-CHOOSE($C26,$F$3,$F$4)))) -> 0.325 | Q26: =IF(OR(T26="VACACIONES",T26="FALTA",T26="LICENCIA",M26="",N26="",WEEKDAY($M$17,2)>5),"", MAX(0,CHOOSE($C26,$H$3,$H$4)-(P26*1440)) ) -> 72 | R26: =IF(OR(T26="VACACIONES",T26="FALTA",T26="LICENCIA",M26="",N26="",O26="NO",WEEKDAY($M$17,2)>5),"",MAX(0,IF(O26="SI", (P26*1440)-CHOOSE($C26,$H$3,$H$4) ))) | S26: =IF(OR(T26="VACACIONES",T26="FALTA",T26="LICENCIA",M26="",N26="",WEEKDAY($M$17,2)<=5),"",IF(WEEKDAY($M$17,2)>5,(P26*1440))) | V26: 0.38472222 | W26: 0.76041667 | X26: NO | Y26: =IF(OR(AC26="VACACIONES",AC26="FALTA",AC26="LICENCIA",V26="",W26=""),"",IF(WEEKDAY($V$17,2)>5,W26-V26,IF(X26="NO",MIN(W26,CHOOSE($C26,$C$3,$C$4))-MAX(V26,CHOOSE($C26,$B$3,$B$4))-CHOOSE($C26,$F$3,$F$4),W26-V26-CHOOSE($C26,$F$3,$F$4)))) -> 0.32361111 | Z26: =IF(OR(AC26="VACACIONES",AC26="FALTA",AC26="LICENCIA",V26="",W26="",WEEKDAY($V$17,2)>5),"", MAX(0,CHOOSE($C26,$H$3,$H$4)-(Y26*1440)) ) -> 74 | AA26: =IF(OR(AC26="VACACIONES",AC26="FALTA",AC26="LICENCIA",V26="",W26="",X26="NO",WEEKDAY($V$17,2)>5),"",MAX(0,IF(X26="SI", (Y26*1440)-CHOOSE($C26,$H$3,$H$4) ))) | AB26: =IF(OR(AC26="VACACIONES",AC26="FALTA",AC26="LICENCIA",V26="",W26="",WEEKDAY($V$17,2)<=5),"",IF(WEEKDAY($V$17,2)>5,(Y26*1440))) | AE26: 0.38472222 | AF26: 0.75694444 | AG26: NO | AH26: =IF(OR(AL26="VACACIONES",AL26="FALTA",AL26="LICENCIA",AE26="",AF26=""),"",IF(WEEKDAY($AE$17,2)>5,AF26-AE26,IF(AG26="NO",MIN(AF26,CHOOSE($C26,$C$3,$C$4))-MAX(AE26,CHOOSE($C26,$B$3,$B$4))-CHOOSE($C26,$F$3,$F$4),AF26-AE26-CHOOSE($C26,$F$3,$F$4)))) -> 0.32361111 | AI26: =IF(OR(AL26="VACACIONES",AL26="FALTA",AL26="LICENCIA",AE26="",AF26="",WEEKDAY($AE$17,2)>5),"", MAX(0,CHOOSE($C26,$H$3,$H$4)-(AH26*1440)) ) -> 74 | AJ26: =IF(OR(AL26="VACACIONES",AL26="FALTA",AL26="LICENCIA",AE26="",AF26="",AG26="NO",WEEKDAY($AE$17,2)>5),"",MAX(0,IF(AG26="SI", (AH26*1440)-CHOOSE($C26,$H$3,$H$4) ))) | AK26: =IF(OR(AL26="VACACIONES",AL26="FALTA",AL26="LICENCIA",AE26="",AF26="",WEEKDAY($AE$17,2)<=5),"",IF(WEEKDAY($AE$17,2)>5,(AH26*1440))) | AN26: 0.37916667 | AO26: 0.76458333 | AP26: NO | AQ26: =IF(OR(AU26="VACACIONES",AU26="FALTA",AU26="LICENCIA",AN26="",AO26=""),"",IF(WEEKDAY($AN$17,2)>5,AO26-AN26,IF(AP26="NO",MIN(AO26,CHOOSE($C26,$C$3,$C$4))-MAX(AN26,CHOOSE($C26,$B$3,$B$4))-CHOOSE($C26,$F$3,$F$4),AO26-AN26-CHOOSE($C26,$F$3,$F$4)))) -> 0.32916667 | AR26: =IF(OR(AU26="VACACIONES",AU26="FALTA",AU26="LICENCIA",AN26="",AO26="",WEEKDAY($AN$17,2)>5),"", MAX(0,CHOOSE($C26,$H$3,$H$4)-(AQ26*1440)) ) -> 66 | AS26: =IF(OR(AU26="VACACIONES",AU26="FALTA",AU26="LICENCIA",AN26="",AO26="",AP26="NO",WEEKDAY($AN$17,2)>5),"",MAX(0,IF(AP26="SI", (AQ26*1440)-CHOOSE($C26,$H$3,$H$4) ))) | AT26: =IF(OR(AU26="VACACIONES",AU26="FALTA",AU26="LICENCIA",AN26="",AO26="",WEEKDAY($AN$17,2)<=5),"",IF(WEEKDAY($AN$17,2)>5,(AQ26*1440))) | AZ26: =IF(OR(BD26="VACACIONES",BD26="FALTA",BD26="LICENCIA",AW26="",AX26=""),"",IF(WEEKDAY($AW$17,2)>5,AX26-AW26,IF(AY26="NO",MIN(AX26,CHOOSE($C26,$C$3,$C$4))-MAX(AW26,CHOOSE($C26,$B$3,$B$4))-CHOOSE($C26,$F$3,$F$4),AX26-AW26-CHOOSE($C26,$F$3,$F$4)))) | BA26: =IF(OR(BD26="VACACIONES",BD26="FALTA",BD26="LICENCIA",AW26="",AX26="",WEEKDAY($AW$17,2)>5),"", MAX(0,CHOOSE($C26,$H$3,$H$4)-(AZ26*1440)) ) | BB26: =IF(OR(BD26="VACACIONES",BD26="FALTA",BD26="LICENCIA",AW26="",AX26="",AY26="NO",WEEKDAY($AW$17,2)>5),"",MAX(0,IF(AY26="SI", (AZ26*1440)-CHOOSE($C26,$H$3,$H$4) ))) | BC26: =IF(OR(BD26="VACACIONES",BD26="FALTA",BD26="LICENCIA",AW26="",AX26="",WEEKDAY($AW$17,2)<=5),"",IF(WEEKDAY($AW$17,2)>5,(AZ26*1440))) | BI26: =IF(OR(BM26="VACACIONES",BM26="FALTA",BM26="LICENCIA",BF26="",BG26=""),"",IF(WEEKDAY($BF$17,2)>5,BG26-BF26,IF(BH26="NO",MIN(BG26,CHOOSE($C26,$C$3,$C$4))-MAX(BF26,CHOOSE($C26,$B$3,$B$4))-CHOOSE($C26,$F$3,$F$4),BG26-BF26-CHOOSE($C26,$F$3,$F$4)))) | BJ26: =IF(OR(BM26="VACACIONES",BM26="FALTA",BM26="LICENCIA",BF26="",BG26="",WEEKDAY($BF$17,2)>5),"", MAX(0,CHOOSE($C26,$H$3,$H$4)-(BI26*1440)) ) | BK26: =IF(OR(BM26="VACACIONES",BM26="FALTA",BM26="LICENCIA",BF26="",BG26="",BH26="NO",WEEKDAY($BF$17,2)>5),"",MAX(0,IF(BH26="SI", (BI26*1440)-CHOOSE($C26,$H$3,$H$4) ))) | BL26: =IF(OR(BM26="VACACIONES",BM26="FALTA",BM26="LICENCIA",BF26="",BG26="",WEEKDAY($BF$17,2)<=5),"",IF(WEEKDAY($BF$17,2)>5,(BI26*1440))) | BO26: 0.37986111 | BP26: 0.69444444 | BQ26: NO | BR26: =IF(OR(BV26="VACACIONES",BV26="FALTA",BV26="LICENCIA",BO26="",BP26=""),"",IF(WEEKDAY($BO$17,2)>5,BP26-BO26,IF(BQ26="NO",MIN(BP26,CHOOSE($C26,$C$3,$C$4))-MAX(BO26,CHOOSE($C26,$B$3,$B$4))-CHOOSE($C26,$F$3,$F$4),BP26-BO26-CHOOSE($C26,$F$3,$F$4)))) -> 0.27291667 | BS26: =IF(OR(BV26="VACACIONES",BV26="FALTA",BV26="LICENCIA",BO26="",BP26="",WEEKDAY($BO$17,2)>5),"", MAX(0,CHOOSE($C26,$H$3,$H$4)-(BR26*1440)) ) -> 147 | BT26: =IF(OR(BV26="VACACIONES",BV26="FALTA",BV26="LICENCIA",BO26="",BP26="",BQ26="NO",WEEKDAY($BO$17,2)>5),"",MAX(0,IF(BQ26="SI", (BR26*1440)-CHOOSE($C26,$H$3,$H$4) ))) | BU26: =IF(OR(BV26="VACACIONES",BV26="FALTA",BV26="LICENCIA",BO26="",BP26="",WEEKDAY($BO$17,2)<=5),"",IF(WEEKDAY($BO$17,2)>5,(BR26*1440))) | BX26: 0.35833333 | BY26: 0.79166667 | BZ26: SI | CA26: =IF(OR(CE26="VACACIONES",CE26="FALTA",CE26="LICENCIA",BX26="",BY26=""),"",IF(WEEKDAY($BX$17,2)>5,BY26-BX26,IF(BZ26="NO",MIN(BY26,CHOOSE($C26,$C$3,$C$4))-MAX(BX26,CHOOSE($C26,$B$3,$B$4))-CHOOSE($C26,$F$3,$F$4),BY26-BX26-CHOOSE($C26,$F$3,$F$4)))) -> 0.39166667 | CB26: =IF(OR(CE26="VACACIONES",CE26="FALTA",CE26="LICENCIA",BX26="",BY26="",WEEKDAY($BX$17,2)>5),"", MAX(0,CHOOSE($C26,$H$3,$H$4)-(CA26*1440)) ) -> 0 | CC26: =IF(OR(CE26="VACACIONES",CE26="FALTA",CE26="LICENCIA",BX26="",BY26="",BZ26="NO",WEEKDAY($BX$17,2)>5),"",MAX(0,IF(BZ26="SI", (CA26*1440)-CHOOSE($C26,$H$3,$H$4) ))) -> 24 | CD26: =IF(OR(CE26="VACACIONES",CE26="FALTA",CE26="LICENCIA",BX26="",BY26="",WEEKDAY($BX$17,2)<=5),"",IF(WEEKDAY($BX$17,2)>5,(CA26*1440))) | CG26: 0.375 | CH26: 0.75902778 | CI26: NO | CJ26: =IF(OR(CN26="VACACIONES",CN26="FALTA",CN26="LICENCIA",CG26="",CH26=""),"",IF(WEEKDAY($CG$17,2)>5,CH26-CG26,IF(CI26="NO",MIN(CH26,CHOOSE($C26,$C$3,$C$4))-MAX(CG26,CHOOSE($C26,$B$3,$B$4))-CHOOSE($C26,$F$3,$F$4),CH26-CG26-CHOOSE($C26,$F$3,$F$4)))) -> 0.33333333 | CK26: =IF(OR(CN26="VACACIONES",CN26="FALTA",CN26="LICENCIA",CG26="",CH26="",WEEKDAY($CG$17,2)>5),"", MAX(0,CHOOSE($C26,$H$3,$H$4)-(CJ26*1440)) ) -> 60 | CL26: =IF(OR(CN26="VACACIONES",CN26="FALTA",CN26="LICENCIA",CG26="",CH26="",CI26="NO",WEEKDAY($CG$17,2)>5),"",MAX(0,IF(CI26="SI", (CJ26*1440)-CHOOSE($C26,$H$3,$H$4) ))) | CM26: =IF(OR(CN26="VACACIONES",CN26="FALTA",CN26="LICENCIA",CG26="",CH26="",WEEKDAY($CG$17,2)<=5),"",IF(WEEKDAY($CG$17,2)>5,(CJ26*1440))) | CP26: 0.31597222 | CQ26: 0.76388889 | CR26: NO | CS26: =IF(OR(CW26="VACACIONES",CW26="FALTA",CW26="LICENCIA",CP26="",CQ26=""),"",IF(WEEKDAY($CP$17,2)>5,CQ26-CP26,IF(CR26="NO",MIN(CQ26,CHOOSE($C26,$C$3,$C$4))-MAX(CP26,CHOOSE($C26,$B$3,$B$4))-CHOOSE($C26,$F$3,$F$4),CQ26-CP26-CHOOSE($C26,$F$3,$F$4)))) -> 0.375 | CT26: =IF(OR(CW26="VACACIONES",CW26="FALTA",CW26="LICENCIA",CP26="",CQ26="",WEEKDAY($CP$17,2)>5),"", MAX(0,CHOOSE($C26,$H$3,$H$4)-(CS26*1440)) ) -> 0 | CU26: =IF(OR(CW26="VACACIONES",CW26="FALTA",CW26="LICENCIA",CP26="",CQ26="",CR26="NO",WEEKDAY($CP$17,2)>5),"",MAX(0,IF(CR26="SI", (CS26*1440)-CHOOSE($C26,$H$3,$H$4) ))) | CV26: =IF(OR(CW26="VACACIONES",CW26="FALTA",CW26="LICENCIA",CP26="",CQ26="",WEEKDAY($CP$17,2)<=5),"",IF(WEEKDAY($CP$17,2)>5,(CS26*1440))) | CY26: 0.37569444 | CZ26: 0.76319444 | DA26: NO | DB26: =IF(OR(DF26="VACACIONES",DF26="FALTA",DF26="LICENCIA",CY26="",CZ26=""),"",IF(WEEKDAY($CY$17,2)>5,CZ26-CY26,IF(DA26="NO",MIN(CZ26,CHOOSE($C26,$C$3,$C$4))-MAX(CY26,CHOOSE($C26,$B$3,$B$4))-CHOOSE($C26,$F$3,$F$4),CZ26-CY26-CHOOSE($C26,$F$3,$F$4)))) -> 0.33263889 | DC26: =IF(OR(DF26="VACACIONES",DF26="FALTA",DF26="LICENCIA",CY26="",CZ26="",WEEKDAY($CY$17,2)>5),"", MAX(0,CHOOSE($C26,$H$3,$H$4)-(DB26*1440)) ) -> 61 | DD26: =IF(OR(DF26="VACACIONES",DF26="FALTA",DF26="LICENCIA",CY26="",CZ26="",DA26="NO",WEEKDAY($CY$17,2)>5),"",MAX(0,IF(DA26="SI", (DB26*1440)-CHOOSE($C26,$H$3,$H$4) ))) | DE26: =IF(OR(DF26="VACACIONES",DF26="FALTA",DF26="LICENCIA",CY26="",CZ26="",WEEKDAY($CY$17,2)<=5),"",IF(WEEKDAY($CY$17,2)>5,(DB26*1440))) | DK26: =IF(OR(DO26="VACACIONES",DO26="FALTA",DO26="LICENCIA",DH26="",DI26=""),"",IF(WEEKDAY($DH$17,2)>5,DI26-DH26,IF(DJ26="NO",MIN(DI26,CHOOSE($C26,$C$3,$C$4))-MAX(DH26,CHOOSE($C26,$B$3,$B$4))-CHOOSE($C26,$F$3,$F$4),DI26-DH26-CHOOSE($C26,$F$3,$F$4)))) | DL26: =IF(OR(DO26="VACACIONES",DO26="FALTA",DO26="LICENCIA",DH26="",DI26="",WEEKDAY($DH$17,2)>5),"", MAX(0,CHOOSE($C26,$H$3,$H$4)-(DK26*1440)) ) | DM26: =IF(OR(DO26="VACACIONES",DO26="FALTA",DO26="LICENCIA",DH26="",DI26="",DJ26="NO",WEEKDAY($DH$17,2)>5),"",MAX(0,IF(DJ26="SI", (DK26*1440)-CHOOSE($C26,$H$3,$H$4) ))) | DN26: =IF(OR(DO26="VACACIONES",DO26="FALTA",DO26="LICENCIA",DH26="",DI26="",WEEKDAY($DH$17,2)<=5),"",IF(WEEKDAY($DH$17,2)>5,(DK26*1440))) | DT26: =IF(OR(DX26="VACACIONES",DX26="FALTA",DX26="LICENCIA",DQ26="",DR26=""),"",IF(WEEKDAY($DQ$17,2)>5,DR26-DR26,IF(DS26="NO",MIN(DR26,CHOOSE($C26,$C$3,$C$4))-MAX(DQ26,CHOOSE($C26,$B$3,$B$4))-CHOOSE($C26,$F$3,$F$4),DR26-DQ26-CHOOSE($C26,$F$3,$F$4)))) | DU26: =IF(OR(DX26="VACACIONES",DX26="FALTA",DX26="LICENCIA",DQ26="",DR26="",WEEKDAY($DQ$17,2)>5),"", MAX(0,CHOOSE($C26,$H$3,$H$4)-(DT26*1440)) ) | DV26: =IF(OR(DX26="VACACIONES",DX26="FALTA",DX26="LICENCIA",DQ26="",DR26="",DS26="NO",WEEKDAY($DQ$17,2)>5),"",MAX(0,IF(DS26="SI", (DT26*1440)-CHOOSE($C26,$H$3,$H$4) ))) | DW26: =IF(OR(DX26="VACACIONES",DX26="FALTA",DX26="LICENCIA",DQ26="",DR26="",WEEKDAY($DQ$17,2)<=5),"",IF(WEEKDAY($DQ$17,2)>5,(DT26*1440))) | DZ26: 0.37152778 | EA26: 0.76319444 | EB26: NO | EC26: =IF(OR(EG26="VACACIONES",EG26="FALTA",EG26="LICENCIA",DZ26="",EA26=""),"",IF(WEEKDAY($CY$17,2)>5,EA26-DZ26,IF(EB26="NO",MIN(EA26,CHOOSE($C26,$C$3,$C$4))-MAX(DZ26,CHOOSE($C26,$B$3,$B$4))-CHOOSE($C26,$F$3,$F$4),EA26-DZ26-CHOOSE($C26,$F$3,$F$4)))) -> 0.33680556 | ED26: =IF(OR(EG26="VACACIONES",EG26="FALTA",EG26="LICENCIA",DZ26="",EA26="",WEEKDAY($CY$17,2)>5),"", MAX(0,CHOOSE($C26,$H$3,$H$4)-(EC26*1440)) ) -> 55 | EE26: =IF(OR(EG26="VACACIONES",EG26="FALTA",EG26="LICENCIA",DZ26="",EA26="",EB26="NO",WEEKDAY($CY$17,2)>5),"",MAX(0,IF(EB26="SI", (EC26*1440)-CHOOSE($C26,$H$3,$H$4) ))) | EF26: =IF(OR(EG26="VACACIONES",EG26="FALTA",EG26="LICENCIA",DZ26="",EA26="",WEEKDAY($CY$17,2)<=5),"",IF(WEEKDAY($CY$17,2)>5,(EC26*1440))) | EK26: =SUM(H26,Q26,Z26,AI26,AR26,BA26,BJ26,BS26,CB26,CK26,CT26,DC26,DL26,DU26,ED26) -> 663 | EL26: =SUM(I26,J26,R26,S26,AA26,AB26,AJ26,AK26,AS26,AT26,BB26,BC26,BK26,BL26,BT26,BU26,CC26,CD26,CL26,CM26,CU26,CV26,DD26,DE26,DM26,DN26,DV26,DW26,EE26,EF26) -> 24 | EM26: =COUNTIF(I26,">0")+COUNTIF(J26,">0")+COUNTIF(R26,">0")+COUNTIF(S26,">0")++COUNTIF(AA26,">0")+COUNTIF(AB26,">0")+COUNTIF(AJ26,">0")+COUNTIF(AK26,">0")+COUNTIF(AS26,">0")+COUNTIF(AT26,">0")+COUNTIF(BB26,">0")+COUNTIF(BC26,">0")+COUNTIF(BK26,">0")+COUNTIF(BL26,">0")+COUNTIF(BT26,">0")+COUNTIF(BU26,">0")+COUNTIF(CC26,">0")+COUNTIF(CD26,">0")+COUNTIF(CL26,">0")+COUNTIF(CM26,">0")+COUNTIF(CU26,">0")+COUNTIF(CV26,">0")+COUNTIF(DD26,">0")+COUNTIF(DE26,">0")+COUNTIF(DM26,">0")+COUNTIF(DN26,">0")+COUNTIF(DV26,">0")+COUNTIF(DW26,">0")+COUNTIF(EE26,">0")+COUNTIF(EF26,">0") -> 1 | EN26: =COUNTIF(D26:EG26,"FALTA") -> 0 | EO26: =15-EN26 -> 15 | EP26: =COUNTIF(D26:EG26,"TRABAJO SABADO") -> 0 | EQ26: =COUNTIF(D26:EG26,"TRABAJO DOMINGO")+COUNTIF(D26:EG26,"TRABAJO FERIADO")+(COUNTIF(D26:EG26,"TRABAJO 1RO MAYO")*2)+((COUNTIF(D28:EG28,"TRABAJO 1RO MAYO EN SU DIA LIBRE")*2)*2) -> 0 | ER26: =COUNTIF(D26:EG26,"VACACIONES") -> 0 | ES26: =COUNTIF(D26:EG26,"LICENCIA") -> 0
A27: SI | B27: ='1RA QUINCENA JUNIO 26'!B18 -> MONTENEGRO OBLITAS GROVER MANUEL | C27: 1 | D27: 0.325 | E27: 0.77430556 | F27: SI | G27: =IF(OR(K27="VACACIONES",K27="FALTA",K27="LICENCIA",D27="",E27=""),"",IF(WEEKDAY($D$17,2)>5,E27-D27,IF(F27="NO",MIN(E27,CHOOSE($C27,$C$3,$C$4))-MAX(D27,CHOOSE($C27,$B$3,$B$4))-CHOOSE($C27,$F$3,$F$4),E27-D27-CHOOSE($C27,$F$3,$F$4)))) -> 0.40763889 | H27: =IF(OR(K27="VACACIONES",K27="FALTA",K27="LICENCIA",D27="",E27="",WEEKDAY($D$17,2)>5),"", MAX(0,CHOOSE($C27,$H$3,$H$4)-(G27*1440)) ) -> 0 | I27: =IF(OR(K27="VACACIONES",K27="FALTA",K27="LICENCIA",D27="",E27="",F27="NO",WEEKDAY($D$17,2)>5),"",MAX(0,IF(F27="SI", (G27*1440)-CHOOSE($C27,$H$3,$H$4) ))) -> 10 | J27: =IF(OR(K27="VACACIONES",K27="FALTA",K27="LICENCIA",D27="",E27="",WEEKDAY($D$17,2)<=5),"",IF(WEEKDAY($D$17,2)>5,(G27*1440))) | M27: 0.32638889 | N27: 0.77916667 | O27: SI | P27: =IF(OR(T27="VACACIONES",T27="FALTA",T27="LICENCIA",M27="",N27=""),"",IF(WEEKDAY($M$17,2)>5,N27-M27,IF(O27="NO",MIN(N27,CHOOSE($C27,$C$3,$C$4))-MAX(M27,CHOOSE($C27,$B$3,$B$4))-CHOOSE($C27,$F$3,$F$4),N27-M27-CHOOSE($C27,$F$3,$F$4)))) -> 0.41111111 | Q27: =IF(OR(T27="VACACIONES",T27="FALTA",T27="LICENCIA",M27="",N27="",WEEKDAY($M$17,2)>5),"", MAX(0,CHOOSE($C27,$H$3,$H$4)-(P27*1440)) ) -> 0 | R27: =IF(OR(T27="VACACIONES",T27="FALTA",T27="LICENCIA",M27="",N27="",O27="NO",WEEKDAY($M$17,2)>5),"",MAX(0,IF(O27="SI", (P27*1440)-CHOOSE($C27,$H$3,$H$4) ))) -> 15 | S27: =IF(OR(T27="VACACIONES",T27="FALTA",T27="LICENCIA",M27="",N27="",WEEKDAY($M$17,2)<=5),"",IF(WEEKDAY($M$17,2)>5,(P27*1440))) | V27: 0.31527778 | W27: 0.79861111 | X27: SI | Y27: =IF(OR(AC27="VACACIONES",AC27="FALTA",AC27="LICENCIA",V27="",W27=""),"",IF(WEEKDAY($V$17,2)>5,W27-V27,IF(X27="NO",MIN(W27,CHOOSE($C27,$C$3,$C$4))-MAX(V27,CHOOSE($C27,$B$3,$B$4))-CHOOSE($C27,$F$3,$F$4),W27-V27-CHOOSE($C27,$F$3,$F$4)))) -> 0.44166667 | Z27: =IF(OR(AC27="VACACIONES",AC27="FALTA",AC27="LICENCIA",V27="",W27="",WEEKDAY($V$17,2)>5),"", MAX(0,CHOOSE($C27,$H$3,$H$4)-(Y27*1440)) ) -> 0 | AA27: =IF(OR(AC27="VACACIONES",AC27="FALTA",AC27="LICENCIA",V27="",W27="",X27="NO",WEEKDAY($V$17,2)>5),"",MAX(0,IF(X27="SI", (Y27*1440)-CHOOSE($C27,$H$3,$H$4) ))) -> 59 | AB27: =IF(OR(AC27="VACACIONES",AC27="FALTA",AC27="LICENCIA",V27="",W27="",WEEKDAY($V$17,2)<=5),"",IF(WEEKDAY($V$17,2)>5,(Y27*1440))) | AE27: 0.31388889 | AF27: 0.79861111 | AG27: SI | AH27: =IF(OR(AL27="VACACIONES",AL27="FALTA",AL27="LICENCIA",AE27="",AF27=""),"",IF(WEEKDAY($AE$17,2)>5,AF27-AE27,IF(AG27="NO",MIN(AF27,CHOOSE($C27,$C$3,$C$4))-MAX(AE27,CHOOSE($C27,$B$3,$B$4))-CHOOSE($C27,$F$3,$F$4),AF27-AE27-CHOOSE($C27,$F$3,$F$4)))) -> 0.44305556 | AI27: =IF(OR(AL27="VACACIONES",AL27="FALTA",AL27="LICENCIA",AE27="",AF27="",WEEKDAY($AE$17,2)>5),"", MAX(0,CHOOSE($C27,$H$3,$H$4)-(AH27*1440)) ) -> 0 | AJ27: =IF(OR(AL27="VACACIONES",AL27="FALTA",AL27="LICENCIA",AE27="",AF27="",AG27="NO",WEEKDAY($AE$17,2)>5),"",MAX(0,IF(AG27="SI", (AH27*1440)-CHOOSE($C27,$H$3,$H$4) ))) -> 61 | AK27: =IF(OR(AL27="VACACIONES",AL27="FALTA",AL27="LICENCIA",AE27="",AF27="",WEEKDAY($AE$17,2)<=5),"",IF(WEEKDAY($AE$17,2)>5,(AH27*1440))) | AN27: 0.30763889 | AO27: 0.79861111 | AP27: SI | AQ27: =IF(OR(AU27="VACACIONES",AU27="FALTA",AU27="LICENCIA",AN27="",AO27=""),"",IF(WEEKDAY($AN$17,2)>5,AO27-AN27,IF(AP27="NO",MIN(AO27,CHOOSE($C27,$C$3,$C$4))-MAX(AN27,CHOOSE($C27,$B$3,$B$4))-CHOOSE($C27,$F$3,$F$4),AO27-AN27-CHOOSE($C27,$F$3,$F$4)))) -> 0.44930556 | AR27: =IF(OR(AU27="VACACIONES",AU27="FALTA",AU27="LICENCIA",AN27="",AO27="",WEEKDAY($AN$17,2)>5),"", MAX(0,CHOOSE($C27,$H$3,$H$4)-(AQ27*1440)) ) -> 0 | AS27: =IF(OR(AU27="VACACIONES",AU27="FALTA",AU27="LICENCIA",AN27="",AO27="",AP27="NO",WEEKDAY($AN$17,2)>5),"",MAX(0,IF(AP27="SI", (AQ27*1440)-CHOOSE($C27,$H$3,$H$4) ))) -> 70 | AT27: =IF(OR(AU27="VACACIONES",AU27="FALTA",AU27="LICENCIA",AN27="",AO27="",WEEKDAY($AN$17,2)<=5),"",IF(WEEKDAY($AN$17,2)>5,(AQ27*1440))) | AW27: 0.30902778 | AX27: 0.55763889 | AZ27: =IF(OR(BD27="VACACIONES",BD27="FALTA",BD27="LICENCIA",AW27="",AX27=""),"",IF(WEEKDAY($AW$17,2)>5,AX27-AW27,IF(AY27="NO",MIN(AX27,CHOOSE($C27,$C$3,$C$4))-MAX(AW27,CHOOSE($C27,$B$3,$B$4))-CHOOSE($C27,$F$3,$F$4),AX27-AW27-CHOOSE($C27,$F$3,$F$4)))) -> 0.24861111 | BA27: =IF(OR(BD27="VACACIONES",BD27="FALTA",BD27="LICENCIA",AW27="",AX27="",WEEKDAY($AW$17,2)>5),"", MAX(0,CHOOSE($C27,$H$3,$H$4)-(AZ27*1440)) ) | BB27: =IF(OR(BD27="VACACIONES",BD27="FALTA",BD27="LICENCIA",AW27="",AX27="",AY27="NO",WEEKDAY($AW$17,2)>5),"",MAX(0,IF(AY27="SI", (AZ27*1440)-CHOOSE($C27,$H$3,$H$4) ))) | BC27: =IF(OR(BD27="VACACIONES",BD27="FALTA",BD27="LICENCIA",AW27="",AX27="",WEEKDAY($AW$17,2)<=5),"",IF(WEEKDAY($AW$17,2)>5,(AZ27*1440))) -> 358 | BD27: TRABAJO SABADO | BI27: =IF(OR(BM27="VACACIONES",BM27="FALTA",BM27="LICENCIA",BF27="",BG27=""),"",IF(WEEKDAY($BF$17,2)>5,BG27-BF27,IF(BH27="NO",MIN(BG27,CHOOSE($C27,$C$3,$C$4))-MAX(BF27,CHOOSE($C27,$B$3,$B$4))-CHOOSE($C27,$F$3,$F$4),BG27-BF27-CHOOSE($C27,$F$3,$F$4)))) | BJ27: =IF(OR(BM27="VACACIONES",BM27="FALTA",BM27="LICENCIA",BF27="",BG27="",WEEKDAY($BF$17,2)>5),"", MAX(0,CHOOSE($C27,$H$3,$H$4)-(BI27*1440)) ) | BK27: =IF(OR(BM27="VACACIONES",BM27="FALTA",BM27="LICENCIA",BF27="",BG27="",BH27="NO",WEEKDAY($BF$17,2)>5),"",MAX(0,IF(BH27="SI", (BI27*1440)-CHOOSE($C27,$H$3,$H$4) ))) | BL27: =IF(OR(BM27="VACACIONES",BM27="FALTA",BM27="LICENCIA",BF27="",BG27="",WEEKDAY($BF$17,2)<=5),"",IF(WEEKDAY($BF$17,2)>5,(BI27*1440))) | BO27: 0.31944444 | BP27: 0.76041667 | BQ27: NO | BR27: =IF(OR(BV27="VACACIONES",BV27="FALTA",BV27="LICENCIA",BO27="",BP27=""),"",IF(WEEKDAY($BO$17,2)>5,BP27-BO27,IF(BQ27="NO",MIN(BP27,CHOOSE($C27,$C$3,$C$4))-MAX(BO27,CHOOSE($C27,$B$3,$B$4))-CHOOSE($C27,$F$3,$F$4),BP27-BO27-CHOOSE($C27,$F$3,$F$4)))) -> 0.38888889 | BS27: =IF(OR(BV27="VACACIONES",BV27="FALTA",BV27="LICENCIA",BO27="",BP27="",WEEKDAY($BO$17,2)>5),"", MAX(0,CHOOSE($C27,$H$3,$H$4)-(BR27*1440)) ) -> 17 | BT27: =IF(OR(BV27="VACACIONES",BV27="FALTA",BV27="LICENCIA",BO27="",BP27="",BQ27="NO",WEEKDAY($BO$17,2)>5),"",MAX(0,IF(BQ27="SI", (BR27*1440)-CHOOSE($C27,$H$3,$H$4) ))) | BU27: =IF(OR(BV27="VACACIONES",BV27="FALTA",BV27="LICENCIA",BO27="",BP27="",WEEKDAY($BO$17,2)<=5),"",IF(WEEKDAY($BO$17,2)>5,(BR27*1440))) | BX27: 0.3125 | BY27: 0.79861111 | BZ27: SI | CA27: =IF(OR(CE27="VACACIONES",CE27="FALTA",CE27="LICENCIA",BX27="",BY27=""),"",IF(WEEKDAY($BX$17,2)>5,BY27-BX27,IF(BZ27="NO",MIN(BY27,CHOOSE($C27,$C$3,$C$4))-MAX(BX27,CHOOSE($C27,$B$3,$B$4))-CHOOSE($C27,$F$3,$F$4),BY27-BX27-CHOOSE($C27,$F$3,$F$4)))) -> 0.44444444 | CB27: =IF(OR(CE27="VACACIONES",CE27="FALTA",CE27="LICENCIA",BX27="",BY27="",WEEKDAY($BX$17,2)>5),"", MAX(0,CHOOSE($C27,$H$3,$H$4)-(CA27*1440)) ) -> 0 | CC27: =IF(OR(CE27="VACACIONES",CE27="FALTA",CE27="LICENCIA",BX27="",BY27="",BZ27="NO",WEEKDAY($BX$17,2)>5),"",MAX(0,IF(BZ27="SI", (CA27*1440)-CHOOSE($C27,$H$3,$H$4) ))) -> 63 | CD27: =IF(OR(CE27="VACACIONES",CE27="FALTA",CE27="LICENCIA",BX27="",BY27="",WEEKDAY($BX$17,2)<=5),"",IF(WEEKDAY($BX$17,2)>5,(CA27*1440))) | CG27: 0.31111111 | CH27: 0.75972222 | CI27: NO | CJ27: =IF(OR(CN27="VACACIONES",CN27="FALTA",CN27="LICENCIA",CG27="",CH27=""),"",IF(WEEKDAY($CG$17,2)>5,CH27-CG27,IF(CI27="NO",MIN(CH27,CHOOSE($C27,$C$3,$C$4))-MAX(CG27,CHOOSE($C27,$B$3,$B$4))-CHOOSE($C27,$F$3,$F$4),CH27-CG27-CHOOSE($C27,$F$3,$F$4)))) -> 0.39722222 | CK27: =IF(OR(CN27="VACACIONES",CN27="FALTA",CN27="LICENCIA",CG27="",CH27="",WEEKDAY($CG$17,2)>5),"", MAX(0,CHOOSE($C27,$H$3,$H$4)-(CJ27*1440)) ) -> 5 | CL27: =IF(OR(CN27="VACACIONES",CN27="FALTA",CN27="LICENCIA",CG27="",CH27="",CI27="NO",WEEKDAY($CG$17,2)>5),"",MAX(0,IF(CI27="SI", (CJ27*1440)-CHOOSE($C27,$H$3,$H$4) ))) | CM27: =IF(OR(CN27="VACACIONES",CN27="FALTA",CN27="LICENCIA",CG27="",CH27="",WEEKDAY($CG$17,2)<=5),"",IF(WEEKDAY($CG$17,2)>5,(CJ27*1440))) | CP27: 0.28263889 | CQ27: 0.75902778 | CR27: NO | CS27: =IF(OR(CW27="VACACIONES",CW27="FALTA",CW27="LICENCIA",CP27="",CQ27=""),"",IF(WEEKDAY($CP$17,2)>5,CQ27-CP27,IF(CR27="NO",MIN(CQ27,CHOOSE($C27,$C$3,$C$4))-MAX(CP27,CHOOSE($C27,$B$3,$B$4))-CHOOSE($C27,$F$3,$F$4),CQ27-CP27-CHOOSE($C27,$F$3,$F$4)))) -> 0.40069444 | CT27: =IF(OR(CW27="VACACIONES",CW27="FALTA",CW27="LICENCIA",CP27="",CQ27="",WEEKDAY($CP$17,2)>5),"", MAX(0,CHOOSE($C27,$H$3,$H$4)-(CS27*1440)) ) -> 0 | CU27: =IF(OR(CW27="VACACIONES",CW27="FALTA",CW27="LICENCIA",CP27="",CQ27="",CR27="NO",WEEKDAY($CP$17,2)>5),"",MAX(0,IF(CR27="SI", (CS27*1440)-CHOOSE($C27,$H$3,$H$4) ))) | CV27: =IF(OR(CW27="VACACIONES",CW27="FALTA",CW27="LICENCIA",CP27="",CQ27="",WEEKDAY($CP$17,2)<=5),"",IF(WEEKDAY($CP$17,2)>5,(CS27*1440))) | CY27: 0.31527778 | CZ27: 0.79861111 | DA27: SI | DB27: =IF(OR(DF27="VACACIONES",DF27="FALTA",DF27="LICENCIA",CY27="",CZ27=""),"",IF(WEEKDAY($CY$17,2)>5,CZ27-CY27,IF(DA27="NO",MIN(CZ27,CHOOSE($C27,$C$3,$C$4))-MAX(CY27,CHOOSE($C27,$B$3,$B$4))-CHOOSE($C27,$F$3,$F$4),CZ27-CY27-CHOOSE($C27,$F$3,$F$4)))) -> 0.44166667 | DC27: =IF(OR(DF27="VACACIONES",DF27="FALTA",DF27="LICENCIA",CY27="",CZ27="",WEEKDAY($CY$17,2)>5),"", MAX(0,CHOOSE($C27,$H$3,$H$4)-(DB27*1440)) ) -> 0 | DD27: =IF(OR(DF27="VACACIONES",DF27="FALTA",DF27="LICENCIA",CY27="",CZ27="",DA27="NO",WEEKDAY($CY$17,2)>5),"",MAX(0,IF(DA27="SI", (DB27*1440)-CHOOSE($C27,$H$3,$H$4) ))) -> 59 | DE27: =IF(OR(DF27="VACACIONES",DF27="FALTA",DF27="LICENCIA",CY27="",CZ27="",WEEKDAY($CY$17,2)<=5),"",IF(WEEKDAY($CY$17,2)>5,(DB27*1440))) | DH27: 0.31111111 | DI27: 0.54930556 | DK27: =IF(OR(DO27="VACACIONES",DO27="FALTA",DO27="LICENCIA",DH27="",DI27=""),"",IF(WEEKDAY($DH$17,2)>5,DI27-DH27,IF(DJ27="NO",MIN(DI27,CHOOSE($C27,$C$3,$C$4))-MAX(DH27,CHOOSE($C27,$B$3,$B$4))-CHOOSE($C27,$F$3,$F$4),DI27-DH27-CHOOSE($C27,$F$3,$F$4)))) -> 0.23819444 | DL27: =IF(OR(DO27="VACACIONES",DO27="FALTA",DO27="LICENCIA",DH27="",DI27="",WEEKDAY($DH$17,2)>5),"", MAX(0,CHOOSE($C27,$H$3,$H$4)-(DK27*1440)) ) | DM27: =IF(OR(DO27="VACACIONES",DO27="FALTA",DO27="LICENCIA",DH27="",DI27="",DJ27="NO",WEEKDAY($DH$17,2)>5),"",MAX(0,IF(DJ27="SI", (DK27*1440)-CHOOSE($C27,$H$3,$H$4) ))) | DN27: =IF(OR(DO27="VACACIONES",DO27="FALTA",DO27="LICENCIA",DH27="",DI27="",WEEKDAY($DH$17,2)<=5),"",IF(WEEKDAY($DH$17,2)>5,(DK27*1440))) -> 343 | DO27: TRABAJO SABADO | DT27: =IF(OR(DX27="VACACIONES",DX27="FALTA",DX27="LICENCIA",DQ27="",DR27=""),"",IF(WEEKDAY($DQ$17,2)>5,DR27-DR27,IF(DS27="NO",MIN(DR27,CHOOSE($C27,$C$3,$C$4))-MAX(DQ27,CHOOSE($C27,$B$3,$B$4))-CHOOSE($C27,$F$3,$F$4),DR27-DQ27-CHOOSE($C27,$F$3,$F$4)))) | DU27: =IF(OR(DX27="VACACIONES",DX27="FALTA",DX27="LICENCIA",DQ27="",DR27="",WEEKDAY($DQ$17,2)>5),"", MAX(0,CHOOSE($C27,$H$3,$H$4)-(DT27*1440)) ) | DV27: =IF(OR(DX27="VACACIONES",DX27="FALTA",DX27="LICENCIA",DQ27="",DR27="",DS27="NO",WEEKDAY($DQ$17,2)>5),"",MAX(0,IF(DS27="SI", (DT27*1440)-CHOOSE($C27,$H$3,$H$4) ))) | DW27: =IF(OR(DX27="VACACIONES",DX27="FALTA",DX27="LICENCIA",DQ27="",DR27="",WEEKDAY($DQ$17,2)<=5),"",IF(WEEKDAY($DQ$17,2)>5,(DT27*1440))) | DZ27: 0.31388889 | EA27: 0.79861111 | EB27: SI | EC27: =IF(OR(EG27="VACACIONES",EG27="FALTA",EG27="LICENCIA",DZ27="",EA27=""),"",IF(WEEKDAY($CY$17,2)>5,EA27-DZ27,IF(EB27="NO",MIN(EA27,CHOOSE($C27,$C$3,$C$4))-MAX(DZ27,CHOOSE($C27,$B$3,$B$4))-CHOOSE($C27,$F$3,$F$4),EA27-DZ27-CHOOSE($C27,$F$3,$F$4)))) -> 0.44305556 | ED27: =IF(OR(EG27="VACACIONES",EG27="FALTA",EG27="LICENCIA",DZ27="",EA27="",WEEKDAY($CY$17,2)>5),"", MAX(0,CHOOSE($C27,$H$3,$H$4)-(EC27*1440)) ) -> 0 | EE27: =IF(OR(EG27="VACACIONES",EG27="FALTA",EG27="LICENCIA",DZ27="",EA27="",EB27="NO",WEEKDAY($CY$17,2)>5),"",MAX(0,IF(EB27="SI", (EC27*1440)-CHOOSE($C27,$H$3,$H$4) ))) -> 61 | EF27: =IF(OR(EG27="VACACIONES",EG27="FALTA",EG27="LICENCIA",DZ27="",EA27="",WEEKDAY($CY$17,2)<=5),"",IF(WEEKDAY($CY$17,2)>5,(EC27*1440))) | EK27: =SUM(H27,Q27,Z27,AI27,AR27,BA27,BJ27,BS27,CB27,CK27,CT27,DC27,DL27,DU27,ED27) -> 22 | EL27: =SUM(I27,J27,R27,S27,AA27,AB27,AJ27,AK27,AS27,AT27,BB27,BC27,BK27,BL27,BT27,BU27,CC27,CD27,CL27,CM27,CU27,CV27,DD27,DE27,DM27,DN27,DV27,DW27,EE27,EF27) -> 1099 | EM27: =COUNTIF(I27,">0")+COUNTIF(J27,">0")+COUNTIF(R27,">0")+COUNTIF(S27,">0")++COUNTIF(AA27,">0")+COUNTIF(AB27,">0")+COUNTIF(AJ27,">0")+COUNTIF(AK27,">0")+COUNTIF(AS27,">0")+COUNTIF(AT27,">0")+COUNTIF(BB27,">0")+COUNTIF(BC27,">0")+COUNTIF(BK27,">0")+COUNTIF(BL27,">0")+COUNTIF(BT27,">0")+COUNTIF(BU27,">0")+COUNTIF(CC27,">0")+COUNTIF(CD27,">0")+COUNTIF(CL27,">0")+COUNTIF(CM27,">0")+COUNTIF(CU27,">0")+COUNTIF(CV27,">0")+COUNTIF(DD27,">0")+COUNTIF(DE27,">0")+COUNTIF(DM27,">0")+COUNTIF(DN27,">0")+COUNTIF(DV27,">0")+COUNTIF(DW27,">0")+COUNTIF(EE27,">0")+COUNTIF(EF27,">0") -> 10 | EN27: =COUNTIF(D27:EG27,"FALTA") -> 0 | EO27: =15-EN27 -> 15 | EP27: =COUNTIF(D27:EG27,"TRABAJO SABADO") -> 2 | EQ27: =COUNTIF(D27:EG27,"TRABAJO DOMINGO")+COUNTIF(D27:EG27,"TRABAJO FERIADO")+(COUNTIF(D27:EG27,"TRABAJO 1RO MAYO")*2)+((COUNTIF(D29:EG29,"TRABAJO 1RO MAYO EN SU DIA LIBRE")*2)*2) -> 0 | ER27: =COUNTIF(D27:EG27,"VACACIONES") -> 0 | ES27: =COUNTIF(D27:EG27,"LICENCIA") -> 0
A28: =A27+1 -> #VALUE! | B28: ='1RA QUINCENA JUNIO 26'!B19 -> PEÑALOZA CAMPOS, FRANK KEVHIN | C28: 1 | D28: 0.30763889 | E28: 0.77430556 | F28: NO | G28: =IF(OR(K28="VACACIONES",K28="FALTA",K28="LICENCIA",D28="",E28=""),"",IF(WEEKDAY($D$17,2)>5,E28-D28,IF(F28="NO",MIN(E28,CHOOSE($C28,$C$3,$C$4))-MAX(D28,CHOOSE($C28,$B$3,$B$4))-CHOOSE($C28,$F$3,$F$4),E28-D28-CHOOSE($C28,$F$3,$F$4)))) -> 0.40069444 | H28: =IF(OR(K28="VACACIONES",K28="FALTA",K28="LICENCIA",D28="",E28="",WEEKDAY($D$17,2)>5),"", MAX(0,CHOOSE($C28,$H$3,$H$4)-(G28*1440)) ) -> 0 | I28: =IF(OR(K28="VACACIONES",K28="FALTA",K28="LICENCIA",D28="",E28="",F28="NO",WEEKDAY($D$17,2)>5),"",MAX(0,IF(F28="SI", (G28*1440)-CHOOSE($C28,$H$3,$H$4) ))) | J28: =IF(OR(K28="VACACIONES",K28="FALTA",K28="LICENCIA",D28="",E28="",WEEKDAY($D$17,2)<=5),"",IF(WEEKDAY($D$17,2)>5,(G28*1440))) | M28: 0.30763889 | N28: 0.76944444 | O28: NO | P28: =IF(OR(T28="VACACIONES",T28="FALTA",T28="LICENCIA",M28="",N28=""),"",IF(WEEKDAY($M$17,2)>5,N28-M28,IF(O28="NO",MIN(N28,CHOOSE($C28,$C$3,$C$4))-MAX(M28,CHOOSE($C28,$B$3,$B$4))-CHOOSE($C28,$F$3,$F$4),N28-M28-CHOOSE($C28,$F$3,$F$4)))) -> 0.40069444 | Q28: =IF(OR(T28="VACACIONES",T28="FALTA",T28="LICENCIA",M28="",N28="",WEEKDAY($M$17,2)>5),"", MAX(0,CHOOSE($C28,$H$3,$H$4)-(P28*1440)) ) -> 0 | R28: =IF(OR(T28="VACACIONES",T28="FALTA",T28="LICENCIA",M28="",N28="",O28="NO",WEEKDAY($M$17,2)>5),"",MAX(0,IF(O28="SI", (P28*1440)-CHOOSE($C28,$H$3,$H$4) ))) | S28: =IF(OR(T28="VACACIONES",T28="FALTA",T28="LICENCIA",M28="",N28="",WEEKDAY($M$17,2)<=5),"",IF(WEEKDAY($M$17,2)>5,(P28*1440))) | V28: 0.30763889 | W28: 0.77361111 | X28: NO | Y28: =IF(OR(AC28="VACACIONES",AC28="FALTA",AC28="LICENCIA",V28="",W28=""),"",IF(WEEKDAY($V$17,2)>5,W28-V28,IF(X28="NO",MIN(W28,CHOOSE($C28,$C$3,$C$4))-MAX(V28,CHOOSE($C28,$B$3,$B$4))-CHOOSE($C28,$F$3,$F$4),W28-V28-CHOOSE($C28,$F$3,$F$4)))) -> 0.40069444 | Z28: =IF(OR(AC28="VACACIONES",AC28="FALTA",AC28="LICENCIA",V28="",W28="",WEEKDAY($V$17,2)>5),"", MAX(0,CHOOSE($C28,$H$3,$H$4)-(Y28*1440)) ) -> 0 | AA28: =IF(OR(AC28="VACACIONES",AC28="FALTA",AC28="LICENCIA",V28="",W28="",X28="NO",WEEKDAY($V$17,2)>5),"",MAX(0,IF(X28="SI", (Y28*1440)-CHOOSE($C28,$H$3,$H$4) ))) | AB28: =IF(OR(AC28="VACACIONES",AC28="FALTA",AC28="LICENCIA",V28="",W28="",WEEKDAY($V$17,2)<=5),"",IF(WEEKDAY($V$17,2)>5,(Y28*1440))) | AE28: 0.30763889 | AF28: 0.76875 | AG28: NO | AH28: =IF(OR(AL28="VACACIONES",AL28="FALTA",AL28="LICENCIA",AE28="",AF28=""),"",IF(WEEKDAY($AE$17,2)>5,AF28-AE28,IF(AG28="NO",MIN(AF28,CHOOSE($C28,$C$3,$C$4))-MAX(AE28,CHOOSE($C28,$B$3,$B$4))-CHOOSE($C28,$F$3,$F$4),AF28-AE28-CHOOSE($C28,$F$3,$F$4)))) -> 0.40069444 | AI28: =IF(OR(AL28="VACACIONES",AL28="FALTA",AL28="LICENCIA",AE28="",AF28="",WEEKDAY($AE$17,2)>5),"", MAX(0,CHOOSE($C28,$H$3,$H$4)-(AH28*1440)) ) -> 0 | AJ28: =IF(OR(AL28="VACACIONES",AL28="FALTA",AL28="LICENCIA",AE28="",AF28="",AG28="NO",WEEKDAY($AE$17,2)>5),"",MAX(0,IF(AG28="SI", (AH28*1440)-CHOOSE($C28,$H$3,$H$4) ))) | AK28: =IF(OR(AL28="VACACIONES",AL28="FALTA",AL28="LICENCIA",AE28="",AF28="",WEEKDAY($AE$17,2)<=5),"",IF(WEEKDAY($AE$17,2)>5,(AH28*1440))) | AN28: 0.30763889 | AO28: 0.77083333 | AP28: NO | AQ28: =IF(OR(AU28="VACACIONES",AU28="FALTA",AU28="LICENCIA",AN28="",AO28=""),"",IF(WEEKDAY($AN$17,2)>5,AO28-AN28,IF(AP28="NO",MIN(AO28,CHOOSE($C28,$C$3,$C$4))-MAX(AN28,CHOOSE($C28,$B$3,$B$4))-CHOOSE($C28,$F$3,$F$4),AO28-AN28-CHOOSE($C28,$F$3,$F$4)))) -> 0.40069444 | AR28: =IF(OR(AU28="VACACIONES",AU28="FALTA",AU28="LICENCIA",AN28="",AO28="",WEEKDAY($AN$17,2)>5),"", MAX(0,CHOOSE($C28,$H$3,$H$4)-(AQ28*1440)) ) -> 0 | AS28: =IF(OR(AU28="VACACIONES",AU28="FALTA",AU28="LICENCIA",AN28="",AO28="",AP28="NO",WEEKDAY($AN$17,2)>5),"",MAX(0,IF(AP28="SI", (AQ28*1440)-CHOOSE($C28,$H$3,$H$4) ))) | AT28: =IF(OR(AU28="VACACIONES",AU28="FALTA",AU28="LICENCIA",AN28="",AO28="",WEEKDAY($AN$17,2)<=5),"",IF(WEEKDAY($AN$17,2)>5,(AQ28*1440))) | AW28: 0.27847222 | AX28: 0.56041667 | AZ28: =IF(OR(BD28="VACACIONES",BD28="FALTA",BD28="LICENCIA",AW28="",AX28=""),"",IF(WEEKDAY($AW$17,2)>5,AX28-AW28,IF(AY28="NO",MIN(AX28,CHOOSE($C28,$C$3,$C$4))-MAX(AW28,CHOOSE($C28,$B$3,$B$4))-CHOOSE($C28,$F$3,$F$4),AX28-AW28-CHOOSE($C28,$F$3,$F$4)))) -> 0.28194444 | BA28: =IF(OR(BD28="VACACIONES",BD28="FALTA",BD28="LICENCIA",AW28="",AX28="",WEEKDAY($AW$17,2)>5),"", MAX(0,CHOOSE($C28,$H$3,$H$4)-(AZ28*1440)) ) | BB28: =IF(OR(BD28="VACACIONES",BD28="FALTA",BD28="LICENCIA",AW28="",AX28="",AY28="NO",WEEKDAY($AW$17,2)>5),"",MAX(0,IF(AY28="SI", (AZ28*1440)-CHOOSE($C28,$H$3,$H$4) ))) | BC28: =IF(OR(BD28="VACACIONES",BD28="FALTA",BD28="LICENCIA",AW28="",AX28="",WEEKDAY($AW$17,2)<=5),"",IF(WEEKDAY($AW$17,2)>5,(AZ28*1440))) -> 406 | BD28: TRABAJO SABADO | BI28: =IF(OR(BM28="VACACIONES",BM28="FALTA",BM28="LICENCIA",BF28="",BG28=""),"",IF(WEEKDAY($BF$17,2)>5,BG28-BF28,IF(BH28="NO",MIN(BG28,CHOOSE($C28,$C$3,$C$4))-MAX(BF28,CHOOSE($C28,$B$3,$B$4))-CHOOSE($C28,$F$3,$F$4),BG28-BF28-CHOOSE($C28,$F$3,$F$4)))) | BJ28: =IF(OR(BM28="VACACIONES",BM28="FALTA",BM28="LICENCIA",BF28="",BG28="",WEEKDAY($BF$17,2)>5),"", MAX(0,CHOOSE($C28,$H$3,$H$4)-(BI28*1440)) ) | BK28: =IF(OR(BM28="VACACIONES",BM28="FALTA",BM28="LICENCIA",BF28="",BG28="",BH28="NO",WEEKDAY($BF$17,2)>5),"",MAX(0,IF(BH28="SI", (BI28*1440)-CHOOSE($C28,$H$3,$H$4) ))) | BL28: =IF(OR(BM28="VACACIONES",BM28="FALTA",BM28="LICENCIA",BF28="",BG28="",WEEKDAY($BF$17,2)<=5),"",IF(WEEKDAY($BF$17,2)>5,(BI28*1440))) | BO28: 0.30763889 | BP28: 0.77291667 | BQ28: NO | BR28: =IF(OR(BV28="VACACIONES",BV28="FALTA",BV28="LICENCIA",BO28="",BP28=""),"",IF(WEEKDAY($BO$17,2)>5,BP28-BO28,IF(BQ28="NO",MIN(BP28,CHOOSE($C28,$C$3,$C$4))-MAX(BO28,CHOOSE($C28,$B$3,$B$4))-CHOOSE($C28,$F$3,$F$4),BP28-BO28-CHOOSE($C28,$F$3,$F$4)))) -> 0.40069444 | BS28: =IF(OR(BV28="VACACIONES",BV28="FALTA",BV28="LICENCIA",BO28="",BP28="",WEEKDAY($BO$17,2)>5),"", MAX(0,CHOOSE($C28,$H$3,$H$4)-(BR28*1440)) ) -> 0 | BT28: =IF(OR(BV28="VACACIONES",BV28="FALTA",BV28="LICENCIA",BO28="",BP28="",BQ28="NO",WEEKDAY($BO$17,2)>5),"",MAX(0,IF(BQ28="SI", (BR28*1440)-CHOOSE($C28,$H$3,$H$4) ))) | BU28: =IF(OR(BV28="VACACIONES",BV28="FALTA",BV28="LICENCIA",BO28="",BP28="",WEEKDAY($BO$17,2)<=5),"",IF(WEEKDAY($BO$17,2)>5,(BR28*1440))) | BX28: 0.30763889 | BY28: 0.79861111 | BZ28: SI | CA28: =IF(OR(CE28="VACACIONES",CE28="FALTA",CE28="LICENCIA",BX28="",BY28=""),"",IF(WEEKDAY($BX$17,2)>5,BY28-BX28,IF(BZ28="NO",MIN(BY28,CHOOSE($C28,$C$3,$C$4))-MAX(BX28,CHOOSE($C28,$B$3,$B$4))-CHOOSE($C28,$F$3,$F$4),BY28-BX28-CHOOSE($C28,$F$3,$F$4)))) -> 0.44930556 | CB28: =IF(OR(CE28="VACACIONES",CE28="FALTA",CE28="LICENCIA",BX28="",BY28="",WEEKDAY($BX$17,2)>5),"", MAX(0,CHOOSE($C28,$H$3,$H$4)-(CA28*1440)) ) -> 0 | CC28: =IF(OR(CE28="VACACIONES",CE28="FALTA",CE28="LICENCIA",BX28="",BY28="",BZ28="NO",WEEKDAY($BX$17,2)>5),"",MAX(0,IF(BZ28="SI", (CA28*1440)-CHOOSE($C28,$H$3,$H$4) ))) -> 70 | CD28: =IF(OR(CE28="VACACIONES",CE28="FALTA",CE28="LICENCIA",BX28="",BY28="",WEEKDAY($BX$17,2)<=5),"",IF(WEEKDAY($BX$17,2)>5,(CA28*1440))) | CG28: 0.27777778 | CH28: 0.77847222 | CI28: NO | CJ28: =IF(OR(CN28="VACACIONES",CN28="FALTA",CN28="LICENCIA",CG28="",CH28=""),"",IF(WEEKDAY($CG$17,2)>5,CH28-CG28,IF(CI28="NO",MIN(CH28,CHOOSE($C28,$C$3,$C$4))-MAX(CG28,CHOOSE($C28,$B$3,$B$4))-CHOOSE($C28,$F$3,$F$4),CH28-CG28-CHOOSE($C28,$F$3,$F$4)))) -> 0.40069444 | CK28: =IF(OR(CN28="VACACIONES",CN28="FALTA",CN28="LICENCIA",CG28="",CH28="",WEEKDAY($CG$17,2)>5),"", MAX(0,CHOOSE($C28,$H$3,$H$4)-(CJ28*1440)) ) -> 0 | CL28: =IF(OR(CN28="VACACIONES",CN28="FALTA",CN28="LICENCIA",CG28="",CH28="",CI28="NO",WEEKDAY($CG$17,2)>5),"",MAX(0,IF(CI28="SI", (CJ28*1440)-CHOOSE($C28,$H$3,$H$4) ))) | CM28: =IF(OR(CN28="VACACIONES",CN28="FALTA",CN28="LICENCIA",CG28="",CH28="",WEEKDAY($CG$17,2)<=5),"",IF(WEEKDAY($CG$17,2)>5,(CJ28*1440))) | CP28: 0.30416667 | CQ28: 0.75347222 | CR28: NO | CS28: =IF(OR(CW28="VACACIONES",CW28="FALTA",CW28="LICENCIA",CP28="",CQ28=""),"",IF(WEEKDAY($CP$17,2)>5,CQ28-CP28,IF(CR28="NO",MIN(CQ28,CHOOSE($C28,$C$3,$C$4))-MAX(CP28,CHOOSE($C28,$B$3,$B$4))-CHOOSE($C28,$F$3,$F$4),CQ28-CP28-CHOOSE($C28,$F$3,$F$4)))) -> 0.40069444 | CT28: =IF(OR(CW28="VACACIONES",CW28="FALTA",CW28="LICENCIA",CP28="",CQ28="",WEEKDAY($CP$17,2)>5),"", MAX(0,CHOOSE($C28,$H$3,$H$4)-(CS28*1440)) ) -> 0 | CU28: =IF(OR(CW28="VACACIONES",CW28="FALTA",CW28="LICENCIA",CP28="",CQ28="",CR28="NO",WEEKDAY($CP$17,2)>5),"",MAX(0,IF(CR28="SI", (CS28*1440)-CHOOSE($C28,$H$3,$H$4) ))) | CV28: =IF(OR(CW28="VACACIONES",CW28="FALTA",CW28="LICENCIA",CP28="",CQ28="",WEEKDAY($CP$17,2)<=5),"",IF(WEEKDAY($CP$17,2)>5,(CS28*1440))) | CY28: 0.27638889 | CZ28: 0.78472222 | DA28: NO | DB28: =IF(OR(DF28="VACACIONES",DF28="FALTA",DF28="LICENCIA",CY28="",CZ28=""),"",IF(WEEKDAY($CY$17,2)>5,CZ28-CY28,IF(DA28="NO",MIN(CZ28,CHOOSE($C28,$C$3,$C$4))-MAX(CY28,CHOOSE($C28,$B$3,$B$4))-CHOOSE($C28,$F$3,$F$4),CZ28-CY28-CHOOSE($C28,$F$3,$F$4)))) -> 0.40069444 | DC28: =IF(OR(DF28="VACACIONES",DF28="FALTA",DF28="LICENCIA",CY28="",CZ28="",WEEKDAY($CY$17,2)>5),"", MAX(0,CHOOSE($C28,$H$3,$H$4)-(DB28*1440)) ) -> 0 | DD28: =IF(OR(DF28="VACACIONES",DF28="FALTA",DF28="LICENCIA",CY28="",CZ28="",DA28="NO",WEEKDAY($CY$17,2)>5),"",MAX(0,IF(DA28="SI", (DB28*1440)-CHOOSE($C28,$H$3,$H$4) ))) | DE28: =IF(OR(DF28="VACACIONES",DF28="FALTA",DF28="LICENCIA",CY28="",CZ28="",WEEKDAY($CY$17,2)<=5),"",IF(WEEKDAY($CY$17,2)>5,(DB28*1440))) | DH28: 0.28125 | DI28: 0.55625 | DK28: =IF(OR(DO28="VACACIONES",DO28="FALTA",DO28="LICENCIA",DH28="",DI28=""),"",IF(WEEKDAY($DH$17,2)>5,DI28-DH28,IF(DJ28="NO",MIN(DI28,CHOOSE($C28,$C$3,$C$4))-MAX(DH28,CHOOSE($C28,$B$3,$B$4))-CHOOSE($C28,$F$3,$F$4),DI28-DH28-CHOOSE($C28,$F$3,$F$4)))) -> 0.275 | DL28: =IF(OR(DO28="VACACIONES",DO28="FALTA",DO28="LICENCIA",DH28="",DI28="",WEEKDAY($DH$17,2)>5),"", MAX(0,CHOOSE($C28,$H$3,$H$4)-(DK28*1440)) ) | DM28: =IF(OR(DO28="VACACIONES",DO28="FALTA",DO28="LICENCIA",DH28="",DI28="",DJ28="NO",WEEKDAY($DH$17,2)>5),"",MAX(0,IF(DJ28="SI", (DK28*1440)-CHOOSE($C28,$H$3,$H$4) ))) | DN28: =IF(OR(DO28="VACACIONES",DO28="FALTA",DO28="LICENCIA",DH28="",DI28="",WEEKDAY($DH$17,2)<=5),"",IF(WEEKDAY($DH$17,2)>5,(DK28*1440))) -> 396 | DO28: TRABAJO SABADO | DT28: =IF(OR(DX28="VACACIONES",DX28="FALTA",DX28="LICENCIA",DQ28="",DR28=""),"",IF(WEEKDAY($DQ$17,2)>5,DR28-DR28,IF(DS28="NO",MIN(DR28,CHOOSE($C28,$C$3,$C$4))-MAX(DQ28,CHOOSE($C28,$B$3,$B$4))-CHOOSE($C28,$F$3,$F$4),DR28-DQ28-CHOOSE($C28,$F$3,$F$4)))) | DU28: =IF(OR(DX28="VACACIONES",DX28="FALTA",DX28="LICENCIA",DQ28="",DR28="",WEEKDAY($DQ$17,2)>5),"", MAX(0,CHOOSE($C28,$H$3,$H$4)-(DT28*1440)) ) | DV28: =IF(OR(DX28="VACACIONES",DX28="FALTA",DX28="LICENCIA",DQ28="",DR28="",DS28="NO",WEEKDAY($DQ$17,2)>5),"",MAX(0,IF(DS28="SI", (DT28*1440)-CHOOSE($C28,$H$3,$H$4) ))) | DW28: =IF(OR(DX28="VACACIONES",DX28="FALTA",DX28="LICENCIA",DQ28="",DR28="",WEEKDAY($DQ$17,2)<=5),"",IF(WEEKDAY($DQ$17,2)>5,(DT28*1440))) | DZ28: 0.27986111 | EA28: 0.77361111 | EB28: NO | EC28: =IF(OR(EG28="VACACIONES",EG28="FALTA",EG28="LICENCIA",DZ28="",EA28=""),"",IF(WEEKDAY($CY$17,2)>5,EA28-DZ28,IF(EB28="NO",MIN(EA28,CHOOSE($C28,$C$3,$C$4))-MAX(DZ28,CHOOSE($C28,$B$3,$B$4))-CHOOSE($C28,$F$3,$F$4),EA28-DZ28-CHOOSE($C28,$F$3,$F$4)))) -> 0.40069444 | ED28: =IF(OR(EG28="VACACIONES",EG28="FALTA",EG28="LICENCIA",DZ28="",EA28="",WEEKDAY($CY$17,2)>5),"", MAX(0,CHOOSE($C28,$H$3,$H$4)-(EC28*1440)) ) -> 0 | EE28: =IF(OR(EG28="VACACIONES",EG28="FALTA",EG28="LICENCIA",DZ28="",EA28="",EB28="NO",WEEKDAY($CY$17,2)>5),"",MAX(0,IF(EB28="SI", (EC28*1440)-CHOOSE($C28,$H$3,$H$4) ))) | EF28: =IF(OR(EG28="VACACIONES",EG28="FALTA",EG28="LICENCIA",DZ28="",EA28="",WEEKDAY($CY$17,2)<=5),"",IF(WEEKDAY($CY$17,2)>5,(EC28*1440))) | EK28: =SUM(H28,Q28,Z28,AI28,AR28,BA28,BJ28,BS28,CB28,CK28,CT28,DC28,DL28,DU28,ED28) -> 0 | EL28: =SUM(I28,J28,R28,S28,AA28,AB28,AJ28,AK28,AS28,AT28,BB28,BC28,BK28,BL28,BT28,BU28,CC28,CD28,CL28,CM28,CU28,CV28,DD28,DE28,DM28,DN28,DV28,DW28,EE28,EF28) -> 872 | EM28: =COUNTIF(I28,">0")+COUNTIF(J28,">0")+COUNTIF(R28,">0")+COUNTIF(S28,">0")++COUNTIF(AA28,">0")+COUNTIF(AB28,">0")+COUNTIF(AJ28,">0")+COUNTIF(AK28,">0")+COUNTIF(AS28,">0")+COUNTIF(AT28,">0")+COUNTIF(BB28,">0")+COUNTIF(BC28,">0")+COUNTIF(BK28,">0")+COUNTIF(BL28,">0")+COUNTIF(BT28,">0")+COUNTIF(BU28,">0")+COUNTIF(CC28,">0")+COUNTIF(CD28,">0")+COUNTIF(CL28,">0")+COUNTIF(CM28,">0")+COUNTIF(CU28,">0")+COUNTIF(CV28,">0")+COUNTIF(DD28,">0")+COUNTIF(DE28,">0")+COUNTIF(DM28,">0")+COUNTIF(DN28,">0")+COUNTIF(DV28,">0")+COUNTIF(DW28,">0")+COUNTIF(EE28,">0")+COUNTIF(EF28,">0") -> 3 | EN28: =COUNTIF(D28:EG28,"FALTA") -> 0 | EO28: =15-EN28 -> 15 | EP28: =COUNTIF(D28:EG28,"TRABAJO SABADO") -> 2 | EQ28: =COUNTIF(D28:EG28,"TRABAJO DOMINGO")+COUNTIF(D28:EG28,"TRABAJO FERIADO")+(COUNTIF(D28:EG28,"TRABAJO 1RO MAYO")*2)+((COUNTIF(D30:EG30,"TRABAJO 1RO MAYO EN SU DIA LIBRE")*2)*2) -> 0 | ER28: =COUNTIF(D28:EG28,"VACACIONES") -> 0 | ES28: =COUNTIF(D28:EG28,"LICENCIA") -> 0
A29: =A28+1 -> #VALUE! | B29: ='1RA QUINCENA JUNIO 26'!B20 -> SANCHEZ MUEDAS FIDEL | C29: 1 | D29: 0.30763889 | E29: 0.77430556 | F29: NO | G29: =IF(OR(K29="VACACIONES",K29="FALTA",K29="LICENCIA",D29="",E29=""),"",IF(WEEKDAY($D$17,2)>5,E29-D29,IF(F29="NO",MIN(E29,CHOOSE($C29,$C$3,$C$4))-MAX(D29,CHOOSE($C29,$B$3,$B$4))-CHOOSE($C29,$F$3,$F$4),E29-D29-CHOOSE($C29,$F$3,$F$4)))) -> 0.40069444 | H29: =IF(OR(K29="VACACIONES",K29="FALTA",K29="LICENCIA",D29="",E29="",WEEKDAY($D$17,2)>5),"", MAX(0,CHOOSE($C29,$H$3,$H$4)-(G29*1440)) ) -> 0 | I29: =IF(OR(K29="VACACIONES",K29="FALTA",K29="LICENCIA",D29="",E29="",F29="NO",WEEKDAY($D$17,2)>5),"",MAX(0,IF(F29="SI", (G29*1440)-CHOOSE($C29,$H$3,$H$4) ))) | J29: =IF(OR(K29="VACACIONES",K29="FALTA",K29="LICENCIA",D29="",E29="",WEEKDAY($D$17,2)<=5),"",IF(WEEKDAY($D$17,2)>5,(G29*1440))) | M29: 0.30763889 | N29: 0.75694444 | O29: NO | P29: =IF(OR(T29="VACACIONES",T29="FALTA",T29="LICENCIA",M29="",N29=""),"",IF(WEEKDAY($M$17,2)>5,N29-M29,IF(O29="NO",MIN(N29,CHOOSE($C29,$C$3,$C$4))-MAX(M29,CHOOSE($C29,$B$3,$B$4))-CHOOSE($C29,$F$3,$F$4),N29-M29-CHOOSE($C29,$F$3,$F$4)))) -> 0.40069444 | Q29: =IF(OR(T29="VACACIONES",T29="FALTA",T29="LICENCIA",M29="",N29="",WEEKDAY($M$17,2)>5),"", MAX(0,CHOOSE($C29,$H$3,$H$4)-(P29*1440)) ) -> 0 | R29: =IF(OR(T29="VACACIONES",T29="FALTA",T29="LICENCIA",M29="",N29="",O29="NO",WEEKDAY($M$17,2)>5),"",MAX(0,IF(O29="SI", (P29*1440)-CHOOSE($C29,$H$3,$H$4) ))) | S29: =IF(OR(T29="VACACIONES",T29="FALTA",T29="LICENCIA",M29="",N29="",WEEKDAY($M$17,2)<=5),"",IF(WEEKDAY($M$17,2)>5,(P29*1440))) | V29: 0.30763889 | W29: 0.75763889 | X29: NO | Y29: =IF(OR(AC29="VACACIONES",AC29="FALTA",AC29="LICENCIA",V29="",W29=""),"",IF(WEEKDAY($V$17,2)>5,W29-V29,IF(X29="NO",MIN(W29,CHOOSE($C29,$C$3,$C$4))-MAX(V29,CHOOSE($C29,$B$3,$B$4))-CHOOSE($C29,$F$3,$F$4),W29-V29-CHOOSE($C29,$F$3,$F$4)))) -> 0.40069444 | Z29: =IF(OR(AC29="VACACIONES",AC29="FALTA",AC29="LICENCIA",V29="",W29="",WEEKDAY($V$17,2)>5),"", MAX(0,CHOOSE($C29,$H$3,$H$4)-(Y29*1440)) ) -> 0 | AA29: =IF(OR(AC29="VACACIONES",AC29="FALTA",AC29="LICENCIA",V29="",W29="",X29="NO",WEEKDAY($V$17,2)>5),"",MAX(0,IF(X29="SI", (Y29*1440)-CHOOSE($C29,$H$3,$H$4) ))) | AB29: =IF(OR(AC29="VACACIONES",AC29="FALTA",AC29="LICENCIA",V29="",W29="",WEEKDAY($V$17,2)<=5),"",IF(WEEKDAY($V$17,2)>5,(Y29*1440))) | AE29: 0.30763889 | AF29: 0.79861111 | AG29: SI | AH29: =IF(OR(AL29="VACACIONES",AL29="FALTA",AL29="LICENCIA",AE29="",AF29=""),"",IF(WEEKDAY($AE$17,2)>5,AF29-AE29,IF(AG29="NO",MIN(AF29,CHOOSE($C29,$C$3,$C$4))-MAX(AE29,CHOOSE($C29,$B$3,$B$4))-CHOOSE($C29,$F$3,$F$4),AF29-AE29-CHOOSE($C29,$F$3,$F$4)))) -> 0.44930556 | AI29: =IF(OR(AL29="VACACIONES",AL29="FALTA",AL29="LICENCIA",AE29="",AF29="",WEEKDAY($AE$17,2)>5),"", MAX(0,CHOOSE($C29,$H$3,$H$4)-(AH29*1440)) ) -> 0 | AJ29: =IF(OR(AL29="VACACIONES",AL29="FALTA",AL29="LICENCIA",AE29="",AF29="",AG29="NO",WEEKDAY($AE$17,2)>5),"",MAX(0,IF(AG29="SI", (AH29*1440)-CHOOSE($C29,$H$3,$H$4) ))) -> 70 | AK29: =IF(OR(AL29="VACACIONES",AL29="FALTA",AL29="LICENCIA",AE29="",AF29="",WEEKDAY($AE$17,2)<=5),"",IF(WEEKDAY($AE$17,2)>5,(AH29*1440))) | AN29: 0.30763889 | AO29: 0.74375 | AP29: NO | AQ29: =IF(OR(AU29="VACACIONES",AU29="FALTA",AU29="LICENCIA",AN29="",AO29=""),"",IF(WEEKDAY($AN$17,2)>5,AO29-AN29,IF(AP29="NO",MIN(AO29,CHOOSE($C29,$C$3,$C$4))-MAX(AN29,CHOOSE($C29,$B$3,$B$4))-CHOOSE($C29,$F$3,$F$4),AO29-AN29-CHOOSE($C29,$F$3,$F$4)))) -> 0.39444444 | AR29: =IF(OR(AU29="VACACIONES",AU29="FALTA",AU29="LICENCIA",AN29="",AO29="",WEEKDAY($AN$17,2)>5),"", MAX(0,CHOOSE($C29,$H$3,$H$4)-(AQ29*1440)) ) -> 9 | AS29: =IF(OR(AU29="VACACIONES",AU29="FALTA",AU29="LICENCIA",AN29="",AO29="",AP29="NO",WEEKDAY($AN$17,2)>5),"",MAX(0,IF(AP29="SI", (AQ29*1440)-CHOOSE($C29,$H$3,$H$4) ))) | AT29: =IF(OR(AU29="VACACIONES",AU29="FALTA",AU29="LICENCIA",AN29="",AO29="",WEEKDAY($AN$17,2)<=5),"",IF(WEEKDAY($AN$17,2)>5,(AQ29*1440))) | AZ29: =IF(OR(BD29="VACACIONES",BD29="FALTA",BD29="LICENCIA",AW29="",AX29=""),"",IF(WEEKDAY($AW$17,2)>5,AX29-AW29,IF(AY29="NO",MIN(AX29,CHOOSE($C29,$C$3,$C$4))-MAX(AW29,CHOOSE($C29,$B$3,$B$4))-CHOOSE($C29,$F$3,$F$4),AX29-AW29-CHOOSE($C29,$F$3,$F$4)))) | BA29: =IF(OR(BD29="VACACIONES",BD29="FALTA",BD29="LICENCIA",AW29="",AX29="",WEEKDAY($AW$17,2)>5),"", MAX(0,CHOOSE($C29,$H$3,$H$4)-(AZ29*1440)) ) | BB29: =IF(OR(BD29="VACACIONES",BD29="FALTA",BD29="LICENCIA",AW29="",AX29="",AY29="NO",WEEKDAY($AW$17,2)>5),"",MAX(0,IF(AY29="SI", (AZ29*1440)-CHOOSE($C29,$H$3,$H$4) ))) | BC29: =IF(OR(BD29="VACACIONES",BD29="FALTA",BD29="LICENCIA",AW29="",AX29="",WEEKDAY($AW$17,2)<=5),"",IF(WEEKDAY($AW$17,2)>5,(AZ29*1440))) | BI29: =IF(OR(BM29="VACACIONES",BM29="FALTA",BM29="LICENCIA",BF29="",BG29=""),"",IF(WEEKDAY($BF$17,2)>5,BG29-BF29,IF(BH29="NO",MIN(BG29,CHOOSE($C29,$C$3,$C$4))-MAX(BF29,CHOOSE($C29,$B$3,$B$4))-CHOOSE($C29,$F$3,$F$4),BG29-BF29-CHOOSE($C29,$F$3,$F$4)))) | BJ29: =IF(OR(BM29="VACACIONES",BM29="FALTA",BM29="LICENCIA",BF29="",BG29="",WEEKDAY($BF$17,2)>5),"", MAX(0,CHOOSE($C29,$H$3,$H$4)-(BI29*1440)) ) | BK29: =IF(OR(BM29="VACACIONES",BM29="FALTA",BM29="LICENCIA",BF29="",BG29="",BH29="NO",WEEKDAY($BF$17,2)>5),"",MAX(0,IF(BH29="SI", (BI29*1440)-CHOOSE($C29,$H$3,$H$4) ))) | BL29: =IF(OR(BM29="VACACIONES",BM29="FALTA",BM29="LICENCIA",BF29="",BG29="",WEEKDAY($BF$17,2)<=5),"",IF(WEEKDAY($BF$17,2)>5,(BI29*1440))) | BO29: 0.30763889 | BP29: 0.75347222 | BQ29: NO | BR29: =IF(OR(BV29="VACACIONES",BV29="FALTA",BV29="LICENCIA",BO29="",BP29=""),"",IF(WEEKDAY($BO$17,2)>5,BP29-BO29,IF(BQ29="NO",MIN(BP29,CHOOSE($C29,$C$3,$C$4))-MAX(BO29,CHOOSE($C29,$B$3,$B$4))-CHOOSE($C29,$F$3,$F$4),BP29-BO29-CHOOSE($C29,$F$3,$F$4)))) -> 0.40069444 | BS29: =IF(OR(BV29="VACACIONES",BV29="FALTA",BV29="LICENCIA",BO29="",BP29="",WEEKDAY($BO$17,2)>5),"", MAX(0,CHOOSE($C29,$H$3,$H$4)-(BR29*1440)) ) -> 0 | BT29: =IF(OR(BV29="VACACIONES",BV29="FALTA",BV29="LICENCIA",BO29="",BP29="",BQ29="NO",WEEKDAY($BO$17,2)>5),"",MAX(0,IF(BQ29="SI", (BR29*1440)-CHOOSE($C29,$H$3,$H$4) ))) | BU29: =IF(OR(BV29="VACACIONES",BV29="FALTA",BV29="LICENCIA",BO29="",BP29="",WEEKDAY($BO$17,2)<=5),"",IF(WEEKDAY($BO$17,2)>5,(BR29*1440))) | BX29: 0.30763889 | BY29: 0.75347222 | BZ29: NO | CA29: =IF(OR(CE29="VACACIONES",CE29="FALTA",CE29="LICENCIA",BX29="",BY29=""),"",IF(WEEKDAY($BX$17,2)>5,BY29-BX29,IF(BZ29="NO",MIN(BY29,CHOOSE($C29,$C$3,$C$4))-MAX(BX29,CHOOSE($C29,$B$3,$B$4))-CHOOSE($C29,$F$3,$F$4),BY29-BX29-CHOOSE($C29,$F$3,$F$4)))) -> 0.40069444 | CB29: =IF(OR(CE29="VACACIONES",CE29="FALTA",CE29="LICENCIA",BX29="",BY29="",WEEKDAY($BX$17,2)>5),"", MAX(0,CHOOSE($C29,$H$3,$H$4)-(CA29*1440)) ) -> 0 | CC29: =IF(OR(CE29="VACACIONES",CE29="FALTA",CE29="LICENCIA",BX29="",BY29="",BZ29="NO",WEEKDAY($BX$17,2)>5),"",MAX(0,IF(BZ29="SI", (CA29*1440)-CHOOSE($C29,$H$3,$H$4) ))) | CD29: =IF(OR(CE29="VACACIONES",CE29="FALTA",CE29="LICENCIA",BX29="",BY29="",WEEKDAY($BX$17,2)<=5),"",IF(WEEKDAY($BX$17,2)>5,(CA29*1440))) | CG29: 0.33402778 | CH29: 0.75902778 | CI29: NO | CJ29: =IF(OR(CN29="VACACIONES",CN29="FALTA",CN29="LICENCIA",CG29="",CH29=""),"",IF(WEEKDAY($CG$17,2)>5,CH29-CG29,IF(CI29="NO",MIN(CH29,CHOOSE($C29,$C$3,$C$4))-MAX(CG29,CHOOSE($C29,$B$3,$B$4))-CHOOSE($C29,$F$3,$F$4),CH29-CG29-CHOOSE($C29,$F$3,$F$4)))) -> 0.37430556 | CK29: =IF(OR(CN29="VACACIONES",CN29="FALTA",CN29="LICENCIA",CG29="",CH29="",WEEKDAY($CG$17,2)>5),"", MAX(0,CHOOSE($C29,$H$3,$H$4)-(CJ29*1440)) ) -> 38 | CL29: =IF(OR(CN29="VACACIONES",CN29="FALTA",CN29="LICENCIA",CG29="",CH29="",CI29="NO",WEEKDAY($CG$17,2)>5),"",MAX(0,IF(CI29="SI", (CJ29*1440)-CHOOSE($C29,$H$3,$H$4) ))) | CM29: =IF(OR(CN29="VACACIONES",CN29="FALTA",CN29="LICENCIA",CG29="",CH29="",WEEKDAY($CG$17,2)<=5),"",IF(WEEKDAY($CG$17,2)>5,(CJ29*1440))) | CP29: 0.27083333 | CQ29: 0.75347222 | CR29: NO | CS29: =IF(OR(CW29="VACACIONES",CW29="FALTA",CW29="LICENCIA",CP29="",CQ29=""),"",IF(WEEKDAY($CP$17,2)>5,CQ29-CP29,IF(CR29="NO",MIN(CQ29,CHOOSE($C29,$C$3,$C$4))-MAX(CP29,CHOOSE($C29,$B$3,$B$4))-CHOOSE($C29,$F$3,$F$4),CQ29-CP29-CHOOSE($C29,$F$3,$F$4)))) -> 0.40069444 | CT29: =IF(OR(CW29="VACACIONES",CW29="FALTA",CW29="LICENCIA",CP29="",CQ29="",WEEKDAY($CP$17,2)>5),"", MAX(0,CHOOSE($C29,$H$3,$H$4)-(CS29*1440)) ) -> 0 | CU29: =IF(OR(CW29="VACACIONES",CW29="FALTA",CW29="LICENCIA",CP29="",CQ29="",CR29="NO",WEEKDAY($CP$17,2)>5),"",MAX(0,IF(CR29="SI", (CS29*1440)-CHOOSE($C29,$H$3,$H$4) ))) | CV29: =IF(OR(CW29="VACACIONES",CW29="FALTA",CW29="LICENCIA",CP29="",CQ29="",WEEKDAY($CP$17,2)<=5),"",IF(WEEKDAY($CP$17,2)>5,(CS29*1440))) | CY29: 0.31319444 | CZ29: 0.75972222 | DA29: NO | DB29: =IF(OR(DF29="VACACIONES",DF29="FALTA",DF29="LICENCIA",CY29="",CZ29=""),"",IF(WEEKDAY($CY$17,2)>5,CZ29-CY29,IF(DA29="NO",MIN(CZ29,CHOOSE($C29,$C$3,$C$4))-MAX(CY29,CHOOSE($C29,$B$3,$B$4))-CHOOSE($C29,$F$3,$F$4),CZ29-CY29-CHOOSE($C29,$F$3,$F$4)))) -> 0.39513889 | DC29: =IF(OR(DF29="VACACIONES",DF29="FALTA",DF29="LICENCIA",CY29="",CZ29="",WEEKDAY($CY$17,2)>5),"", MAX(0,CHOOSE($C29,$H$3,$H$4)-(DB29*1440)) ) -> 8 | DD29: =IF(OR(DF29="VACACIONES",DF29="FALTA",DF29="LICENCIA",CY29="",CZ29="",DA29="NO",WEEKDAY($CY$17,2)>5),"",MAX(0,IF(DA29="SI", (DB29*1440)-CHOOSE($C29,$H$3,$H$4) ))) | DE29: =IF(OR(DF29="VACACIONES",DF29="FALTA",DF29="LICENCIA",CY29="",CZ29="",WEEKDAY($CY$17,2)<=5),"",IF(WEEKDAY($CY$17,2)>5,(DB29*1440))) | DK29: =IF(OR(DO29="VACACIONES",DO29="FALTA",DO29="LICENCIA",DH29="",DI29=""),"",IF(WEEKDAY($DH$17,2)>5,DI29-DH29,IF(DJ29="NO",MIN(DI29,CHOOSE($C29,$C$3,$C$4))-MAX(DH29,CHOOSE($C29,$B$3,$B$4))-CHOOSE($C29,$F$3,$F$4),DI29-DH29-CHOOSE($C29,$F$3,$F$4)))) | DL29: =IF(OR(DO29="VACACIONES",DO29="FALTA",DO29="LICENCIA",DH29="",DI29="",WEEKDAY($DH$17,2)>5),"", MAX(0,CHOOSE($C29,$H$3,$H$4)-(DK29*1440)) ) | DM29: =IF(OR(DO29="VACACIONES",DO29="FALTA",DO29="LICENCIA",DH29="",DI29="",DJ29="NO",WEEKDAY($DH$17,2)>5),"",MAX(0,IF(DJ29="SI", (DK29*1440)-CHOOSE($C29,$H$3,$H$4) ))) | DN29: =IF(OR(DO29="VACACIONES",DO29="FALTA",DO29="LICENCIA",DH29="",DI29="",WEEKDAY($DH$17,2)<=5),"",IF(WEEKDAY($DH$17,2)>5,(DK29*1440))) | DT29: =IF(OR(DX29="VACACIONES",DX29="FALTA",DX29="LICENCIA",DQ29="",DR29=""),"",IF(WEEKDAY($DQ$17,2)>5,DR29-DR29,IF(DS29="NO",MIN(DR29,CHOOSE($C29,$C$3,$C$4))-MAX(DQ29,CHOOSE($C29,$B$3,$B$4))-CHOOSE($C29,$F$3,$F$4),DR29-DQ29-CHOOSE($C29,$F$3,$F$4)))) | DU29: =IF(OR(DX29="VACACIONES",DX29="FALTA",DX29="LICENCIA",DQ29="",DR29="",WEEKDAY($DQ$17,2)>5),"", MAX(0,CHOOSE($C29,$H$3,$H$4)-(DT29*1440)) ) | DV29: =IF(OR(DX29="VACACIONES",DX29="FALTA",DX29="LICENCIA",DQ29="",DR29="",DS29="NO",WEEKDAY($DQ$17,2)>5),"",MAX(0,IF(DS29="SI", (DT29*1440)-CHOOSE($C29,$H$3,$H$4) ))) | DW29: =IF(OR(DX29="VACACIONES",DX29="FALTA",DX29="LICENCIA",DQ29="",DR29="",WEEKDAY($DQ$17,2)<=5),"",IF(WEEKDAY($DQ$17,2)>5,(DT29*1440))) | DZ29: 0.30763889 | EA29: 0.75972222 | EB29: NO | EC29: =IF(OR(EG29="VACACIONES",EG29="FALTA",EG29="LICENCIA",DZ29="",EA29=""),"",IF(WEEKDAY($CY$17,2)>5,EA29-DZ29,IF(EB29="NO",MIN(EA29,CHOOSE($C29,$C$3,$C$4))-MAX(DZ29,CHOOSE($C29,$B$3,$B$4))-CHOOSE($C29,$F$3,$F$4),EA29-DZ29-CHOOSE($C29,$F$3,$F$4)))) -> 0.40069444 | ED29: =IF(OR(EG29="VACACIONES",EG29="FALTA",EG29="LICENCIA",DZ29="",EA29="",WEEKDAY($CY$17,2)>5),"", MAX(0,CHOOSE($C29,$H$3,$H$4)-(EC29*1440)) ) -> 0 | EE29: =IF(OR(EG29="VACACIONES",EG29="FALTA",EG29="LICENCIA",DZ29="",EA29="",EB29="NO",WEEKDAY($CY$17,2)>5),"",MAX(0,IF(EB29="SI", (EC29*1440)-CHOOSE($C29,$H$3,$H$4) ))) | EF29: =IF(OR(EG29="VACACIONES",EG29="FALTA",EG29="LICENCIA",DZ29="",EA29="",WEEKDAY($CY$17,2)<=5),"",IF(WEEKDAY($CY$17,2)>5,(EC29*1440))) | EK29: =SUM(H29,Q29,Z29,AI29,AR29,BA29,BJ29,BS29,CB29,CK29,CT29,DC29,DL29,DU29,ED29) -> 55 | EL29: =SUM(I29,J29,R29,S29,AA29,AB29,AJ29,AK29,AS29,AT29,BB29,BC29,BK29,BL29,BT29,BU29,CC29,CD29,CL29,CM29,CU29,CV29,DD29,DE29,DM29,DN29,DV29,DW29,EE29,EF29) -> 70 | EM29: =COUNTIF(I29,">0")+COUNTIF(J29,">0")+COUNTIF(R29,">0")+COUNTIF(S29,">0")++COUNTIF(AA29,">0")+COUNTIF(AB29,">0")+COUNTIF(AJ29,">0")+COUNTIF(AK29,">0")+COUNTIF(AS29,">0")+COUNTIF(AT29,">0")+COUNTIF(BB29,">0")+COUNTIF(BC29,">0")+COUNTIF(BK29,">0")+COUNTIF(BL29,">0")+COUNTIF(BT29,">0")+COUNTIF(BU29,">0")+COUNTIF(CC29,">0")+COUNTIF(CD29,">0")+COUNTIF(CL29,">0")+COUNTIF(CM29,">0")+COUNTIF(CU29,">0")+COUNTIF(CV29,">0")+COUNTIF(DD29,">0")+COUNTIF(DE29,">0")+COUNTIF(DM29,">0")+COUNTIF(DN29,">0")+COUNTIF(DV29,">0")+COUNTIF(DW29,">0")+COUNTIF(EE29,">0")+COUNTIF(EF29,">0") -> 1 | EN29: =COUNTIF(D29:EG29,"FALTA") -> 0 | EO29: =15-EN29 -> 15 | EP29: =COUNTIF(D29:EG29,"TRABAJO SABADO") -> 0 | EQ29: =COUNTIF(D29:EG29,"TRABAJO DOMINGO")+COUNTIF(D29:EG29,"TRABAJO FERIADO")+(COUNTIF(D29:EG29,"TRABAJO 1RO MAYO")*2)+((COUNTIF(D31:EG31,"TRABAJO 1RO MAYO EN SU DIA LIBRE")*2)*2) -> 0 | ER29: =COUNTIF(D29:EG29,"VACACIONES") -> 0 | ES29: =COUNTIF(D29:EG29,"LICENCIA") -> 0
A30: =A29+1 -> #VALUE! | B30: ='1RA QUINCENA JUNIO 26'!B21 -> SEVERICHE CARLOS ANGELICA JESUS | C30: 2 | D30: 0.33333333 | E30: 0.75 | F30: NO | G30: =IF(OR(K30="VACACIONES",K30="FALTA",K30="LICENCIA",D30="",E30=""),"",IF(WEEKDAY($D$17,2)>5,E30-D30,IF(F30="NO",MIN(E30,CHOOSE($C30,$C$3,$C$4))-MAX(D30,CHOOSE($C30,$B$3,$B$4))-CHOOSE($C30,$F$3,$F$4),E30-D30-CHOOSE($C30,$F$3,$F$4)))) -> 0.375 | H30: =IF(OR(K30="VACACIONES",K30="FALTA",K30="LICENCIA",D30="",E30="",WEEKDAY($D$17,2)>5),"", MAX(0,CHOOSE($C30,$H$3,$H$4)-(G30*1440)) ) -> 0 | I30: =IF(OR(K30="VACACIONES",K30="FALTA",K30="LICENCIA",D30="",E30="",F30="NO",WEEKDAY($D$17,2)>5),"",MAX(0,IF(F30="SI", (G30*1440)-CHOOSE($C30,$H$3,$H$4) ))) | J30: =IF(OR(K30="VACACIONES",K30="FALTA",K30="LICENCIA",D30="",E30="",WEEKDAY($D$17,2)<=5),"",IF(WEEKDAY($D$17,2)>5,(G30*1440))) | M30: 0.33333333 | N30: 0.75 | O30: NO | P30: =IF(OR(T30="VACACIONES",T30="FALTA",T30="LICENCIA",M30="",N30=""),"",IF(WEEKDAY($M$17,2)>5,N30-M30,IF(O30="NO",MIN(N30,CHOOSE($C30,$C$3,$C$4))-MAX(M30,CHOOSE($C30,$B$3,$B$4))-CHOOSE($C30,$F$3,$F$4),N30-M30-CHOOSE($C30,$F$3,$F$4)))) -> 0.375 | Q30: =IF(OR(T30="VACACIONES",T30="FALTA",T30="LICENCIA",M30="",N30="",WEEKDAY($M$17,2)>5),"", MAX(0,CHOOSE($C30,$H$3,$H$4)-(P30*1440)) ) -> 0 | R30: =IF(OR(T30="VACACIONES",T30="FALTA",T30="LICENCIA",M30="",N30="",O30="NO",WEEKDAY($M$17,2)>5),"",MAX(0,IF(O30="SI", (P30*1440)-CHOOSE($C30,$H$3,$H$4) ))) | S30: =IF(OR(T30="VACACIONES",T30="FALTA",T30="LICENCIA",M30="",N30="",WEEKDAY($M$17,2)<=5),"",IF(WEEKDAY($M$17,2)>5,(P30*1440))) | V30: 0.33333333 | W30: 0.75 | X30: NO | Y30: =IF(OR(AC30="VACACIONES",AC30="FALTA",AC30="LICENCIA",V30="",W30=""),"",IF(WEEKDAY($V$17,2)>5,W30-V30,IF(X30="NO",MIN(W30,CHOOSE($C30,$C$3,$C$4))-MAX(V30,CHOOSE($C30,$B$3,$B$4))-CHOOSE($C30,$F$3,$F$4),W30-V30-CHOOSE($C30,$F$3,$F$4)))) -> 0.375 | Z30: =IF(OR(AC30="VACACIONES",AC30="FALTA",AC30="LICENCIA",V30="",W30="",WEEKDAY($V$17,2)>5),"", MAX(0,CHOOSE($C30,$H$3,$H$4)-(Y30*1440)) ) -> 0 | AA30: =IF(OR(AC30="VACACIONES",AC30="FALTA",AC30="LICENCIA",V30="",W30="",X30="NO",WEEKDAY($V$17,2)>5),"",MAX(0,IF(X30="SI", (Y30*1440)-CHOOSE($C30,$H$3,$H$4) ))) | AB30: =IF(OR(AC30="VACACIONES",AC30="FALTA",AC30="LICENCIA",V30="",W30="",WEEKDAY($V$17,2)<=5),"",IF(WEEKDAY($V$17,2)>5,(Y30*1440))) | AE30: 0.33333333 | AF30: 0.75 | AG30: NO | AH30: =IF(OR(AL30="VACACIONES",AL30="FALTA",AL30="LICENCIA",AE30="",AF30=""),"",IF(WEEKDAY($AE$17,2)>5,AF30-AE30,IF(AG30="NO",MIN(AF30,CHOOSE($C30,$C$3,$C$4))-MAX(AE30,CHOOSE($C30,$B$3,$B$4))-CHOOSE($C30,$F$3,$F$4),AF30-AE30-CHOOSE($C30,$F$3,$F$4)))) -> 0.375 | AI30: =IF(OR(AL30="VACACIONES",AL30="FALTA",AL30="LICENCIA",AE30="",AF30="",WEEKDAY($AE$17,2)>5),"", MAX(0,CHOOSE($C30,$H$3,$H$4)-(AH30*1440)) ) -> 0 | AJ30: =IF(OR(AL30="VACACIONES",AL30="FALTA",AL30="LICENCIA",AE30="",AF30="",AG30="NO",WEEKDAY($AE$17,2)>5),"",MAX(0,IF(AG30="SI", (AH30*1440)-CHOOSE($C30,$H$3,$H$4) ))) | AK30: =IF(OR(AL30="VACACIONES",AL30="FALTA",AL30="LICENCIA",AE30="",AF30="",WEEKDAY($AE$17,2)<=5),"",IF(WEEKDAY($AE$17,2)>5,(AH30*1440))) | AN30: 0.33333333 | AO30: 0.75 | AP30: NO | AQ30: =IF(OR(AU30="VACACIONES",AU30="FALTA",AU30="LICENCIA",AN30="",AO30=""),"",IF(WEEKDAY($AN$17,2)>5,AO30-AN30,IF(AP30="NO",MIN(AO30,CHOOSE($C30,$C$3,$C$4))-MAX(AN30,CHOOSE($C30,$B$3,$B$4))-CHOOSE($C30,$F$3,$F$4),AO30-AN30-CHOOSE($C30,$F$3,$F$4)))) -> 0.375 | AR30: =IF(OR(AU30="VACACIONES",AU30="FALTA",AU30="LICENCIA",AN30="",AO30="",WEEKDAY($AN$17,2)>5),"", MAX(0,CHOOSE($C30,$H$3,$H$4)-(AQ30*1440)) ) -> 0 | AS30: =IF(OR(AU30="VACACIONES",AU30="FALTA",AU30="LICENCIA",AN30="",AO30="",AP30="NO",WEEKDAY($AN$17,2)>5),"",MAX(0,IF(AP30="SI", (AQ30*1440)-CHOOSE($C30,$H$3,$H$4) ))) | AT30: =IF(OR(AU30="VACACIONES",AU30="FALTA",AU30="LICENCIA",AN30="",AO30="",WEEKDAY($AN$17,2)<=5),"",IF(WEEKDAY($AN$17,2)>5,(AQ30*1440))) | AZ30: =IF(OR(BD30="VACACIONES",BD30="FALTA",BD30="LICENCIA",AW30="",AX30=""),"",IF(WEEKDAY($AW$17,2)>5,AX30-AW30,IF(AY30="NO",MIN(AX30,CHOOSE($C30,$C$3,$C$4))-MAX(AW30,CHOOSE($C30,$B$3,$B$4))-CHOOSE($C30,$F$3,$F$4),AX30-AW30-CHOOSE($C30,$F$3,$F$4)))) | BA30: =IF(OR(BD30="VACACIONES",BD30="FALTA",BD30="LICENCIA",AW30="",AX30="",WEEKDAY($AW$17,2)>5),"", MAX(0,CHOOSE($C30,$H$3,$H$4)-(AZ30*1440)) ) | BB30: =IF(OR(BD30="VACACIONES",BD30="FALTA",BD30="LICENCIA",AW30="",AX30="",AY30="NO",WEEKDAY($AW$17,2)>5),"",MAX(0,IF(AY30="SI", (AZ30*1440)-CHOOSE($C30,$H$3,$H$4) ))) | BC30: =IF(OR(BD30="VACACIONES",BD30="FALTA",BD30="LICENCIA",AW30="",AX30="",WEEKDAY($AW$17,2)<=5),"",IF(WEEKDAY($AW$17,2)>5,(AZ30*1440))) | BI30: =IF(OR(BM30="VACACIONES",BM30="FALTA",BM30="LICENCIA",BF30="",BG30=""),"",IF(WEEKDAY($BF$17,2)>5,BG30-BF30,IF(BH30="NO",MIN(BG30,CHOOSE($C30,$C$3,$C$4))-MAX(BF30,CHOOSE($C30,$B$3,$B$4))-CHOOSE($C30,$F$3,$F$4),BG30-BF30-CHOOSE($C30,$F$3,$F$4)))) | BJ30: =IF(OR(BM30="VACACIONES",BM30="FALTA",BM30="LICENCIA",BF30="",BG30="",WEEKDAY($BF$17,2)>5),"", MAX(0,CHOOSE($C30,$H$3,$H$4)-(BI30*1440)) ) | BK30: =IF(OR(BM30="VACACIONES",BM30="FALTA",BM30="LICENCIA",BF30="",BG30="",BH30="NO",WEEKDAY($BF$17,2)>5),"",MAX(0,IF(BH30="SI", (BI30*1440)-CHOOSE($C30,$H$3,$H$4) ))) | BL30: =IF(OR(BM30="VACACIONES",BM30="FALTA",BM30="LICENCIA",BF30="",BG30="",WEEKDAY($BF$17,2)<=5),"",IF(WEEKDAY($BF$17,2)>5,(BI30*1440))) | BO30: 0.33333333 | BP30: 0.75 | BQ30: NO | BR30: =IF(OR(BV30="VACACIONES",BV30="FALTA",BV30="LICENCIA",BO30="",BP30=""),"",IF(WEEKDAY($BO$17,2)>5,BP30-BO30,IF(BQ30="NO",MIN(BP30,CHOOSE($C30,$C$3,$C$4))-MAX(BO30,CHOOSE($C30,$B$3,$B$4))-CHOOSE($C30,$F$3,$F$4),BP30-BO30-CHOOSE($C30,$F$3,$F$4)))) -> 0.375 | BS30: =IF(OR(BV30="VACACIONES",BV30="FALTA",BV30="LICENCIA",BO30="",BP30="",WEEKDAY($BO$17,2)>5),"", MAX(0,CHOOSE($C30,$H$3,$H$4)-(BR30*1440)) ) -> 0 | BT30: =IF(OR(BV30="VACACIONES",BV30="FALTA",BV30="LICENCIA",BO30="",BP30="",BQ30="NO",WEEKDAY($BO$17,2)>5),"",MAX(0,IF(BQ30="SI", (BR30*1440)-CHOOSE($C30,$H$3,$H$4) ))) | BU30: =IF(OR(BV30="VACACIONES",BV30="FALTA",BV30="LICENCIA",BO30="",BP30="",WEEKDAY($BO$17,2)<=5),"",IF(WEEKDAY($BO$17,2)>5,(BR30*1440))) | BX30: 0.33333333 | BY30: 0.75 | BZ30: NO | CA30: =IF(OR(CE30="VACACIONES",CE30="FALTA",CE30="LICENCIA",BX30="",BY30=""),"",IF(WEEKDAY($BX$17,2)>5,BY30-BX30,IF(BZ30="NO",MIN(BY30,CHOOSE($C30,$C$3,$C$4))-MAX(BX30,CHOOSE($C30,$B$3,$B$4))-CHOOSE($C30,$F$3,$F$4),BY30-BX30-CHOOSE($C30,$F$3,$F$4)))) -> 0.375 | CB30: =IF(OR(CE30="VACACIONES",CE30="FALTA",CE30="LICENCIA",BX30="",BY30="",WEEKDAY($BX$17,2)>5),"", MAX(0,CHOOSE($C30,$H$3,$H$4)-(CA30*1440)) ) -> 0 | CC30: =IF(OR(CE30="VACACIONES",CE30="FALTA",CE30="LICENCIA",BX30="",BY30="",BZ30="NO",WEEKDAY($BX$17,2)>5),"",MAX(0,IF(BZ30="SI", (CA30*1440)-CHOOSE($C30,$H$3,$H$4) ))) | CD30: =IF(OR(CE30="VACACIONES",CE30="FALTA",CE30="LICENCIA",BX30="",BY30="",WEEKDAY($BX$17,2)<=5),"",IF(WEEKDAY($BX$17,2)>5,(CA30*1440))) | CG30: 0.33333333 | CH30: 0.75 | CI30: NO | CJ30: =IF(OR(CN30="VACACIONES",CN30="FALTA",CN30="LICENCIA",CG30="",CH30=""),"",IF(WEEKDAY($CG$17,2)>5,CH30-CG30,IF(CI30="NO",MIN(CH30,CHOOSE($C30,$C$3,$C$4))-MAX(CG30,CHOOSE($C30,$B$3,$B$4))-CHOOSE($C30,$F$3,$F$4),CH30-CG30-CHOOSE($C30,$F$3,$F$4)))) -> 0.375 | CK30: =IF(OR(CN30="VACACIONES",CN30="FALTA",CN30="LICENCIA",CG30="",CH30="",WEEKDAY($CG$17,2)>5),"", MAX(0,CHOOSE($C30,$H$3,$H$4)-(CJ30*1440)) ) -> 0 | CL30: =IF(OR(CN30="VACACIONES",CN30="FALTA",CN30="LICENCIA",CG30="",CH30="",CI30="NO",WEEKDAY($CG$17,2)>5),"",MAX(0,IF(CI30="SI", (CJ30*1440)-CHOOSE($C30,$H$3,$H$4) ))) | CM30: =IF(OR(CN30="VACACIONES",CN30="FALTA",CN30="LICENCIA",CG30="",CH30="",WEEKDAY($CG$17,2)<=5),"",IF(WEEKDAY($CG$17,2)>5,(CJ30*1440))) | CP30: 0.33333333 | CQ30: 0.75 | CR30: NO | CS30: =IF(OR(CW30="VACACIONES",CW30="FALTA",CW30="LICENCIA",CP30="",CQ30=""),"",IF(WEEKDAY($CP$17,2)>5,CQ30-CP30,IF(CR30="NO",MIN(CQ30,CHOOSE($C30,$C$3,$C$4))-MAX(CP30,CHOOSE($C30,$B$3,$B$4))-CHOOSE($C30,$F$3,$F$4),CQ30-CP30-CHOOSE($C30,$F$3,$F$4)))) -> 0.375 | CT30: =IF(OR(CW30="VACACIONES",CW30="FALTA",CW30="LICENCIA",CP30="",CQ30="",WEEKDAY($CP$17,2)>5),"", MAX(0,CHOOSE($C30,$H$3,$H$4)-(CS30*1440)) ) -> 0 | CU30: =IF(OR(CW30="VACACIONES",CW30="FALTA",CW30="LICENCIA",CP30="",CQ30="",CR30="NO",WEEKDAY($CP$17,2)>5),"",MAX(0,IF(CR30="SI", (CS30*1440)-CHOOSE($C30,$H$3,$H$4) ))) | CV30: =IF(OR(CW30="VACACIONES",CW30="FALTA",CW30="LICENCIA",CP30="",CQ30="",WEEKDAY($CP$17,2)<=5),"",IF(WEEKDAY($CP$17,2)>5,(CS30*1440))) | CY30: 0.33333333 | CZ30: 0.75 | DA30: NO | DB30: =IF(OR(DF30="VACACIONES",DF30="FALTA",DF30="LICENCIA",CY30="",CZ30=""),"",IF(WEEKDAY($CY$17,2)>5,CZ30-CY30,IF(DA30="NO",MIN(CZ30,CHOOSE($C30,$C$3,$C$4))-MAX(CY30,CHOOSE($C30,$B$3,$B$4))-CHOOSE($C30,$F$3,$F$4),CZ30-CY30-CHOOSE($C30,$F$3,$F$4)))) -> 0.375 | DC30: =IF(OR(DF30="VACACIONES",DF30="FALTA",DF30="LICENCIA",CY30="",CZ30="",WEEKDAY($CY$17,2)>5),"", MAX(0,CHOOSE($C30,$H$3,$H$4)-(DB30*1440)) ) -> 0 | DD30: =IF(OR(DF30="VACACIONES",DF30="FALTA",DF30="LICENCIA",CY30="",CZ30="",DA30="NO",WEEKDAY($CY$17,2)>5),"",MAX(0,IF(DA30="SI", (DB30*1440)-CHOOSE($C30,$H$3,$H$4) ))) | DE30: =IF(OR(DF30="VACACIONES",DF30="FALTA",DF30="LICENCIA",CY30="",CZ30="",WEEKDAY($CY$17,2)<=5),"",IF(WEEKDAY($CY$17,2)>5,(DB30*1440))) | DK30: =IF(OR(DO30="VACACIONES",DO30="FALTA",DO30="LICENCIA",DH30="",DI30=""),"",IF(WEEKDAY($DH$17,2)>5,DI30-DH30,IF(DJ30="NO",MIN(DI30,CHOOSE($C30,$C$3,$C$4))-MAX(DH30,CHOOSE($C30,$B$3,$B$4))-CHOOSE($C30,$F$3,$F$4),DI30-DH30-CHOOSE($C30,$F$3,$F$4)))) | DL30: =IF(OR(DO30="VACACIONES",DO30="FALTA",DO30="LICENCIA",DH30="",DI30="",WEEKDAY($DH$17,2)>5),"", MAX(0,CHOOSE($C30,$H$3,$H$4)-(DK30*1440)) ) | DM30: =IF(OR(DO30="VACACIONES",DO30="FALTA",DO30="LICENCIA",DH30="",DI30="",DJ30="NO",WEEKDAY($DH$17,2)>5),"",MAX(0,IF(DJ30="SI", (DK30*1440)-CHOOSE($C30,$H$3,$H$4) ))) | DN30: =IF(OR(DO30="VACACIONES",DO30="FALTA",DO30="LICENCIA",DH30="",DI30="",WEEKDAY($DH$17,2)<=5),"",IF(WEEKDAY($DH$17,2)>5,(DK30*1440))) | DT30: =IF(OR(DX30="VACACIONES",DX30="FALTA",DX30="LICENCIA",DQ30="",DR30=""),"",IF(WEEKDAY($DQ$17,2)>5,DR30-DR30,IF(DS30="NO",MIN(DR30,CHOOSE($C30,$C$3,$C$4))-MAX(DQ30,CHOOSE($C30,$B$3,$B$4))-CHOOSE($C30,$F$3,$F$4),DR30-DQ30-CHOOSE($C30,$F$3,$F$4)))) | DU30: =IF(OR(DX30="VACACIONES",DX30="FALTA",DX30="LICENCIA",DQ30="",DR30="",WEEKDAY($DQ$17,2)>5),"", MAX(0,CHOOSE($C30,$H$3,$H$4)-(DT30*1440)) ) | DV30: =IF(OR(DX30="VACACIONES",DX30="FALTA",DX30="LICENCIA",DQ30="",DR30="",DS30="NO",WEEKDAY($DQ$17,2)>5),"",MAX(0,IF(DS30="SI", (DT30*1440)-CHOOSE($C30,$H$3,$H$4) ))) | DW30: =IF(OR(DX30="VACACIONES",DX30="FALTA",DX30="LICENCIA",DQ30="",DR30="",WEEKDAY($DQ$17,2)<=5),"",IF(WEEKDAY($DQ$17,2)>5,(DT30*1440))) | DZ30: 0.33333333 | EA30: 0.75 | EB30: NO | EC30: =IF(OR(EG30="VACACIONES",EG30="FALTA",EG30="LICENCIA",DZ30="",EA30=""),"",IF(WEEKDAY($CY$17,2)>5,EA30-DZ30,IF(EB30="NO",MIN(EA30,CHOOSE($C30,$C$3,$C$4))-MAX(DZ30,CHOOSE($C30,$B$3,$B$4))-CHOOSE($C30,$F$3,$F$4),EA30-DZ30-CHOOSE($C30,$F$3,$F$4)))) -> 0.375 | ED30: =IF(OR(EG30="VACACIONES",EG30="FALTA",EG30="LICENCIA",DZ30="",EA30="",WEEKDAY($CY$17,2)>5),"", MAX(0,CHOOSE($C30,$H$3,$H$4)-(EC30*1440)) ) -> 0 | EE30: =IF(OR(EG30="VACACIONES",EG30="FALTA",EG30="LICENCIA",DZ30="",EA30="",EB30="NO",WEEKDAY($CY$17,2)>5),"",MAX(0,IF(EB30="SI", (EC30*1440)-CHOOSE($C30,$H$3,$H$4) ))) | EF30: =IF(OR(EG30="VACACIONES",EG30="FALTA",EG30="LICENCIA",DZ30="",EA30="",WEEKDAY($CY$17,2)<=5),"",IF(WEEKDAY($CY$17,2)>5,(EC30*1440))) | EK30: =SUM(H30,Q30,Z30,AI30,AR30,BA30,BJ30,BS30,CB30,CK30,CT30,DC30,DL30,DU30,ED30) -> 0 | EL30: =SUM(I30,J30,R30,S30,AA30,AB30,AJ30,AK30,AS30,AT30,BB30,BC30,BK30,BL30,BT30,BU30,CC30,CD30,CL30,CM30,CU30,CV30,DD30,DE30,DM30,DN30,DV30,DW30,EE30,EF30) -> 0 | EM30: =COUNTIF(I30,">0")+COUNTIF(J30,">0")+COUNTIF(R30,">0")+COUNTIF(S30,">0")++COUNTIF(AA30,">0")+COUNTIF(AB30,">0")+COUNTIF(AJ30,">0")+COUNTIF(AK30,">0")+COUNTIF(AS30,">0")+COUNTIF(AT30,">0")+COUNTIF(BB30,">0")+COUNTIF(BC30,">0")+COUNTIF(BK30,">0")+COUNTIF(BL30,">0")+COUNTIF(BT30,">0")+COUNTIF(BU30,">0")+COUNTIF(CC30,">0")+COUNTIF(CD30,">0")+COUNTIF(CL30,">0")+COUNTIF(CM30,">0")+COUNTIF(CU30,">0")+COUNTIF(CV30,">0")+COUNTIF(DD30,">0")+COUNTIF(DE30,">0")+COUNTIF(DM30,">0")+COUNTIF(DN30,">0")+COUNTIF(DV30,">0")+COUNTIF(DW30,">0")+COUNTIF(EE30,">0")+COUNTIF(EF30,">0") -> 0 | EN30: =COUNTIF(D30:EG30,"FALTA") -> 0 | EO30: =15-EN30 -> 15 | EP30: =COUNTIF(D30:EG30,"TRABAJO SABADO") -> 0 | EQ30: =COUNTIF(D30:EG30,"TRABAJO DOMINGO")+COUNTIF(D30:EG30,"TRABAJO FERIADO")+(COUNTIF(D30:EG30,"TRABAJO 1RO MAYO")*2)+((COUNTIF(D32:EG32,"TRABAJO 1RO MAYO EN SU DIA LIBRE")*2)*2) -> 0 | ER30: =COUNTIF(D30:EG30,"VACACIONES") -> 0 | ES30: =COUNTIF(D30:EG30,"LICENCIA") -> 0
A31: =A30+1 -> #VALUE! | B31: ='1RA QUINCENA JUNIO 26'!B22 -> TENORIO MARTINEZ DE CISNEROS RUTH LOURDES | C31: 1 | D31: 0.30763889 | E31: 0.75 | F31: NO | G31: =IF(OR(K31="VACACIONES",K31="FALTA",K31="LICENCIA",D31="",E31=""),"",IF(WEEKDAY($D$17,2)>5,E31-D31,IF(F31="NO",MIN(E31,CHOOSE($C31,$C$3,$C$4))-MAX(D31,CHOOSE($C31,$B$3,$B$4))-CHOOSE($C31,$F$3,$F$4),E31-D31-CHOOSE($C31,$F$3,$F$4)))) -> 0.40069444 | H31: =IF(OR(K31="VACACIONES",K31="FALTA",K31="LICENCIA",D31="",E31="",WEEKDAY($D$17,2)>5),"", MAX(0,CHOOSE($C31,$H$3,$H$4)-(G31*1440)) ) -> 0 | I31: =IF(OR(K31="VACACIONES",K31="FALTA",K31="LICENCIA",D31="",E31="",F31="NO",WEEKDAY($D$17,2)>5),"",MAX(0,IF(F31="SI", (G31*1440)-CHOOSE($C31,$H$3,$H$4) ))) | J31: =IF(OR(K31="VACACIONES",K31="FALTA",K31="LICENCIA",D31="",E31="",WEEKDAY($D$17,2)<=5),"",IF(WEEKDAY($D$17,2)>5,(G31*1440))) | M31: 0.30763889 | N31: 0.75 | O31: NO | P31: =IF(OR(T31="VACACIONES",T31="FALTA",T31="LICENCIA",M31="",N31=""),"",IF(WEEKDAY($M$17,2)>5,N31-M31,IF(O31="NO",MIN(N31,CHOOSE($C31,$C$3,$C$4))-MAX(M31,CHOOSE($C31,$B$3,$B$4))-CHOOSE($C31,$F$3,$F$4),N31-M31-CHOOSE($C31,$F$3,$F$4)))) -> 0.40069444 | Q31: =IF(OR(T31="VACACIONES",T31="FALTA",T31="LICENCIA",M31="",N31="",WEEKDAY($M$17,2)>5),"", MAX(0,CHOOSE($C31,$H$3,$H$4)-(P31*1440)) ) -> 0 | R31: =IF(OR(T31="VACACIONES",T31="FALTA",T31="LICENCIA",M31="",N31="",O31="NO",WEEKDAY($M$17,2)>5),"",MAX(0,IF(O31="SI", (P31*1440)-CHOOSE($C31,$H$3,$H$4) ))) | S31: =IF(OR(T31="VACACIONES",T31="FALTA",T31="LICENCIA",M31="",N31="",WEEKDAY($M$17,2)<=5),"",IF(WEEKDAY($M$17,2)>5,(P31*1440))) | V31: 0.30763889 | W31: 0.75 | X31: NO | Y31: =IF(OR(AC31="VACACIONES",AC31="FALTA",AC31="LICENCIA",V31="",W31=""),"",IF(WEEKDAY($V$17,2)>5,W31-V31,IF(X31="NO",MIN(W31,CHOOSE($C31,$C$3,$C$4))-MAX(V31,CHOOSE($C31,$B$3,$B$4))-CHOOSE($C31,$F$3,$F$4),W31-V31-CHOOSE($C31,$F$3,$F$4)))) -> 0.40069444 | Z31: =IF(OR(AC31="VACACIONES",AC31="FALTA",AC31="LICENCIA",V31="",W31="",WEEKDAY($V$17,2)>5),"", MAX(0,CHOOSE($C31,$H$3,$H$4)-(Y31*1440)) ) -> 0 | AA31: =IF(OR(AC31="VACACIONES",AC31="FALTA",AC31="LICENCIA",V31="",W31="",X31="NO",WEEKDAY($V$17,2)>5),"",MAX(0,IF(X31="SI", (Y31*1440)-CHOOSE($C31,$H$3,$H$4) ))) | AB31: =IF(OR(AC31="VACACIONES",AC31="FALTA",AC31="LICENCIA",V31="",W31="",WEEKDAY($V$17,2)<=5),"",IF(WEEKDAY($V$17,2)>5,(Y31*1440))) | AE31: 0.30763889 | AF31: 0.75 | AG31: NO | AH31: =IF(OR(AL31="VACACIONES",AL31="FALTA",AL31="LICENCIA",AE31="",AF31=""),"",IF(WEEKDAY($AE$17,2)>5,AF31-AE31,IF(AG31="NO",MIN(AF31,CHOOSE($C31,$C$3,$C$4))-MAX(AE31,CHOOSE($C31,$B$3,$B$4))-CHOOSE($C31,$F$3,$F$4),AF31-AE31-CHOOSE($C31,$F$3,$F$4)))) -> 0.40069444 | AI31: =IF(OR(AL31="VACACIONES",AL31="FALTA",AL31="LICENCIA",AE31="",AF31="",WEEKDAY($AE$17,2)>5),"", MAX(0,CHOOSE($C31,$H$3,$H$4)-(AH31*1440)) ) -> 0 | AJ31: =IF(OR(AL31="VACACIONES",AL31="FALTA",AL31="LICENCIA",AE31="",AF31="",AG31="NO",WEEKDAY($AE$17,2)>5),"",MAX(0,IF(AG31="SI", (AH31*1440)-CHOOSE($C31,$H$3,$H$4) ))) | AK31: =IF(OR(AL31="VACACIONES",AL31="FALTA",AL31="LICENCIA",AE31="",AF31="",WEEKDAY($AE$17,2)<=5),"",IF(WEEKDAY($AE$17,2)>5,(AH31*1440))) | AN31: 0.30763889 | AO31: 0.75 | AP31: NO | AQ31: =IF(OR(AU31="VACACIONES",AU31="FALTA",AU31="LICENCIA",AN31="",AO31=""),"",IF(WEEKDAY($AN$17,2)>5,AO31-AN31,IF(AP31="NO",MIN(AO31,CHOOSE($C31,$C$3,$C$4))-MAX(AN31,CHOOSE($C31,$B$3,$B$4))-CHOOSE($C31,$F$3,$F$4),AO31-AN31-CHOOSE($C31,$F$3,$F$4)))) -> 0.40069444 | AR31: =IF(OR(AU31="VACACIONES",AU31="FALTA",AU31="LICENCIA",AN31="",AO31="",WEEKDAY($AN$17,2)>5),"", MAX(0,CHOOSE($C31,$H$3,$H$4)-(AQ31*1440)) ) -> 0 | AS31: =IF(OR(AU31="VACACIONES",AU31="FALTA",AU31="LICENCIA",AN31="",AO31="",AP31="NO",WEEKDAY($AN$17,2)>5),"",MAX(0,IF(AP31="SI", (AQ31*1440)-CHOOSE($C31,$H$3,$H$4) ))) | AT31: =IF(OR(AU31="VACACIONES",AU31="FALTA",AU31="LICENCIA",AN31="",AO31="",WEEKDAY($AN$17,2)<=5),"",IF(WEEKDAY($AN$17,2)>5,(AQ31*1440))) | AZ31: =IF(OR(BD31="VACACIONES",BD31="FALTA",BD31="LICENCIA",AW31="",AX31=""),"",IF(WEEKDAY($AW$17,2)>5,AX31-AW31,IF(AY31="NO",MIN(AX31,CHOOSE($C31,$C$3,$C$4))-MAX(AW31,CHOOSE($C31,$B$3,$B$4))-CHOOSE($C31,$F$3,$F$4),AX31-AW31-CHOOSE($C31,$F$3,$F$4)))) | BA31: =IF(OR(BD31="VACACIONES",BD31="FALTA",BD31="LICENCIA",AW31="",AX31="",WEEKDAY($AW$17,2)>5),"", MAX(0,CHOOSE($C31,$H$3,$H$4)-(AZ31*1440)) ) | BB31: =IF(OR(BD31="VACACIONES",BD31="FALTA",BD31="LICENCIA",AW31="",AX31="",AY31="NO",WEEKDAY($AW$17,2)>5),"",MAX(0,IF(AY31="SI", (AZ31*1440)-CHOOSE($C31,$H$3,$H$4) ))) | BC31: =IF(OR(BD31="VACACIONES",BD31="FALTA",BD31="LICENCIA",AW31="",AX31="",WEEKDAY($AW$17,2)<=5),"",IF(WEEKDAY($AW$17,2)>5,(AZ31*1440))) | BI31: =IF(OR(BM31="VACACIONES",BM31="FALTA",BM31="LICENCIA",BF31="",BG31=""),"",IF(WEEKDAY($BF$17,2)>5,BG31-BF31,IF(BH31="NO",MIN(BG31,CHOOSE($C31,$C$3,$C$4))-MAX(BF31,CHOOSE($C31,$B$3,$B$4))-CHOOSE($C31,$F$3,$F$4),BG31-BF31-CHOOSE($C31,$F$3,$F$4)))) | BJ31: =IF(OR(BM31="VACACIONES",BM31="FALTA",BM31="LICENCIA",BF31="",BG31="",WEEKDAY($BF$17,2)>5),"", MAX(0,CHOOSE($C31,$H$3,$H$4)-(BI31*1440)) ) | BK31: =IF(OR(BM31="VACACIONES",BM31="FALTA",BM31="LICENCIA",BF31="",BG31="",BH31="NO",WEEKDAY($BF$17,2)>5),"",MAX(0,IF(BH31="SI", (BI31*1440)-CHOOSE($C31,$H$3,$H$4) ))) | BL31: =IF(OR(BM31="VACACIONES",BM31="FALTA",BM31="LICENCIA",BF31="",BG31="",WEEKDAY($BF$17,2)<=5),"",IF(WEEKDAY($BF$17,2)>5,(BI31*1440))) | BO31: 0.30763889 | BP31: 0.75 | BQ31: NO | BR31: =IF(OR(BV31="VACACIONES",BV31="FALTA",BV31="LICENCIA",BO31="",BP31=""),"",IF(WEEKDAY($BO$17,2)>5,BP31-BO31,IF(BQ31="NO",MIN(BP31,CHOOSE($C31,$C$3,$C$4))-MAX(BO31,CHOOSE($C31,$B$3,$B$4))-CHOOSE($C31,$F$3,$F$4),BP31-BO31-CHOOSE($C31,$F$3,$F$4)))) -> 0.40069444 | BS31: =IF(OR(BV31="VACACIONES",BV31="FALTA",BV31="LICENCIA",BO31="",BP31="",WEEKDAY($BO$17,2)>5),"", MAX(0,CHOOSE($C31,$H$3,$H$4)-(BR31*1440)) ) -> 0 | BT31: =IF(OR(BV31="VACACIONES",BV31="FALTA",BV31="LICENCIA",BO31="",BP31="",BQ31="NO",WEEKDAY($BO$17,2)>5),"",MAX(0,IF(BQ31="SI", (BR31*1440)-CHOOSE($C31,$H$3,$H$4) ))) | BU31: =IF(OR(BV31="VACACIONES",BV31="FALTA",BV31="LICENCIA",BO31="",BP31="",WEEKDAY($BO$17,2)<=5),"",IF(WEEKDAY($BO$17,2)>5,(BR31*1440))) | BX31: 0.30763889 | BY31: 0.75 | BZ31: NO | CA31: =IF(OR(CE31="VACACIONES",CE31="FALTA",CE31="LICENCIA",BX31="",BY31=""),"",IF(WEEKDAY($BX$17,2)>5,BY31-BX31,IF(BZ31="NO",MIN(BY31,CHOOSE($C31,$C$3,$C$4))-MAX(BX31,CHOOSE($C31,$B$3,$B$4))-CHOOSE($C31,$F$3,$F$4),BY31-BX31-CHOOSE($C31,$F$3,$F$4)))) -> 0.40069444 | CB31: =IF(OR(CE31="VACACIONES",CE31="FALTA",CE31="LICENCIA",BX31="",BY31="",WEEKDAY($BX$17,2)>5),"", MAX(0,CHOOSE($C31,$H$3,$H$4)-(CA31*1440)) ) -> 0 | CC31: =IF(OR(CE31="VACACIONES",CE31="FALTA",CE31="LICENCIA",BX31="",BY31="",BZ31="NO",WEEKDAY($BX$17,2)>5),"",MAX(0,IF(BZ31="SI", (CA31*1440)-CHOOSE($C31,$H$3,$H$4) ))) | CD31: =IF(OR(CE31="VACACIONES",CE31="FALTA",CE31="LICENCIA",BX31="",BY31="",WEEKDAY($BX$17,2)<=5),"",IF(WEEKDAY($BX$17,2)>5,(CA31*1440))) | CG31: 0.30763889 | CH31: 0.75 | CI31: NO | CJ31: =IF(OR(CN31="VACACIONES",CN31="FALTA",CN31="LICENCIA",CG31="",CH31=""),"",IF(WEEKDAY($CG$17,2)>5,CH31-CG31,IF(CI31="NO",MIN(CH31,CHOOSE($C31,$C$3,$C$4))-MAX(CG31,CHOOSE($C31,$B$3,$B$4))-CHOOSE($C31,$F$3,$F$4),CH31-CG31-CHOOSE($C31,$F$3,$F$4)))) -> 0.40069444 | CK31: =IF(OR(CN31="VACACIONES",CN31="FALTA",CN31="LICENCIA",CG31="",CH31="",WEEKDAY($CG$17,2)>5),"", MAX(0,CHOOSE($C31,$H$3,$H$4)-(CJ31*1440)) ) -> 0 | CL31: =IF(OR(CN31="VACACIONES",CN31="FALTA",CN31="LICENCIA",CG31="",CH31="",CI31="NO",WEEKDAY($CG$17,2)>5),"",MAX(0,IF(CI31="SI", (CJ31*1440)-CHOOSE($C31,$H$3,$H$4) ))) | CM31: =IF(OR(CN31="VACACIONES",CN31="FALTA",CN31="LICENCIA",CG31="",CH31="",WEEKDAY($CG$17,2)<=5),"",IF(WEEKDAY($CG$17,2)>5,(CJ31*1440))) | CP31: 0.30763889 | CQ31: 0.75 | CR31: NO | CS31: =IF(OR(CW31="VACACIONES",CW31="FALTA",CW31="LICENCIA",CP31="",CQ31=""),"",IF(WEEKDAY($CP$17,2)>5,CQ31-CP31,IF(CR31="NO",MIN(CQ31,CHOOSE($C31,$C$3,$C$4))-MAX(CP31,CHOOSE($C31,$B$3,$B$4))-CHOOSE($C31,$F$3,$F$4),CQ31-CP31-CHOOSE($C31,$F$3,$F$4)))) -> 0.40069444 | CT31: =IF(OR(CW31="VACACIONES",CW31="FALTA",CW31="LICENCIA",CP31="",CQ31="",WEEKDAY($CP$17,2)>5),"", MAX(0,CHOOSE($C31,$H$3,$H$4)-(CS31*1440)) ) -> 0 | CU31: =IF(OR(CW31="VACACIONES",CW31="FALTA",CW31="LICENCIA",CP31="",CQ31="",CR31="NO",WEEKDAY($CP$17,2)>5),"",MAX(0,IF(CR31="SI", (CS31*1440)-CHOOSE($C31,$H$3,$H$4) ))) | CV31: =IF(OR(CW31="VACACIONES",CW31="FALTA",CW31="LICENCIA",CP31="",CQ31="",WEEKDAY($CP$17,2)<=5),"",IF(WEEKDAY($CP$17,2)>5,(CS31*1440))) | CY31: 0.30763889 | CZ31: 0.75 | DA31: NO | DB31: =IF(OR(DF31="VACACIONES",DF31="FALTA",DF31="LICENCIA",CY31="",CZ31=""),"",IF(WEEKDAY($CY$17,2)>5,CZ31-CY31,IF(DA31="NO",MIN(CZ31,CHOOSE($C31,$C$3,$C$4))-MAX(CY31,CHOOSE($C31,$B$3,$B$4))-CHOOSE($C31,$F$3,$F$4),CZ31-CY31-CHOOSE($C31,$F$3,$F$4)))) -> 0.40069444 | DC31: =IF(OR(DF31="VACACIONES",DF31="FALTA",DF31="LICENCIA",CY31="",CZ31="",WEEKDAY($CY$17,2)>5),"", MAX(0,CHOOSE($C31,$H$3,$H$4)-(DB31*1440)) ) -> 0 | DD31: =IF(OR(DF31="VACACIONES",DF31="FALTA",DF31="LICENCIA",CY31="",CZ31="",DA31="NO",WEEKDAY($CY$17,2)>5),"",MAX(0,IF(DA31="SI", (DB31*1440)-CHOOSE($C31,$H$3,$H$4) ))) | DE31: =IF(OR(DF31="VACACIONES",DF31="FALTA",DF31="LICENCIA",CY31="",CZ31="",WEEKDAY($CY$17,2)<=5),"",IF(WEEKDAY($CY$17,2)>5,(DB31*1440))) | DK31: =IF(OR(DO31="VACACIONES",DO31="FALTA",DO31="LICENCIA",DH31="",DI31=""),"",IF(WEEKDAY($DH$17,2)>5,DI31-DH31,IF(DJ31="NO",MIN(DI31,CHOOSE($C31,$C$3,$C$4))-MAX(DH31,CHOOSE($C31,$B$3,$B$4))-CHOOSE($C31,$F$3,$F$4),DI31-DH31-CHOOSE($C31,$F$3,$F$4)))) | DL31: =IF(OR(DO31="VACACIONES",DO31="FALTA",DO31="LICENCIA",DH31="",DI31="",WEEKDAY($DH$17,2)>5),"", MAX(0,CHOOSE($C31,$H$3,$H$4)-(DK31*1440)) ) | DM31: =IF(OR(DO31="VACACIONES",DO31="FALTA",DO31="LICENCIA",DH31="",DI31="",DJ31="NO",WEEKDAY($DH$17,2)>5),"",MAX(0,IF(DJ31="SI", (DK31*1440)-CHOOSE($C31,$H$3,$H$4) ))) | DN31: =IF(OR(DO31="VACACIONES",DO31="FALTA",DO31="LICENCIA",DH31="",DI31="",WEEKDAY($DH$17,2)<=5),"",IF(WEEKDAY($DH$17,2)>5,(DK31*1440))) | DT31: =IF(OR(DX31="VACACIONES",DX31="FALTA",DX31="LICENCIA",DQ31="",DR31=""),"",IF(WEEKDAY($DQ$17,2)>5,DR31-DR31,IF(DS31="NO",MIN(DR31,CHOOSE($C31,$C$3,$C$4))-MAX(DQ31,CHOOSE($C31,$B$3,$B$4))-CHOOSE($C31,$F$3,$F$4),DR31-DQ31-CHOOSE($C31,$F$3,$F$4)))) | DU31: =IF(OR(DX31="VACACIONES",DX31="FALTA",DX31="LICENCIA",DQ31="",DR31="",WEEKDAY($DQ$17,2)>5),"", MAX(0,CHOOSE($C31,$H$3,$H$4)-(DT31*1440)) ) | DV31: =IF(OR(DX31="VACACIONES",DX31="FALTA",DX31="LICENCIA",DQ31="",DR31="",DS31="NO",WEEKDAY($DQ$17,2)>5),"",MAX(0,IF(DS31="SI", (DT31*1440)-CHOOSE($C31,$H$3,$H$4) ))) | DW31: =IF(OR(DX31="VACACIONES",DX31="FALTA",DX31="LICENCIA",DQ31="",DR31="",WEEKDAY($DQ$17,2)<=5),"",IF(WEEKDAY($DQ$17,2)>5,(DT31*1440))) | DZ31: 0.27083333 | EA31: 0.75 | EB31: NO | EC31: =IF(OR(EG31="VACACIONES",EG31="FALTA",EG31="LICENCIA",DZ31="",EA31=""),"",IF(WEEKDAY($CY$17,2)>5,EA31-DZ31,IF(EB31="NO",MIN(EA31,CHOOSE($C31,$C$3,$C$4))-MAX(DZ31,CHOOSE($C31,$B$3,$B$4))-CHOOSE($C31,$F$3,$F$4),EA31-DZ31-CHOOSE($C31,$F$3,$F$4)))) -> 0.40069444 | ED31: =IF(OR(EG31="VACACIONES",EG31="FALTA",EG31="LICENCIA",DZ31="",EA31="",WEEKDAY($CY$17,2)>5),"", MAX(0,CHOOSE($C31,$H$3,$H$4)-(EC31*1440)) ) -> 0 | EE31: =IF(OR(EG31="VACACIONES",EG31="FALTA",EG31="LICENCIA",DZ31="",EA31="",EB31="NO",WEEKDAY($CY$17,2)>5),"",MAX(0,IF(EB31="SI", (EC31*1440)-CHOOSE($C31,$H$3,$H$4) ))) | EF31: =IF(OR(EG31="VACACIONES",EG31="FALTA",EG31="LICENCIA",DZ31="",EA31="",WEEKDAY($CY$17,2)<=5),"",IF(WEEKDAY($CY$17,2)>5,(EC31*1440))) | EK31: =SUM(H31,Q31,Z31,AI31,AR31,BA31,BJ31,BS31,CB31,CK31,CT31,DC31,DL31,DU31,ED31) -> 0 | EL31: =SUM(I31,J31,R31,S31,AA31,AB31,AJ31,AK31,AS31,AT31,BB31,BC31,BK31,BL31,BT31,BU31,CC31,CD31,CL31,CM31,CU31,CV31,DD31,DE31,DM31,DN31,DV31,DW31,EE31,EF31) -> 0 | EM31: =COUNTIF(I31,">0")+COUNTIF(J31,">0")+COUNTIF(R31,">0")+COUNTIF(S31,">0")++COUNTIF(AA31,">0")+COUNTIF(AB31,">0")+COUNTIF(AJ31,">0")+COUNTIF(AK31,">0")+COUNTIF(AS31,">0")+COUNTIF(AT31,">0")+COUNTIF(BB31,">0")+COUNTIF(BC31,">0")+COUNTIF(BK31,">0")+COUNTIF(BL31,">0")+COUNTIF(BT31,">0")+COUNTIF(BU31,">0")+COUNTIF(CC31,">0")+COUNTIF(CD31,">0")+COUNTIF(CL31,">0")+COUNTIF(CM31,">0")+COUNTIF(CU31,">0")+COUNTIF(CV31,">0")+COUNTIF(DD31,">0")+COUNTIF(DE31,">0")+COUNTIF(DM31,">0")+COUNTIF(DN31,">0")+COUNTIF(DV31,">0")+COUNTIF(DW31,">0")+COUNTIF(EE31,">0")+COUNTIF(EF31,">0") -> 0 | EN31: =COUNTIF(D31:EG31,"FALTA") -> 0 | EO31: =15-EN31 -> 15 | EP31: =COUNTIF(D31:EG31,"TRABAJO SABADO") -> 0 | EQ31: =COUNTIF(D31:EG31,"TRABAJO DOMINGO")+COUNTIF(D31:EG31,"TRABAJO FERIADO")+(COUNTIF(D31:EG31,"TRABAJO 1RO MAYO")*2)+((COUNTIF(D33:EG33,"TRABAJO 1RO MAYO EN SU DIA LIBRE")*2)*2) -> 0 | ER31: =COUNTIF(D31:EG31,"VACACIONES") -> 0 | ES31: =COUNTIF(D31:EG31,"LICENCIA") -> 0
